{"decks": 192, "cards": 1435, "staples": 328, "pet": 436, "last_set": "Outlaws of Thunder Junction", "last_set_top_10": [{"occurrences": 3, "cardName": "High Noon"}, {"occurrences": 3, "cardName": "Aven Interrupter"}, {"occurrences": 2, "cardName": "Magda, the Hoardmaster"}, {"occurrences": 2, "cardName": "Final Showdown"}, {"occurrences": 1, "cardName": "Tinybones, the Pickpocket"}, {"occurrences": 1, "cardName": "Great Train Heist"}, {"occurrences": 1, "cardName": "Return the Favor"}, {"occurrences": 1, "cardName": "Annie Joins Up"}, {"occurrences": 1, "cardName": "Selvala, Eager Trailblazer"}]}