[{"occurrences": 1, "cardName": "Underworld Breach", "card_faces": [], "colorIdentity": "R", "colors": "R", "decklists": [{"commanders": "Atogatog", "decks": [{"name": "Toontown {CEDH}", "url": "https://www.moxfield.com/decks/vnV82CWvaUer1JhrL9GIgw", "commanders": [{"name": "Atogatog", "color_identity": ["B", "G", "R", "U", "W"]}]}], "colorIdentity": ["W", "U", "B", "R", "G"]}], "cmc": 2.0, "prices": {"usd": 27.5, "usd_foil": 49.22, "eur": 19.37, "eur_foil": 34.42, "ck": 29.99, "ck_foil": 49.99, "lastUpdatedAtUtc": "2024-07-22T10:49:15.082Z", "ck_buy": 17.5, "ck_buy_foil": 25.0, "csi": 23.99, "csi_foil": 39.99, "csi_buy": 13.0, "csi_buy_foil": 0.0, "ct": 22.31, "ct_foil": 49.79}, "reserved": false, "multiplePrintings": true, "lastPrint": "Mystery Booster 2", "multiverse_ids": [642848], "type": "Enchantment", "typeLine": "Enchantment", "power": "", "toughness": "", "isCommander": false, "isIn99": true, "percentageOfUse": 100.0, "percentageOfUseByIdentity": 0.01, "avgWinRate": 0.0, "avgDrawRate": 0.143}, {"occurrences": 1, "cardName": "Arcane Signet", "card_faces": [], "colorIdentity": "C", "colors": "C", "decklists": [{"commanders": "Atogatog", "decks": [{"name": "Toontown {CEDH}", "url": "https://www.moxfield.com/decks/vnV82CWvaUer1JhrL9GIgw", "commanders": [{"name": "Atogatog", "color_identity": ["B", "G", "R", "U", "W"]}]}], "colorIdentity": ["W", "U", "B", "R", "G"]}], "cmc": 2.0, "prices": {"usd": 0.23, "eur": 0.31, "ck": 0.99, "lastUpdatedAtUtc": "2024-07-22T10:49:15.082Z", "ck_buy": 0.15, "csi": 1.25, "csi_buy": 0.25, "ct": 0.55}, "reserved": false, "multiplePrintings": true, "lastPrint": "Bloomburrow Commander", "multiverse_ids": [0], "type": "Artifact", "typeLine": "Artifact", "power": "", "toughness": "", "isCommander": false, "isIn99": true, "percentageOfUse": 100.0, "percentageOfUseByIdentity": 100.0, "avgWinRate": 0.0, "avgDrawRate": 0.143}, {"occurrences": 1, "cardName": "Command Tower", "card_faces": [], "colorIdentity": "C", "colors": "C", "decklists": [{"commanders": "Atogatog", "decks": [{"name": "Toontown {CEDH}", "url": "https://www.moxfield.com/decks/vnV82CWvaUer1JhrL9GIgw", "commanders": [{"name": "Atogatog", "color_identity": ["B", "G", "R", "U", "W"]}]}], "colorIdentity": ["W", "U", "B", "R", "G"]}], "cmc": 0, "prices": {"usd": 0.15, "eur": 0.18, "tix": 0.05, "ck": 0.49, "lastUpdatedAtUtc": "2024-07-22T10:49:15.082Z", "ck_buy": 0.1, "csi": 0.49, "csi_buy": 0.02, "ct": 0.17}, "reserved": false, "multiplePrintings": true, "lastPrint": "Jurassic World Collection", "multiverse_ids": [640621], "type": "Land", "typeLine": "Land", "power": "", "toughness": "", "isCommander": false, "isIn99": true, "percentageOfUse": 100.0, "percentageOfUseByIdentity": 100.0, "avgWinRate": 0.0, "avgDrawRate": 0.143}, {"occurrences": 1, "cardName": "Demonic Tutor", "card_faces": [], "colorIdentity": "B", "colors": "B", "decklists": [{"commanders": "Atogatog", "decks": [{"name": "Toontown {CEDH}", "url": "https://www.moxfield.com/decks/vnV82CWvaUer1JhrL9GIgw", "commanders": [{"name": "Atogatog", "color_identity": ["B", "G", "R", "U", "W"]}]}], "colorIdentity": ["W", "U", "B", "R", "G"]}], "cmc": 2.0, "prices": {"usd": 104.76, "usd_foil": 274.5, "usd_etched": 163.44, "eur": 100.88, "eur_foil": 235.14, "tix": 7.36, "ck": 109.99, "ck_foil": 329.99, "ck_etched": 159.99, "lastUpdatedAtUtc": "2024-07-22T10:49:15.082Z", "ck_buy": 65.0, "ck_buy_foil": 198.0, "ck_buy_etched": 100.0, "ck_buy_qty": 5, "ck_buy_foil_qty": 5, "ck_buy_etched_qty": 5, "csi": 99.99, "csi_foil": 229.99, "csi_buy": 55.0, "csi_buy_foil": 130.0, "csi_buy_qty": 20, "csi_buy_foil_qty": 20}, "reserved": false, "multiplePrintings": true, "lastPrint": "Commander Masters", "multiverse_ids": [0], "type": "Sorcery", "typeLine": "Sorcery", "power": "", "toughness": "", "isCommander": false, "isIn99": true, "percentageOfUse": 100.0, "percentageOfUseByIdentity": 0.01, "avgWinRate": 0.0, "avgDrawRate": 0.143}, {"occurrences": 1, "cardName": "Dispel", "card_faces": [], "colorIdentity": "U", "colors": "U", "decklists": [{"commanders": "Atogatog", "decks": [{"name": "Toontown {CEDH}", "url": "https://www.moxfield.com/decks/vnV82CWvaUer1JhrL9GIgw", "commanders": [{"name": "Atogatog", "color_identity": ["B", "G", "R", "U", "W"]}]}], "colorIdentity": ["W", "U", "B", "R", "G"]}], "cmc": 1.0, "prices": {"usd": 0.26, "usd_foil": 7.7, "eur": 0.22, "eur_foil": 2.58, "tix": 0.03, "ck": 0.35, "ck_foil": 6.99, "lastUpdatedAtUtc": "2024-07-22T10:49:15.082Z", "ck_buy": 0.03, "ck_buy_foil": 3.5, "csi": 0.25, "csi_foil": 2.99, "csi_buy": 0.0, "csi_buy_foil": 1.0, "ct": 0.33, "ct_foil": 4.73}, "reserved": false, "multiplePrintings": true, "lastPrint": "Battle for Zendikar", "multiverse_ids": [253566], "type": "Instant", "typeLine": "Instant", "power": "", "toughness": "", "isCommander": false, "isIn99": true, "percentageOfUse": 100.0, "percentageOfUseByIdentity": 0.0, "avgWinRate": 0.0, "avgDrawRate": 0.143}, {"occurrences": 1, "cardName": "Lightning Greaves", "card_faces": [], "colorIdentity": "C", "colors": "C", "decklists": [{"commanders": "Atogatog", "decks": [{"name": "Toontown {CEDH}", "url": "https://www.moxfield.com/decks/vnV82CWvaUer1JhrL9GIgw", "commanders": [{"name": "Atogatog", "color_identity": ["B", "G", "R", "U", "W"]}]}], "colorIdentity": ["W", "U", "B", "R", "G"]}], "cmc": 2.0, "prices": {"usd_foil": 193.77, "eur_foil": 117.96, "tix": 0.75, "ck_foil": 229.99, "lastUpdatedAtUtc": "2024-07-22T10:49:15.082Z", "ck_buy_foil": 150.0, "ck_buy_foil_qty": 5, "csi_foil": 159.99, "csi_buy_foil": 90.0, "csi_buy_foil_qty": 20, "ct_foil": 123.27}, "reserved": false, "multiplePrintings": true, "lastPrint": "Mystery Booster 2", "multiverse_ids": [420601], "type": "Artifact", "typeLine": "Artifact — Equipment", "power": "", "toughness": "", "isCommander": false, "isIn99": true, "percentageOfUse": 100.0, "percentageOfUseByIdentity": 100.0, "avgWinRate": 0.0, "avgDrawRate": 0.143}, {"occurrences": 1, "cardName": "Lotus Petal", "card_faces": [], "colorIdentity": "C", "colors": "C", "decklists": [{"commanders": "Atogatog", "decks": [{"name": "Toontown {CEDH}", "url": "https://www.moxfield.com/decks/vnV82CWvaUer1JhrL9GIgw", "commanders": [{"name": "Atogatog", "color_identity": ["B", "G", "R", "U", "W"]}]}], "colorIdentity": ["W", "U", "B", "R", "G"]}], "cmc": 0, "prices": {"usd_etched": 14.38, "ck_etched": 19.99, "lastUpdatedAtUtc": "2024-07-22T10:49:15.082Z", "csi_foil": 17.99, "csi_buy_foil": 10.0, "ct_etched": 12.15}, "reserved": false, "multiplePrintings": true, "lastPrint": "Mystery Booster 2", "multiverse_ids": [0], "type": "Artifact", "typeLine": "Artifact", "power": "", "toughness": "", "isCommander": false, "isIn99": true, "percentageOfUse": 100.0, "percentageOfUseByIdentity": 100.0, "avgWinRate": 0.0, "avgDrawRate": 0.143}, {"occurrences": 1, "cardName": "Mana Crypt", "card_faces": [], "colorIdentity": "C", "colors": "C", "decklists": [{"commanders": "Atogatog", "decks": [{"name": "Toontown {CEDH}", "url": "https://www.moxfield.com/decks/vnV82CWvaUer1JhrL9GIgw", "commanders": [{"name": "Atogatog", "color_identity": ["B", "G", "R", "U", "W"]}]}], "colorIdentity": ["W", "U", "B", "R", "G"]}], "cmc": 0, "prices": {"usd": 185.61, "usd_foil": 225.39, "eur": 147.28, "eur_foil": 172.75, "tix": 12.59, "ck": 229.99, "ck_foil": 329.99, "lastUpdatedAtUtc": "2024-07-22T10:49:15.082Z", "ck_buy": 115.0, "ck_buy_foil": 165.0, "csi": 199.99, "csi_foil": 249.99, "csi_buy": 125.0, "csi_buy_foil": 130.0, "ct": 187.1, "ct_foil": 199.52}, "reserved": false, "multiplePrintings": true, "lastPrint": "Double Masters", "multiverse_ids": [489943], "type": "Artifact", "typeLine": "Artifact", "power": "", "toughness": "", "isCommander": false, "isIn99": true, "percentageOfUse": 100.0, "percentageOfUseByIdentity": 100.0, "avgWinRate": 0.0, "avgDrawRate": 0.143}, {"occurrences": 1, "cardName": "Martyr's Bond", "card_faces": [], "colorIdentity": "W", "colors": "W", "decklists": [{"commanders": "Atogatog", "decks": [{"name": "Toontown {CEDH}", "url": "https://www.moxfield.com/decks/vnV82CWvaUer1JhrL9GIgw", "commanders": [{"name": "Atogatog", "color_identity": ["B", "G", "R", "U", "W"]}]}], "colorIdentity": ["W", "U", "B", "R", "G"]}], "cmc": 6.0, "prices": {"usd": 0.42, "usd_foil": 1.03, "eur": 0.29, "eur_foil": 0.72, "ck": 0.59, "ck_foil": 1.49, "lastUpdatedAtUtc": "2024-07-22T10:49:15.082Z", "ck_buy": 0.08, "ck_buy_foil": 0.45, "csi": 0.49, "csi_foil": 0.99, "csi_buy": 0.1, "csi_buy_foil": 0.25, "ct": 0.22, "ct_foil": 0.69}, "reserved": false, "multiplePrintings": true, "lastPrint": "Signature Spellbook: Gideon", "multiverse_ids": [470540], "type": "Enchantment", "typeLine": "Enchantment", "power": "", "toughness": "", "isCommander": false, "isIn99": true, "percentageOfUse": 100.0, "percentageOfUseByIdentity": 0.01, "avgWinRate": 0.0, "avgDrawRate": 0.143}, {"occurrences": 1, "cardName": "Rhystic Study", "card_faces": [], "colorIdentity": "U", "colors": "U", "decklists": [{"commanders": "Atogatog", "decks": [{"name": "Toontown {CEDH}", "url": "https://www.moxfield.com/decks/vnV82CWvaUer1JhrL9GIgw", "commanders": [{"name": "Atogatog", "color_identity": ["B", "G", "R", "U", "W"]}]}], "colorIdentity": ["W", "U", "B", "R", "G"]}], "cmc": 3.0, "prices": {"usd": 88.83, "usd_foil": 260.16, "tix": 5.78, "ck": 109.99, "ck_foil": 329.99, "lastUpdatedAtUtc": "2024-07-22T10:49:15.082Z", "ck_buy": 70.0, "ck_buy_foil": 198.0, "csi": 89.99, "csi_foil": 199.99, "csi_buy": 50.0, "csi_buy_foil": 0.0, "ct": 90.34, "ct_foil": 265.15}, "reserved": false, "multiplePrintings": true, "lastPrint": "Jumpstart 2022", "multiverse_ids": [632396], "type": "Enchantment", "typeLine": "Enchantment", "power": "", "toughness": "", "isCommander": false, "isIn99": true, "percentageOfUse": 100.0, "percentageOfUseByIdentity": 0.0, "avgWinRate": 0.0, "avgDrawRate": 0.143}, {"occurrences": 1, "cardName": "Sol Ring", "card_faces": [], "colorIdentity": "C", "colors": "C", "decklists": [{"commanders": "Atogatog", "decks": [{"name": "Toontown {CEDH}", "url": "https://www.moxfield.com/decks/vnV82CWvaUer1JhrL9GIgw", "commanders": [{"name": "Atogatog", "color_identity": ["B", "G", "R", "U", "W"]}]}], "colorIdentity": ["W", "U", "B", "R", "G"]}], "cmc": 1.0, "prices": {"usd": 21.07, "usd_foil": 28.44, "ck": 25.99, "ck_foil": 39.99, "lastUpdatedAtUtc": "2024-07-22T10:49:15.082Z", "ck_buy": 15.0, "ck_buy_foil": 16.0, "csi": 24.99, "csi_foil": 39.99, "csi_buy": 13.0, "csi_buy_foil": 18.0, "ct": 20.6, "ct_foil": 20.02}, "reserved": false, "multiplePrintings": true, "lastPrint": "Bloomburrow Commander", "multiverse_ids": [654914], "type": "Artifact", "typeLine": "Artifact", "power": "", "toughness": "", "isCommander": false, "isIn99": true, "percentageOfUse": 100.0, "percentageOfUseByIdentity": 100.0, "avgWinRate": 0.0, "avgDrawRate": 0.143}, {"occurrences": 1, "cardName": "Snap", "card_faces": [], "colorIdentity": "U", "colors": "U", "decklists": [{"commanders": "Atogatog", "decks": [{"name": "Toontown {CEDH}", "url": "https://www.moxfield.com/decks/vnV82CWvaUer1JhrL9GIgw", "commanders": [{"name": "Atogatog", "color_identity": ["B", "G", "R", "U", "W"]}]}], "colorIdentity": ["W", "U", "B", "R", "G"]}], "cmc": 2.0, "prices": {"usd": 8.68, "usd_foil": 10.9, "ck": 10.99, "ck_foil": 13.99, "lastUpdatedAtUtc": "2024-07-22T10:49:15.082Z", "ck_buy": 6.4, "ck_buy_foil": 5.75, "csi": 9.99, "csi_foil": 11.99, "csi_buy": 4.0, "csi_buy_foil": 4.0, "ct": 12.25, "ct_foil": 12.25}, "reserved": false, "multiplePrintings": true, "lastPrint": "Wilds of Eldraine Commander", "multiverse_ids": [0], "type": "Instant", "typeLine": "Instant", "power": "", "toughness": "", "isCommander": false, "isIn99": true, "percentageOfUse": 100.0, "percentageOfUseByIdentity": 0.0, "avgWinRate": 0.0, "avgDrawRate": 0.143}, {"occurrences": 1, "cardName": "Swords to Plowshares", "card_faces": [], "colorIdentity": "W", "colors": "W", "decklists": [{"commanders": "Atogatog", "decks": [{"name": "Toontown {CEDH}", "url": "https://www.moxfield.com/decks/vnV82CWvaUer1JhrL9GIgw", "commanders": [{"name": "Atogatog", "color_identity": ["B", "G", "R", "U", "W"]}]}], "colorIdentity": ["W", "U", "B", "R", "G"]}], "cmc": 1.0, "prices": {"usd": 14.99, "lastUpdatedAtUtc": "2024-07-22T10:49:15.082Z", "csi": 0.0, "csi_foil": 0.0, "csi_buy": 0.0, "csi_buy_foil": 0.0, "csi_buy_qty": 0, "csi_buy_foil_qty": 0}, "reserved": false, "multiplePrintings": true, "lastPrint": "Bloomburrow Commander", "multiverse_ids": [0], "type": "Instant", "typeLine": "Instant", "power": "", "toughness": "", "isCommander": false, "isIn99": true, "percentageOfUse": 100.0, "percentageOfUseByIdentity": 0.01, "avgWinRate": 0.0, "avgDrawRate": 0.143}, {"occurrences": 1, "cardName": "Teferi's Protection", "card_faces": [], "colorIdentity": "W", "colors": "W", "decklists": [{"commanders": "Atogatog", "decks": [{"name": "Toontown {CEDH}", "url": "https://www.moxfield.com/decks/vnV82CWvaUer1JhrL9GIgw", "commanders": [{"name": "Atogatog", "color_identity": ["B", "G", "R", "U", "W"]}]}], "colorIdentity": ["W", "U", "B", "R", "G"]}], "cmc": 3.0, "prices": {"usd_foil": 27.06, "eur_foil": 21.0, "ck_foil": 32.99, "lastUpdatedAtUtc": "2021-09-20T08:05:43.488Z"}, "reserved": false, "multiplePrintings": true, "lastPrint": "Double Masters 2022", "multiverse_ids": [0], "type": "Instant", "typeLine": "Instant", "power": "", "toughness": "", "isCommander": false, "isIn99": true, "percentageOfUse": 100.0, "percentageOfUseByIdentity": 0.01, "avgWinRate": 0.0, "avgDrawRate": 0.143}, {"occurrences": 1, "cardName": "Heroic Intervention", "card_faces": [], "colorIdentity": "G", "colors": "G", "decklists": [{"commanders": "Atogatog", "decks": [{"name": "Toontown {CEDH}", "url": "https://www.moxfield.com/decks/vnV82CWvaUer1JhrL9GIgw", "commanders": [{"name": "Atogatog", "color_identity": ["B", "G", "R", "U", "W"]}]}], "colorIdentity": ["W", "U", "B", "R", "G"]}], "cmc": 2.0, "prices": {"usd": 9.17, "usd_foil": 8.75, "eur": 7.52, "eur_foil": 7.67, "ck": 13.99, "ck_foil": 13.99, "lastUpdatedAtUtc": "2024-07-22T10:49:15.082Z", "ck_buy": 6.5, "ck_buy_foil": 8.4, "csi": 7.99, "csi_foil": 8.99, "csi_buy": 3.0, "csi_buy_foil": 4.0, "ct": 9.43, "ct_foil": 8.92}, "reserved": false, "multiplePrintings": true, "lastPrint": "Fallout", "multiverse_ids": [653165], "type": "Instant", "typeLine": "Instant", "power": "", "toughness": "", "isCommander": false, "isIn99": true, "percentageOfUse": 100.0, "percentageOfUseByIdentity": 0.01, "avgWinRate": 0.0, "avgDrawRate": 0.143}, {"occurrences": 1, "cardName": "Fellwar Stone", "card_faces": [], "colorIdentity": "C", "colors": "C", "decklists": [{"commanders": "Atogatog", "decks": [{"name": "Toontown {CEDH}", "url": "https://www.moxfield.com/decks/vnV82CWvaUer1JhrL9GIgw", "commanders": [{"name": "Atogatog", "color_identity": ["B", "G", "R", "U", "W"]}]}], "colorIdentity": ["W", "U", "B", "R", "G"]}], "cmc": 2.0, "prices": {"usd": 11.77, "usd_foil": 14.46, "ck": 11.99, "ck_foil": 17.99, "lastUpdatedAtUtc": "2024-07-22T10:49:15.082Z", "ck_buy": 7.5, "ck_buy_foil": 10.0, "ck_buy_qty": 10, "ck_buy_foil_qty": 5, "csi": 9.99, "csi_foil": 14.99, "csi_buy": 5.0, "csi_buy_foil": 7.0, "csi_buy_qty": 20, "csi_buy_foil_qty": 20, "ct": 10.66, "ct_foil": 14.78}, "reserved": false, "multiplePrintings": true, "lastPrint": "Bloomburrow Commander", "multiverse_ids": [0], "type": "Artifact", "typeLine": "Artifact", "power": "", "toughness": "", "isCommander": false, "isIn99": true, "percentageOfUse": 100.0, "percentageOfUseByIdentity": 100.0, "avgWinRate": 0.0, "avgDrawRate": 0.143}, {"occurrences": 1, "cardName": "Mana Vault", "card_faces": [], "colorIdentity": "C", "colors": "C", "decklists": [{"commanders": "Atogatog", "decks": [{"name": "Toontown {CEDH}", "url": "https://www.moxfield.com/decks/vnV82CWvaUer1JhrL9GIgw", "commanders": [{"name": "Atogatog", "color_identity": ["B", "G", "R", "U", "W"]}]}], "colorIdentity": ["W", "U", "B", "R", "G"]}], "cmc": 1.0, "prices": {"usd_foil": 1028.82, "ck_foil": 1099.99, "lastUpdatedAtUtc": "2024-07-22T10:49:15.082Z", "ck_buy_foil": 715.0, "ck_buy_foil_qty": 5, "csi": 0.0, "csi_foil": 1199.99, "csi_buy": 0.0, "csi_buy_foil": 0.0, "csi_buy_qty": 0, "csi_buy_foil_qty": 0, "ct_foil": 892.97}, "reserved": false, "multiplePrintings": true, "lastPrint": "Double Masters 2022", "multiverse_ids": [0], "type": "Artifact", "typeLine": "Artifact", "power": "", "toughness": "", "isCommander": false, "isIn99": true, "percentageOfUse": 100.0, "percentageOfUseByIdentity": 100.0, "avgWinRate": 0.0, "avgDrawRate": 0.143}, {"occurrences": 1, "cardName": "Strip Mine", "card_faces": [], "colorIdentity": "C", "colors": "C", "decklists": [{"commanders": "Atogatog", "decks": [{"name": "Toontown {CEDH}", "url": "https://www.moxfield.com/decks/vnV82CWvaUer1JhrL9GIgw", "commanders": [{"name": "Atogatog", "color_identity": ["B", "G", "R", "U", "W"]}]}], "colorIdentity": ["W", "U", "B", "R", "G"]}], "cmc": 0, "prices": {"usd": 16.47, "eur": 9.79, "ck": 15.99, "lastUpdatedAtUtc": "2024-07-22T10:49:15.082Z", "ck_buy": 8.0, "csi": 14.99, "csi_buy": 7.0, "ct": 15.13}, "reserved": false, "multiplePrintings": true, "lastPrint": "From the Vault: Exiled", "multiverse_ids": [0], "type": "Land", "typeLine": "Land", "power": "", "toughness": "", "isCommander": false, "isIn99": true, "percentageOfUse": 100.0, "percentageOfUseByIdentity": 100.0, "avgWinRate": 0.0, "avgDrawRate": 0.143}, {"occurrences": 1, "cardName": "Veil of Summer", "card_faces": [], "colorIdentity": "G", "colors": "G", "decklists": [{"commanders": "Atogatog", "decks": [{"name": "Toontown {CEDH}", "url": "https://www.moxfield.com/decks/vnV82CWvaUer1JhrL9GIgw", "commanders": [{"name": "Atogatog", "color_identity": ["B", "G", "R", "U", "W"]}]}], "colorIdentity": ["W", "U", "B", "R", "G"]}], "cmc": 1.0, "prices": {"usd": 15.79, "usd_foil": 20.02, "ck": 21.99, "ck_foil": 24.99, "lastUpdatedAtUtc": "2024-07-22T10:49:15.082Z", "ck_buy": 12.5, "ck_buy_foil": 14.0, "csi": 14.99, "csi_foil": 23.99, "csi_buy": 8.0, "csi_buy_foil": 0.0, "ct": 18.38, "ct_foil": 27.62}, "reserved": false, "multiplePrintings": true, "lastPrint": "Mystery Booster 2", "multiverse_ids": [0], "type": "Instant", "typeLine": "Instant", "power": "", "toughness": "", "isCommander": false, "isIn99": true, "percentageOfUse": 100.0, "percentageOfUseByIdentity": 0.01, "avgWinRate": 0.0, "avgDrawRate": 0.143}, {"occurrences": 1, "cardName": "Bayou", "card_faces": [], "colorIdentity": "BG", "colors": "C", "decklists": [{"commanders": "Atogatog", "decks": [{"name": "Toontown {CEDH}", "url": "https://www.moxfield.com/decks/vnV82CWvaUer1JhrL9GIgw", "commanders": [{"name": "Atogatog", "color_identity": ["B", "G", "R", "U", "W"]}]}], "colorIdentity": ["W", "U", "B", "R", "G"]}], "cmc": 0, "prices": {"usd": 393.65, "eur": 243.4, "ck": 349.99, "lastUpdatedAtUtc": "2024-07-22T10:49:15.082Z", "ck_buy": 210.0, "csi": 449.99, "csi_buy": 280.0, "ct": 302.38}, "reserved": true, "multiplePrintings": true, "lastPrint": "Foreign Black Border", "multiverse_ids": [1377], "type": "Land", "typeLine": "Land — Swamp Forest", "power": "", "toughness": "", "isCommander": false, "isIn99": true, "percentageOfUse": 100.0, "percentageOfUseByIdentity": 0.01, "avgWinRate": 0.0, "avgDrawRate": 0.143}, {"occurrences": 1, "cardName": "Berserk", "card_faces": [], "colorIdentity": "G", "colors": "G", "decklists": [{"commanders": "Atogatog", "decks": [{"name": "Toontown {CEDH}", "url": "https://www.moxfield.com/decks/vnV82CWvaUer1JhrL9GIgw", "commanders": [{"name": "Atogatog", "color_identity": ["B", "G", "R", "U", "W"]}]}], "colorIdentity": ["W", "U", "B", "R", "G"]}], "cmc": 1.0, "prices": {"usd_foil": 22.37, "eur_foil": 21.46, "ck_foil": 29.99, "lastUpdatedAtUtc": "2024-07-22T10:49:15.082Z", "ck_buy_foil": 17.5, "csi_foil": 23.99, "csi_buy_foil": 12.0, "ct_foil": 28.57}, "reserved": false, "multiplePrintings": true, "lastPrint": "Conspiracy: Take the Crown", "multiverse_ids": [194969], "type": "Instant", "typeLine": "Instant", "power": "", "toughness": "", "isCommander": false, "isIn99": true, "percentageOfUse": 100.0, "percentageOfUseByIdentity": 0.01, "avgWinRate": 0.0, "avgDrawRate": 0.143}, {"occurrences": 1, "cardName": "Badlands", "card_faces": [], "colorIdentity": "BR", "colors": "C", "decklists": [{"commanders": "Atogatog", "decks": [{"name": "Toontown {CEDH}", "url": "https://www.moxfield.com/decks/vnV82CWvaUer1JhrL9GIgw", "commanders": [{"name": "Atogatog", "color_identity": ["B", "G", "R", "U", "W"]}]}], "colorIdentity": ["W", "U", "B", "R", "G"]}], "cmc": 0, "prices": {"usd": 395.81, "eur": 283.16, "ck": 499.99, "lastUpdatedAtUtc": "2024-07-22T10:49:15.082Z", "ck_buy": 325.0, "csi": 449.99, "csi_buy": 280.0, "ct": 317.47}, "reserved": true, "multiplePrintings": true, "lastPrint": "Foreign Black Border", "multiverse_ids": [1376], "type": "Land", "typeLine": "Land — Swamp Mountain", "power": "", "toughness": "", "isCommander": false, "isIn99": true, "percentageOfUse": 100.0, "percentageOfUseByIdentity": 0.01, "avgWinRate": 0.0, "avgDrawRate": 0.143}, {"occurrences": 1, "cardName": "Plateau", "card_faces": [], "colorIdentity": "WR", "colors": "C", "decklists": [{"commanders": "Atogatog", "decks": [{"name": "Toontown {CEDH}", "url": "https://www.moxfield.com/decks/vnV82CWvaUer1JhrL9GIgw", "commanders": [{"name": "Atogatog", "color_identity": ["B", "G", "R", "U", "W"]}]}], "colorIdentity": ["W", "U", "B", "R", "G"]}], "cmc": 0, "prices": {"usd": 316.4, "eur": 195.67, "ck": 349.99, "lastUpdatedAtUtc": "2024-07-22T10:49:15.082Z", "ck_buy": 230.0, "csi": 349.99, "csi_buy": 210.0, "ct": 201.41}, "reserved": true, "multiplePrintings": true, "lastPrint": "Foreign Black Border", "multiverse_ids": [1378], "type": "Land", "typeLine": "Land — Mountain Plains", "power": "", "toughness": "", "isCommander": false, "isIn99": true, "percentageOfUse": 100.0, "percentageOfUseByIdentity": 0.01, "avgWinRate": 0.0, "avgDrawRate": 0.143}, {"occurrences": 1, "cardName": "Savannah", "card_faces": [], "colorIdentity": "WG", "colors": "C", "decklists": [{"commanders": "Atogatog", "decks": [{"name": "Toontown {CEDH}", "url": "https://www.moxfield.com/decks/vnV82CWvaUer1JhrL9GIgw", "commanders": [{"name": "Atogatog", "color_identity": ["B", "G", "R", "U", "W"]}]}], "colorIdentity": ["W", "U", "B", "R", "G"]}], "cmc": 0, "prices": {"eur": 4900.0, "lastUpdatedAtUtc": "2024-07-22T10:49:15.082Z"}, "reserved": true, "multiplePrintings": true, "lastPrint": "Foreign Black Border", "multiverse_ids": [0], "type": "Land", "typeLine": "Land — Forest Plains", "power": "", "toughness": "", "isCommander": false, "isIn99": true, "percentageOfUse": 100.0, "percentageOfUseByIdentity": 0.02, "avgWinRate": 0.0, "avgDrawRate": 0.143}, {"occurrences": 1, "cardName": "Taiga", "card_faces": [], "colorIdentity": "RG", "colors": "C", "decklists": [{"commanders": "Atogatog", "decks": [{"name": "Toontown {CEDH}", "url": "https://www.moxfield.com/decks/vnV82CWvaUer1JhrL9GIgw", "commanders": [{"name": "Atogatog", "color_identity": ["B", "G", "R", "U", "W"]}]}], "colorIdentity": ["W", "U", "B", "R", "G"]}], "cmc": 0, "prices": {"usd": 359.97, "eur": 239.1, "ck": 339.99, "lastUpdatedAtUtc": "2024-07-22T10:49:15.082Z", "ck_buy": 205.0, "csi": 369.99, "csi_buy": 230.0, "ct": 256.11}, "reserved": true, "multiplePrintings": true, "lastPrint": "Foreign Black Border", "multiverse_ids": [1381], "type": "Land", "typeLine": "Land — Mountain Forest", "power": "", "toughness": "", "isCommander": false, "isIn99": true, "percentageOfUse": 100.0, "percentageOfUseByIdentity": 0.01, "avgWinRate": 0.0, "avgDrawRate": 0.143}, {"occurrences": 1, "cardName": "Tundra", "card_faces": [], "colorIdentity": "WU", "colors": "C", "decklists": [{"commanders": "Atogatog", "decks": [{"name": "Toontown {CEDH}", "url": "https://www.moxfield.com/decks/vnV82CWvaUer1JhrL9GIgw", "commanders": [{"name": "Atogatog", "color_identity": ["B", "G", "R", "U", "W"]}]}], "colorIdentity": ["W", "U", "B", "R", "G"]}], "cmc": 0, "prices": {"usd": 482.85, "eur": 305.45, "ck": 499.99, "lastUpdatedAtUtc": "2024-07-22T10:49:15.082Z", "ck_buy": 280.0, "csi": 499.99, "csi_buy": 300.0, "ct": 320.5}, "reserved": true, "multiplePrintings": true, "lastPrint": "Foreign Black Border", "multiverse_ids": [1383], "type": "Land", "typeLine": "Land — Plains Island", "power": "", "toughness": "", "isCommander": false, "isIn99": true, "percentageOfUse": 100.0, "percentageOfUseByIdentity": 0.01, "avgWinRate": 0.0, "avgDrawRate": 0.143}, {"occurrences": 1, "cardName": "Tropical Island", "card_faces": [], "colorIdentity": "UG", "colors": "C", "decklists": [{"commanders": "Atogatog", "decks": [{"name": "Toontown {CEDH}", "url": "https://www.moxfield.com/decks/vnV82CWvaUer1JhrL9GIgw", "commanders": [{"name": "Atogatog", "color_identity": ["B", "G", "R", "U", "W"]}]}], "colorIdentity": ["W", "U", "B", "R", "G"]}], "cmc": 0, "prices": {"usd": 516.69, "eur": 345.17, "ck": 649.99, "lastUpdatedAtUtc": "2024-07-22T10:49:15.082Z", "ck_buy": 390.0, "csi": 549.99, "csi_buy": 325.0, "ct": 340.52}, "reserved": true, "multiplePrintings": true, "lastPrint": "Foreign Black Border", "multiverse_ids": [1382], "type": "Land", "typeLine": "Land — Forest Island", "power": "", "toughness": "", "isCommander": false, "isIn99": true, "percentageOfUse": 100.0, "percentageOfUseByIdentity": 0.01, "avgWinRate": 0.0, "avgDrawRate": 0.143}, {"occurrences": 1, "cardName": "Underground Sea", "card_faces": [], "colorIdentity": "UB", "colors": "C", "decklists": [{"commanders": "Atogatog", "decks": [{"name": "Toontown {CEDH}", "url": "https://www.moxfield.com/decks/vnV82CWvaUer1JhrL9GIgw", "commanders": [{"name": "Atogatog", "color_identity": ["B", "G", "R", "U", "W"]}]}], "colorIdentity": ["W", "U", "B", "R", "G"]}], "cmc": 0, "prices": {"usd": 764.71, "eur": 501.35, "ck": 799.99, "lastUpdatedAtUtc": "2024-07-22T10:49:15.082Z", "ck_buy": 450.0, "csi": 899.99, "csi_buy": 575.0, "ct": 588.31}, "reserved": true, "multiplePrintings": true, "lastPrint": "Foreign Black Border", "multiverse_ids": [1384], "type": "Land", "typeLine": "Land — Island Swamp", "power": "", "toughness": "", "isCommander": false, "isIn99": true, "percentageOfUse": 100.0, "percentageOfUseByIdentity": 0.01, "avgWinRate": 0.0, "avgDrawRate": 0.143}, {"occurrences": 1, "cardName": "Dockside Extortionist", "card_faces": [], "colorIdentity": "R", "colors": "R", "decklists": [{"commanders": "Atogatog", "decks": [{"name": "Toontown {CEDH}", "url": "https://www.moxfield.com/decks/vnV82CWvaUer1JhrL9GIgw", "commanders": [{"name": "Atogatog", "color_identity": ["B", "G", "R", "U", "W"]}]}], "colorIdentity": ["W", "U", "B", "R", "G"]}], "cmc": 2.0, "prices": {"usd": 95.57, "usd_foil": 118.29, "eur": 84.72, "eur_foil": 96.35, "ck": 94.99, "ck_foil": 159.99, "lastUpdatedAtUtc": "2024-07-22T10:49:15.082Z", "ck_buy": 53.0, "ck_buy_foil": 80.0, "csi": 99.99, "csi_foil": 119.99, "csi_buy": 65.0, "csi_buy_foil": 70.0, "ct": 93.15, "ct_foil": 126.36}, "reserved": false, "multiplePrintings": true, "lastPrint": "Double Masters 2022", "multiverse_ids": [573022], "type": "Creature", "typeLine": "Creature — Goblin Pirate", "power": "1", "toughness": "2", "isCommander": false, "isIn99": true, "percentageOfUse": 100.0, "percentageOfUseByIdentity": 0.01, "avgWinRate": 0.0, "avgDrawRate": 0.143}, {"occurrences": 1, "cardName": "Atog", "card_faces": [], "colorIdentity": "R", "colors": "R", "decklists": [{"commanders": "Atogatog", "decks": [{"name": "Toontown {CEDH}", "url": "https://www.moxfield.com/decks/vnV82CWvaUer1JhrL9GIgw", "commanders": [{"name": "Atogatog", "color_identity": ["B", "G", "R", "U", "W"]}]}], "colorIdentity": ["W", "U", "B", "R", "G"]}], "cmc": 2.0, "prices": {"usd": 0.22, "usd_foil": 2.99, "eur": 0.22, "eur_foil": 1.87, "tix": 0.03, "ck": 0.35, "ck_foil": 2.99, "lastUpdatedAtUtc": "2024-07-22T10:49:15.082Z", "ck_buy": 0.03, "ck_buy_foil": 0.9, "csi": 0.49, "csi_foil": 3.99, "csi_buy": 0.0, "csi_buy_foil": 0.0, "ct": 0.15, "ct_foil": 2.65}, "reserved": false, "multiplePrintings": true, "lastPrint": "Mirrodin", "multiverse_ids": [46106], "type": "Creature", "typeLine": "Creature — Atog", "power": "1", "toughness": "2", "isCommander": false, "isIn99": true, "percentageOfUse": 100.0, "percentageOfUseByIdentity": 0.01, "avgWinRate": 0.0, "avgDrawRate": 0.143}, {"occurrences": 1, "cardName": "Mana Drain", "card_faces": [], "colorIdentity": "U", "colors": "U", "decklists": [{"commanders": "Atogatog", "decks": [{"name": "Toontown {CEDH}", "url": "https://www.moxfield.com/decks/vnV82CWvaUer1JhrL9GIgw", "commanders": [{"name": "Atogatog", "color_identity": ["B", "G", "R", "U", "W"]}]}], "colorIdentity": ["W", "U", "B", "R", "G"]}], "cmc": 2.0, "prices": {"usd": 29.44, "usd_foil": 33.23, "tix": 0.48, "ck": 37.99, "ck_foil": 49.99, "lastUpdatedAtUtc": "2024-07-22T10:49:15.082Z", "ck_buy": 21.0, "ck_buy_foil": 20.0, "csi": 32.99, "csi_foil": 44.99, "csi_buy": 18.0, "csi_buy_foil": 0.0, "ct": 28.93, "ct_foil": 38.7}, "reserved": false, "multiplePrintings": true, "lastPrint": "Double Masters 2022", "multiverse_ids": [657756], "type": "Instant", "typeLine": "Instant", "power": "", "toughness": "", "isCommander": false, "isIn99": true, "percentageOfUse": 100.0, "percentageOfUseByIdentity": 0.0, "avgWinRate": 0.0, "avgDrawRate": 0.143}, {"occurrences": 1, "cardName": "City of Brass", "card_faces": [], "colorIdentity": "C", "colors": "C", "decklists": [{"commanders": "Atogatog", "decks": [{"name": "Toontown {CEDH}", "url": "https://www.moxfield.com/decks/vnV82CWvaUer1JhrL9GIgw", "commanders": [{"name": "Atogatog", "color_identity": ["B", "G", "R", "U", "W"]}]}], "colorIdentity": ["W", "U", "B", "R", "G"]}], "cmc": 0, "prices": {"usd": 23.65, "usd_foil": 27.42, "eur": 16.49, "eur_foil": 27.55, "ck": 21.99, "ck_foil": 29.99, "lastUpdatedAtUtc": "2024-07-22T10:49:15.082Z", "ck_buy": 13.0, "ck_buy_foil": 15.0, "csi": 15.99, "csi_foil": 24.99, "csi_buy": 9.0, "csi_buy_foil": 13.0, "ct": 16.87, "ct_foil": 27.32}, "reserved": false, "multiplePrintings": true, "lastPrint": "Mystery Booster 2", "multiverse_ids": [573065], "type": "Land", "typeLine": "Land", "power": "", "toughness": "", "isCommander": false, "isIn99": true, "percentageOfUse": 100.0, "percentageOfUseByIdentity": 100.0, "avgWinRate": 0.0, "avgDrawRate": 0.143}, {"occurrences": 1, "cardName": "Jokulhaups", "card_faces": [], "colorIdentity": "R", "colors": "R", "decklists": [{"commanders": "Atogatog", "decks": [{"name": "Toontown {CEDH}", "url": "https://www.moxfield.com/decks/vnV82CWvaUer1JhrL9GIgw", "commanders": [{"name": "Atogatog", "color_identity": ["B", "G", "R", "U", "W"]}]}], "colorIdentity": ["W", "U", "B", "R", "G"]}], "cmc": 6.0, "prices": {"usd": 4.24, "eur": 2.78, "ck": 3.99, "lastUpdatedAtUtc": "2024-07-22T10:49:15.082Z", "ck_buy": 0.75, "ck_buy_qty": 0, "csi": 5.99, "csi_buy": 2.75, "csi_buy_qty": 20, "ct": 4.38}, "reserved": false, "multiplePrintings": true, "lastPrint": "Classic Sixth Edition", "multiverse_ids": [0], "type": "Sorcery", "typeLine": "Sorcery", "power": "", "toughness": "", "isCommander": false, "isIn99": true, "percentageOfUse": 100.0, "percentageOfUseByIdentity": 0.01, "avgWinRate": 0.0, "avgDrawRate": 0.143}, {"occurrences": 1, "cardName": "Pyroblast", "card_faces": [], "colorIdentity": "R", "colors": "R", "decklists": [{"commanders": "Atogatog", "decks": [{"name": "Toontown {CEDH}", "url": "https://www.moxfield.com/decks/vnV82CWvaUer1JhrL9GIgw", "commanders": [{"name": "Atogatog", "color_identity": ["B", "G", "R", "U", "W"]}]}], "colorIdentity": ["W", "U", "B", "R", "G"]}], "cmc": 1.0, "prices": {"usd": 7.04, "ck": 9.49, "lastUpdatedAtUtc": "2024-07-22T10:49:15.082Z", "ck_buy": 3.8, "csi": 7.99, "csi_buy": 4.0, "ct": 5.53}, "reserved": false, "multiplePrintings": true, "lastPrint": "Mystery Booster 2", "multiverse_ids": [0], "type": "Instant", "typeLine": "Instant", "power": "", "toughness": "", "isCommander": false, "isIn99": true, "percentageOfUse": 100.0, "percentageOfUseByIdentity": 0.01, "avgWinRate": 0.0, "avgDrawRate": 0.143}, {"occurrences": 1, "cardName": "Sphere of Resistance", "card_faces": [], "colorIdentity": "C", "colors": "C", "decklists": [{"commanders": "Atogatog", "decks": [{"name": "Toontown {CEDH}", "url": "https://www.moxfield.com/decks/vnV82CWvaUer1JhrL9GIgw", "commanders": [{"name": "Atogatog", "color_identity": ["B", "G", "R", "U", "W"]}]}], "colorIdentity": ["W", "U", "B", "R", "G"]}], "cmc": 2.0, "prices": {"usd": 5.66, "ck": 7.49, "lastUpdatedAtUtc": "2024-07-22T10:49:15.082Z", "ck_buy": 3.0, "csi": 7.99, "csi_foil": 8.99, "csi_buy": 0.0, "csi_buy_foil": 0.0, "ct": 9.17, "ct_foil": 10.25}, "reserved": false, "multiplePrintings": false, "lastPrint": "Exodus", "multiverse_ids": [0], "type": "Artifact", "typeLine": "Artifact", "power": "", "toughness": "", "isCommander": false, "isIn99": true, "percentageOfUse": 100.0, "percentageOfUseByIdentity": 100.0, "avgWinRate": 0.0, "avgDrawRate": 0.143}, {"occurrences": 1, "cardName": "Reanimate", "card_faces": [], "colorIdentity": "B", "colors": "B", "decklists": [{"commanders": "Atogatog", "decks": [{"name": "Toontown {CEDH}", "url": "https://www.moxfield.com/decks/vnV82CWvaUer1JhrL9GIgw", "commanders": [{"name": "Atogatog", "color_identity": ["B", "G", "R", "U", "W"]}]}], "colorIdentity": ["W", "U", "B", "R", "G"]}], "cmc": 1.0, "prices": {"usd": 6.31, "usd_foil": 10.31, "eur": 6.05, "eur_foil": 7.09, "tix": 0.14, "ck": 8.99, "ck_foil": 11.99, "lastUpdatedAtUtc": "2024-07-22T10:49:15.082Z", "ck_buy": 4.5, "ck_buy_foil": 4.8, "csi": 6.99, "csi_foil": 8.99, "csi_buy": 3.0, "csi_buy_foil": 3.0, "ct": 7.06, "ct_foil": 7.75}, "reserved": false, "multiplePrintings": true, "lastPrint": "Murders at Karlov Manor Commander", "multiverse_ids": [657763], "type": "Sorcery", "typeLine": "Sorcery", "power": "", "toughness": "", "isCommander": false, "isIn99": true, "percentageOfUse": 100.0, "percentageOfUseByIdentity": 0.01, "avgWinRate": 0.0, "avgDrawRate": 0.143}, {"occurrences": 1, "cardName": "Bloodstained Mire", "card_faces": [], "colorIdentity": "C", "colors": "C", "decklists": [{"commanders": "Atogatog", "decks": [{"name": "Toontown {CEDH}", "url": "https://www.moxfield.com/decks/vnV82CWvaUer1JhrL9GIgw", "commanders": [{"name": "Atogatog", "color_identity": ["B", "G", "R", "U", "W"]}]}], "colorIdentity": ["W", "U", "B", "R", "G"]}], "cmc": 0, "prices": {"usd": 17.52, "usd_foil": 31.49, "tix": 1.11, "ck": 23.99, "ck_foil": 47.99, "lastUpdatedAtUtc": "2024-07-22T10:49:15.082Z", "ck_buy": 14.0, "ck_buy_foil": 19.2, "csi": 19.99, "csi_foil": 37.99, "csi_buy": 12.0, "csi_buy_foil": 20.0, "ct": 17.39, "ct_foil": 32.15}, "reserved": false, "multiplePrintings": true, "lastPrint": "Modern Horizons 3", "multiverse_ids": [661391], "type": "Land", "typeLine": "Land", "power": "", "toughness": "", "isCommander": false, "isIn99": true, "percentageOfUse": 100.0, "percentageOfUseByIdentity": 100.0, "avgWinRate": 0.0, "avgDrawRate": 0.143}, {"occurrences": 1, "cardName": "Flooded Strand", "card_faces": [], "colorIdentity": "C", "colors": "C", "decklists": [{"commanders": "Atogatog", "decks": [{"name": "Toontown {CEDH}", "url": "https://www.moxfield.com/decks/vnV82CWvaUer1JhrL9GIgw", "commanders": [{"name": "Atogatog", "color_identity": ["B", "G", "R", "U", "W"]}]}], "colorIdentity": ["W", "U", "B", "R", "G"]}], "cmc": 0, "prices": {"usd": 16.12, "usd_foil": 31.36, "tix": 2.17, "ck": 20.99, "ck_foil": 34.99, "lastUpdatedAtUtc": "2024-07-22T10:49:15.082Z", "ck_buy": 10.5, "ck_buy_foil": 14.0, "csi": 17.99, "csi_foil": 34.99, "csi_buy": 5.0, "csi_buy_foil": 18.0, "ct": 17.3, "ct_foil": 29.93}, "reserved": false, "multiplePrintings": true, "lastPrint": "Modern Horizons 3", "multiverse_ids": [661392], "type": "Land", "typeLine": "Land", "power": "", "toughness": "", "isCommander": false, "isIn99": true, "percentageOfUse": 100.0, "percentageOfUseByIdentity": 100.0, "avgWinRate": 0.0, "avgDrawRate": 0.143}, {"occurrences": 1, "cardName": "Barren Glory", "card_faces": [], "colorIdentity": "W", "colors": "W", "decklists": [{"commanders": "Atogatog", "decks": [{"name": "Toontown {CEDH}", "url": "https://www.moxfield.com/decks/vnV82CWvaUer1JhrL9GIgw", "commanders": [{"name": "Atogatog", "color_identity": ["B", "G", "R", "U", "W"]}]}], "colorIdentity": ["W", "U", "B", "R", "G"]}], "cmc": 6.0, "prices": {"usd": 1.42, "usd_foil": 16.83, "eur": 0.73, "eur_foil": 3.81, "tix": 0.02, "ck": 1.49, "ck_foil": 11.99, "lastUpdatedAtUtc": "2024-07-22T10:49:15.082Z", "ck_buy": 0.38, "ck_buy_foil": 6.0, "ck_buy_qty": 10, "ck_buy_foil_qty": 5, "csi": 0.99, "csi_foil": 6.99, "csi_buy": 0.25, "csi_buy_foil": 0.0, "csi_buy_qty": 20, "csi_buy_foil_qty": 0, "ct_foil": 7.79}, "reserved": false, "multiplePrintings": false, "lastPrint": "Future Sight", "multiverse_ids": [136048], "type": "Enchantment", "typeLine": "Enchantment", "power": "", "toughness": "", "isCommander": false, "isIn99": true, "percentageOfUse": 100.0, "percentageOfUseByIdentity": 0.01, "avgWinRate": 0.0, "avgDrawRate": 0.143}, {"occurrences": 1, "cardName": "Force of Will", "card_faces": [], "colorIdentity": "U", "colors": "U", "decklists": [{"commanders": "Atogatog", "decks": [{"name": "Toontown {CEDH}", "url": "https://www.moxfield.com/decks/vnV82CWvaUer1JhrL9GIgw", "commanders": [{"name": "Atogatog", "color_identity": ["B", "G", "R", "U", "W"]}]}], "colorIdentity": ["W", "U", "B", "R", "G"]}], "cmc": 5.0, "prices": {"usd_foil": 209.35, "eur_foil": 190.14, "tix": 10.31, "ck_foil": 249.99, "lastUpdatedAtUtc": "2024-07-22T10:49:15.082Z", "ck_buy_foil": 165.0, "ck_buy_foil_qty": 5, "csi_foil": 239.99, "csi_buy_foil": 125.0, "csi_buy_foil_qty": 20, "ct_foil": 218.75}, "reserved": false, "multiplePrintings": true, "lastPrint": "Dominaria Remastered", "multiverse_ids": [429873], "type": "Instant", "typeLine": "Instant", "power": "", "toughness": "", "isCommander": false, "isIn99": true, "percentageOfUse": 100.0, "percentageOfUseByIdentity": 0.0, "avgWinRate": 0.0, "avgDrawRate": 0.143}, {"occurrences": 1, "cardName": "Mystic Remora", "card_faces": [], "colorIdentity": "U", "colors": "U", "decklists": [{"commanders": "Atogatog", "decks": [{"name": "Toontown {CEDH}", "url": "https://www.moxfield.com/decks/vnV82CWvaUer1JhrL9GIgw", "commanders": [{"name": "Atogatog", "color_identity": ["B", "G", "R", "U", "W"]}]}], "colorIdentity": ["W", "U", "B", "R", "G"]}], "cmc": 1.0, "prices": {"usd": 39.59, "usd_foil": 43.93, "ck": 39.99, "ck_foil": 49.99, "lastUpdatedAtUtc": "2024-07-22T10:49:15.082Z", "ck_buy": 22.0, "ck_buy_foil": 30.0, "csi": 34.99, "csi_foil": 37.99, "csi_buy": 16.0, "csi_buy_foil": 18.0, "ct": 29.27, "ct_foil": 38.4}, "reserved": false, "multiplePrintings": true, "lastPrint": "Dominaria Remastered", "multiverse_ids": [0], "type": "Enchantment", "typeLine": "Enchantment", "power": "", "toughness": "", "isCommander": false, "isIn99": true, "percentageOfUse": 100.0, "percentageOfUseByIdentity": 0.0, "avgWinRate": 0.0, "avgDrawRate": 0.143}, {"occurrences": 1, "cardName": "Mystical Tutor", "card_faces": [], "colorIdentity": "U", "colors": "U", "decklists": [{"commanders": "Atogatog", "decks": [{"name": "Toontown {CEDH}", "url": "https://www.moxfield.com/decks/vnV82CWvaUer1JhrL9GIgw", "commanders": [{"name": "Atogatog", "color_identity": ["B", "G", "R", "U", "W"]}]}], "colorIdentity": ["W", "U", "B", "R", "G"]}], "cmc": 1.0, "prices": {"usd": 7.94, "usd_foil": 10.89, "tix": 0.51, "ck": 13.99, "ck_foil": 14.99, "lastUpdatedAtUtc": "2024-07-22T10:49:15.082Z", "ck_buy": 6.5, "ck_buy_foil": 7.5, "csi": 9.99, "csi_foil": 10.99, "csi_buy": 5.0, "csi_buy_foil": 5.5, "ct": 8.09, "ct_foil": 10.85}, "reserved": false, "multiplePrintings": true, "lastPrint": "Dominaria Remastered", "multiverse_ids": [600972], "type": "Instant", "typeLine": "Instant", "power": "", "toughness": "", "isCommander": false, "isIn99": true, "percentageOfUse": 100.0, "percentageOfUseByIdentity": 0.0, "avgWinRate": 0.0, "avgDrawRate": 0.143}, {"occurrences": 1, "cardName": "Blind Obedience", "card_faces": [], "colorIdentity": "W", "colors": "W", "decklists": [{"commanders": "Atogatog", "decks": [{"name": "Toontown {CEDH}", "url": "https://www.moxfield.com/decks/vnV82CWvaUer1JhrL9GIgw", "commanders": [{"name": "Atogatog", "color_identity": ["B", "G", "R", "U", "W"]}]}], "colorIdentity": ["W", "U", "B", "R", "G"]}], "cmc": 2.0, "prices": {"usd": 18.88, "usd_foil": 27.56, "ck": 21.99, "ck_foil": 29.99, "lastUpdatedAtUtc": "2024-07-22T10:49:15.082Z", "ck_buy": 14.0, "ck_buy_foil": 17.5, "csi": 19.99, "csi_foil": 23.99, "csi_buy": 10.0, "csi_buy_foil": 12.0, "ct": 18.21, "ct_foil": 22.12}, "reserved": false, "multiplePrintings": true, "lastPrint": "Ravnica Remastered", "multiverse_ids": [0], "type": "Enchantment", "typeLine": "Enchantment", "power": "", "toughness": "", "isCommander": false, "isIn99": true, "percentageOfUse": 100.0, "percentageOfUseByIdentity": 0.01, "avgWinRate": 0.0, "avgDrawRate": 0.143}, {"occurrences": 1, "cardName": "Boros Charm", "card_faces": [], "colorIdentity": "WR", "colors": "WR", "decklists": [{"commanders": "Atogatog", "decks": [{"name": "Toontown {CEDH}", "url": "https://www.moxfield.com/decks/vnV82CWvaUer1JhrL9GIgw", "commanders": [{"name": "Atogatog", "color_identity": ["B", "G", "R", "U", "W"]}]}], "colorIdentity": ["W", "U", "B", "R", "G"]}], "cmc": 2.0, "prices": {"usd": 18.37, "usd_foil": 21.54, "eur": 20.34, "eur_foil": 22.35, "tix": 0.43, "ck": 21.99, "ck_foil": 24.99, "lastUpdatedAtUtc": "2024-07-22T10:49:15.082Z", "ck_buy": 12.5, "ck_buy_foil": 14.5, "csi": 17.99, "csi_foil": 19.99, "csi_buy": 9.0, "csi_buy_foil": 10.0, "ct": 23.15, "ct_foil": 23.15}, "reserved": false, "multiplePrintings": true, "lastPrint": "Outlaws of Thunder Junction Commander", "multiverse_ids": [509363], "type": "Instant", "typeLine": "Instant", "power": "", "toughness": "", "isCommander": false, "isIn99": true, "percentageOfUse": 100.0, "percentageOfUseByIdentity": 0.01, "avgWinRate": 0.0, "avgDrawRate": 0.143}, {"occurrences": 1, "cardName": "Kessig Wolf Run", "card_faces": [], "colorIdentity": "RG", "colors": "C", "decklists": [{"commanders": "Atogatog", "decks": [{"name": "Toontown {CEDH}", "url": "https://www.moxfield.com/decks/vnV82CWvaUer1JhrL9GIgw", "commanders": [{"name": "Atogatog", "color_identity": ["B", "G", "R", "U", "W"]}]}], "colorIdentity": ["W", "U", "B", "R", "G"]}], "cmc": 0, "prices": {"usd": 10.73, "usd_foil": 12.08, "ck": 14.99, "ck_foil": 9.49, "lastUpdatedAtUtc": "2024-07-22T10:49:15.082Z", "ck_buy": 7.5, "ck_buy_foil": 5.3, "ck_buy_qty": 5, "ck_buy_foil_qty": 5, "csi": 9.99, "csi_foil": 11.99, "csi_buy": 4.0, "csi_buy_foil": 4.0, "csi_buy_qty": 20, "csi_buy_foil_qty": 20, "ct": 10.19, "ct_foil": 12.54}, "reserved": false, "multiplePrintings": true, "lastPrint": "Modern Horizons 3 Commander", "multiverse_ids": [0], "type": "Land", "typeLine": "Land", "power": "", "toughness": "", "isCommander": false, "isIn99": true, "percentageOfUse": 100.0, "percentageOfUseByIdentity": 0.01, "avgWinRate": 0.0, "avgDrawRate": 0.143}, {"occurrences": 1, "cardName": "Mycosynth Lattice", "card_faces": [], "colorIdentity": "C", "colors": "C", "decklists": [{"commanders": "Atogatog", "decks": [{"name": "Toontown {CEDH}", "url": "https://www.moxfield.com/decks/vnV82CWvaUer1JhrL9GIgw", "commanders": [{"name": "Atogatog", "color_identity": ["B", "G", "R", "U", "W"]}]}], "colorIdentity": ["W", "U", "B", "R", "G"]}], "cmc": 6.0, "prices": {"usd": 20.08, "ck": 24.99, "lastUpdatedAtUtc": "2024-07-22T10:49:15.082Z", "ck_buy": 14.0, "ck_buy_qty": 5, "csi": 19.99, "csi_foil": 24.99, "csi_buy": 8.0, "csi_buy_foil": 0.0, "csi_buy_qty": 20, "csi_buy_foil_qty": 0, "ct": 14.11, "ct_foil": 18.2}, "reserved": false, "multiplePrintings": true, "lastPrint": "Battlebond", "multiverse_ids": [0], "type": "Artifact", "typeLine": "Artifact", "power": "", "toughness": "", "isCommander": false, "isIn99": true, "percentageOfUse": 100.0, "percentageOfUseByIdentity": 100.0, "avgWinRate": 0.0, "avgDrawRate": 0.143}, {"occurrences": 1, "cardName": "Chandra's Ignition", "card_faces": [], "colorIdentity": "R", "colors": "R", "decklists": [{"commanders": "Atogatog", "decks": [{"name": "Toontown {CEDH}", "url": "https://www.moxfield.com/decks/vnV82CWvaUer1JhrL9GIgw", "commanders": [{"name": "Atogatog", "color_identity": ["B", "G", "R", "U", "W"]}]}], "colorIdentity": ["W", "U", "B", "R", "G"]}], "cmc": 5.0, "prices": {"usd_foil": 10.67, "ck_foil": 9.49, "lastUpdatedAtUtc": "2024-07-22T10:49:15.082Z", "ck_buy_foil": 5.7}, "reserved": false, "multiplePrintings": true, "lastPrint": "Modern Horizons 3 Commander", "multiverse_ids": [0], "type": "Sorcery", "typeLine": "Sorcery", "power": "", "toughness": "", "isCommander": false, "isIn99": true, "percentageOfUse": 100.0, "percentageOfUseByIdentity": 0.01, "avgWinRate": 0.0, "avgDrawRate": 0.143}, {"occurrences": 1, "cardName": "Imperial Seal", "card_faces": [], "colorIdentity": "B", "colors": "B", "decklists": [{"commanders": "Atogatog", "decks": [{"name": "Toontown {CEDH}", "url": "https://www.moxfield.com/decks/vnV82CWvaUer1JhrL9GIgw", "commanders": [{"name": "Atogatog", "color_identity": ["B", "G", "R", "U", "W"]}]}], "colorIdentity": ["W", "U", "B", "R", "G"]}], "cmc": 1.0, "prices": {"usd": 84.23, "usd_foil": 102.37, "eur": 71.23, "eur_foil": 88.01, "ck": 99.99, "ck_foil": 139.99, "lastUpdatedAtUtc": "2024-07-22T10:49:15.082Z", "ck_buy": 60.0, "ck_buy_foil": 70.0, "csi": 99.99, "csi_foil": 109.99, "csi_buy": 60.0, "csi_buy_foil": 60.0, "ct": 81.07, "ct_foil": 101.2}, "reserved": false, "multiplePrintings": true, "lastPrint": "Double Masters 2022", "multiverse_ids": [573016], "type": "Sorcery", "typeLine": "Sorcery", "power": "", "toughness": "", "isCommander": false, "isIn99": true, "percentageOfUse": 100.0, "percentageOfUseByIdentity": 0.01, "avgWinRate": 0.0, "avgDrawRate": 0.143}, {"occurrences": 1, "cardName": "Enlightened Tutor", "card_faces": [], "colorIdentity": "W", "colors": "W", "decklists": [{"commanders": "Atogatog", "decks": [{"name": "Toontown {CEDH}", "url": "https://www.moxfield.com/decks/vnV82CWvaUer1JhrL9GIgw", "commanders": [{"name": "Atogatog", "color_identity": ["B", "G", "R", "U", "W"]}]}], "colorIdentity": ["W", "U", "B", "R", "G"]}], "cmc": 1.0, "prices": {"usd_foil": 55.71, "eur_foil": 49.65, "ck_foil": 59.99, "lastUpdatedAtUtc": "2024-07-22T10:49:15.082Z", "ck_buy_foil": 33.0, "ck_buy_foil_qty": 5, "csi_foil": 69.99, "csi_buy_foil": 35.0, "csi_buy_foil_qty": 20, "ct_foil": 53.85}, "reserved": false, "multiplePrintings": true, "lastPrint": "Dominaria Remastered", "multiverse_ids": [0], "type": "Instant", "typeLine": "Instant", "power": "", "toughness": "", "isCommander": false, "isIn99": true, "percentageOfUse": 100.0, "percentageOfUseByIdentity": 0.01, "avgWinRate": 0.0, "avgDrawRate": 0.143}, {"occurrences": 1, "cardName": "Vampiric Tutor", "card_faces": [], "colorIdentity": "B", "colors": "B", "decklists": [{"commanders": "Atogatog", "decks": [{"name": "Toontown {CEDH}", "url": "https://www.moxfield.com/decks/vnV82CWvaUer1JhrL9GIgw", "commanders": [{"name": "Atogatog", "color_identity": ["B", "G", "R", "U", "W"]}]}], "colorIdentity": ["W", "U", "B", "R", "G"]}], "cmc": 1.0, "prices": {"usd_foil": 84.35, "eur_foil": 62.77, "ck_foil": 94.99, "lastUpdatedAtUtc": "2024-07-22T10:49:15.082Z", "ck_buy_foil": 53.0, "ck_buy_foil_qty": 5, "csi_foil": 84.99, "csi_buy_foil": 40.0, "csi_buy_foil_qty": 20, "ct_foil": 80.51}, "reserved": false, "multiplePrintings": true, "lastPrint": "Dominaria Remastered", "multiverse_ids": [0], "type": "Instant", "typeLine": "Instant", "power": "", "toughness": "", "isCommander": false, "isIn99": true, "percentageOfUse": 100.0, "percentageOfUseByIdentity": 0.01, "avgWinRate": 0.0, "avgDrawRate": 0.143}, {"occurrences": 1, "cardName": "Ancient Tomb", "card_faces": [], "colorIdentity": "C", "colors": "C", "decklists": [{"commanders": "Atogatog", "decks": [{"name": "Toontown {CEDH}", "url": "https://www.moxfield.com/decks/vnV82CWvaUer1JhrL9GIgw", "commanders": [{"name": "Atogatog", "color_identity": ["B", "G", "R", "U", "W"]}]}], "colorIdentity": ["W", "U", "B", "R", "G"]}], "cmc": 0, "prices": {"usd": 98.63, "usd_foil": 103.23, "eur": 83.47, "eur_foil": 83.65, "tix": 20.95, "ck": 119.99, "ck_foil": 129.99, "lastUpdatedAtUtc": "2024-07-22T10:49:15.082Z", "ck_buy": 75.0, "ck_buy_foil": 65.0, "csi": 99.99, "csi_foil": 99.99, "csi_buy": 60.0, "csi_buy_foil": 60.0, "ct": 110.66, "ct_foil": 110.66}, "reserved": false, "multiplePrintings": true, "lastPrint": "Tales of Middle-earth Commander", "multiverse_ids": [622589], "type": "Land", "typeLine": "Land", "power": "", "toughness": "", "isCommander": false, "isIn99": true, "percentageOfUse": 100.0, "percentageOfUseByIdentity": 100.0, "avgWinRate": 0.0, "avgDrawRate": 0.143}, {"occurrences": 1, "cardName": "Smothering Tithe", "card_faces": [], "colorIdentity": "W", "colors": "W", "decklists": [{"commanders": "Atogatog", "decks": [{"name": "Toontown {CEDH}", "url": "https://www.moxfield.com/decks/vnV82CWvaUer1JhrL9GIgw", "commanders": [{"name": "Atogatog", "color_identity": ["B", "G", "R", "U", "W"]}]}], "colorIdentity": ["W", "U", "B", "R", "G"]}], "cmc": 4.0, "prices": {"usd": 76.79, "usd_foil": 195.9, "tix": 0.87, "ck": 84.99, "ck_foil": 159.99, "lastUpdatedAtUtc": "2024-07-22T10:49:15.082Z", "ck_buy": 51.0, "ck_buy_foil": 80.0, "csi": 79.99, "csi_foil": 149.99, "csi_buy": 40.0, "csi_buy_foil": 0.0, "ct": 70.01, "ct_foil": 140.34}, "reserved": false, "multiplePrintings": true, "lastPrint": "Commander Masters", "multiverse_ids": [632392], "type": "Enchantment", "typeLine": "Enchantment", "power": "", "toughness": "", "isCommander": false, "isIn99": true, "percentageOfUse": 100.0, "percentageOfUseByIdentity": 0.01, "avgWinRate": 0.0, "avgDrawRate": 0.143}, {"occurrences": 1, "cardName": "Abrupt Decay", "card_faces": [], "colorIdentity": "BG", "colors": "BG", "decklists": [{"commanders": "Atogatog", "decks": [{"name": "Toontown {CEDH}", "url": "https://www.moxfield.com/decks/vnV82CWvaUer1JhrL9GIgw", "commanders": [{"name": "Atogatog", "color_identity": ["B", "G", "R", "U", "W"]}]}], "colorIdentity": ["W", "U", "B", "R", "G"]}], "cmc": 2.0, "prices": {"usd": 0.86, "usd_foil": 1.83, "eur": 0.68, "eur_foil": 1.51, "tix": 0.02, "ck": 0.99, "ck_foil": 0.99, "lastUpdatedAtUtc": "2024-07-22T10:49:15.082Z", "ck_buy": 0.3, "ck_buy_foil": 0.2, "csi": 0.99, "csi_foil": 1.99, "csi_buy": 0.0, "csi_buy_foil": 0.0, "ct": 0.33, "ct_foil": 2.03}, "reserved": false, "multiplePrintings": true, "lastPrint": "Mystery Booster 2", "multiverse_ids": [657779], "type": "Instant", "typeLine": "Instant", "power": "", "toughness": "", "isCommander": false, "isIn99": true, "percentageOfUse": 100.0, "percentageOfUseByIdentity": 0.01, "avgWinRate": 0.0, "avgDrawRate": 0.143}, {"occurrences": 1, "cardName": "Arid Mesa", "card_faces": [], "colorIdentity": "C", "colors": "C", "decklists": [{"commanders": "Atogatog", "decks": [{"name": "Toontown {CEDH}", "url": "https://www.moxfield.com/decks/vnV82CWvaUer1JhrL9GIgw", "commanders": [{"name": "Atogatog", "color_identity": ["B", "G", "R", "U", "W"]}]}], "colorIdentity": ["W", "U", "B", "R", "G"]}], "cmc": 0, "prices": {"usd": 29.8, "eur": 21.34, "ck": 32.99, "lastUpdatedAtUtc": "2024-07-22T10:49:15.082Z", "ck_buy": 20.5, "csi": 22.99, "csi_buy": 11.0, "ct": 25.2}, "reserved": false, "multiplePrintings": true, "lastPrint": "Modern Horizons 2 Timeshifts", "multiverse_ids": [0], "type": "Land", "typeLine": "Land", "power": "", "toughness": "", "isCommander": false, "isIn99": true, "percentageOfUse": 100.0, "percentageOfUseByIdentity": 100.0, "avgWinRate": 0.0, "avgDrawRate": 0.143}, {"occurrences": 1, "cardName": "Marsh Flats", "card_faces": [], "colorIdentity": "C", "colors": "C", "decklists": [{"commanders": "Atogatog", "decks": [{"name": "Toontown {CEDH}", "url": "https://www.moxfield.com/decks/vnV82CWvaUer1JhrL9GIgw", "commanders": [{"name": "Atogatog", "color_identity": ["B", "G", "R", "U", "W"]}]}], "colorIdentity": ["W", "U", "B", "R", "G"]}], "cmc": 0, "prices": {"usd": 25.92, "eur": 19.71, "ck": 32.99, "lastUpdatedAtUtc": "2024-07-22T10:49:15.082Z", "ck_buy": 20.5, "csi": 21.99, "csi_buy": 12.0, "ct": 18.72}, "reserved": false, "multiplePrintings": true, "lastPrint": "Modern Horizons 2 Timeshifts", "multiverse_ids": [0], "type": "Land", "typeLine": "Land", "power": "", "toughness": "", "isCommander": false, "isIn99": true, "percentageOfUse": 100.0, "percentageOfUseByIdentity": 100.0, "avgWinRate": 0.0, "avgDrawRate": 0.143}, {"occurrences": 1, "cardName": "Misty Rainforest", "card_faces": [], "colorIdentity": "C", "colors": "C", "decklists": [{"commanders": "Atogatog", "decks": [{"name": "Toontown {CEDH}", "url": "https://www.moxfield.com/decks/vnV82CWvaUer1JhrL9GIgw", "commanders": [{"name": "Atogatog", "color_identity": ["B", "G", "R", "U", "W"]}]}], "colorIdentity": ["W", "U", "B", "R", "G"]}], "cmc": 0, "prices": {"usd_foil": 265.77, "eur_foil": 197.7, "tix": 5.13, "ck_foil": 269.99, "lastUpdatedAtUtc": "2024-07-22T10:49:15.082Z", "ck_buy_foil": 165.0, "ck_buy_foil_qty": 5, "csi_foil": 279.99, "csi_buy_foil": 150.0, "csi_buy_foil_qty": 20, "ct_foil": 267.98}, "reserved": false, "multiplePrintings": true, "lastPrint": "Modern Horizons 2 Timeshifts", "multiverse_ids": [405102], "type": "Land", "typeLine": "Land", "power": "", "toughness": "", "isCommander": false, "isIn99": true, "percentageOfUse": 100.0, "percentageOfUseByIdentity": 100.0, "avgWinRate": 0.0, "avgDrawRate": 0.143}, {"occurrences": 1, "cardName": "Scalding Tarn", "card_faces": [], "colorIdentity": "C", "colors": "C", "decklists": [{"commanders": "Atogatog", "decks": [{"name": "Toontown {CEDH}", "url": "https://www.moxfield.com/decks/vnV82CWvaUer1JhrL9GIgw", "commanders": [{"name": "Atogatog", "color_identity": ["B", "G", "R", "U", "W"]}]}], "colorIdentity": ["W", "U", "B", "R", "G"]}], "cmc": 0, "prices": {"usd": 38.21, "usd_foil": 52.18, "eur": 32.03, "eur_foil": 69.6, "tix": 12.41, "ck": 44.99, "ck_foil": 69.99, "lastUpdatedAtUtc": "2024-07-22T10:49:15.082Z", "ck_buy": 27.0, "ck_buy_foil": 28.0, "csi": 37.99, "csi_foil": 59.99, "csi_buy": 20.0, "csi_buy_foil": 30.0, "ct": 35.41, "ct_foil": 52.83}, "reserved": false, "multiplePrintings": true, "lastPrint": "Modern Horizons 2 Timeshifts", "multiverse_ids": [497167], "type": "Land", "typeLine": "Land", "power": "", "toughness": "", "isCommander": false, "isIn99": true, "percentageOfUse": 100.0, "percentageOfUseByIdentity": 100.0, "avgWinRate": 0.0, "avgDrawRate": 0.143}, {"occurrences": 1, "cardName": "Verdant Catacombs", "card_faces": [], "colorIdentity": "C", "colors": "C", "decklists": [{"commanders": "Atogatog", "decks": [{"name": "Toontown {CEDH}", "url": "https://www.moxfield.com/decks/vnV82CWvaUer1JhrL9GIgw", "commanders": [{"name": "Atogatog", "color_identity": ["B", "G", "R", "U", "W"]}]}], "colorIdentity": ["W", "U", "B", "R", "G"]}], "cmc": 0, "prices": {"usd": 26.15, "eur": 18.01, "ck": 29.99, "lastUpdatedAtUtc": "2024-07-22T10:49:15.082Z", "ck_buy": 17.5, "ck_buy_qty": 5, "csi": 23.99, "csi_buy": 12.0, "csi_buy_qty": 20, "ct": 23.18}, "reserved": false, "multiplePrintings": true, "lastPrint": "Modern Horizons 2 Timeshifts", "multiverse_ids": [0], "type": "Land", "typeLine": "Land", "power": "", "toughness": "", "isCommander": false, "isIn99": true, "percentageOfUse": 100.0, "percentageOfUseByIdentity": 100.0, "avgWinRate": 0.0, "avgDrawRate": 0.143}, {"occurrences": 1, "cardName": "Mana Confluence", "card_faces": [], "colorIdentity": "C", "colors": "C", "decklists": [{"commanders": "Atogatog", "decks": [{"name": "Toontown {CEDH}", "url": "https://www.moxfield.com/decks/vnV82CWvaUer1JhrL9GIgw", "commanders": [{"name": "Atogatog", "color_identity": ["B", "G", "R", "U", "W"]}]}], "colorIdentity": ["W", "U", "B", "R", "G"]}], "cmc": 0, "prices": {"usd_foil": 41.38, "eur_foil": 30.62, "ck_foil": 47.99, "lastUpdatedAtUtc": "2024-07-22T10:49:15.082Z", "ck_buy_foil": 24.0, "csi_foil": 47.99, "csi_buy_foil": 27.0, "ct": 43.82, "ct_foil": 45.34}, "reserved": false, "multiplePrintings": true, "lastPrint": "Commander Legends", "multiverse_ids": [0], "type": "Land", "typeLine": "Land", "power": "", "toughness": "", "isCommander": false, "isIn99": true, "percentageOfUse": 100.0, "percentageOfUseByIdentity": 100.0, "avgWinRate": 0.0, "avgDrawRate": 0.143}, {"occurrences": 1, "cardName": "Polluted Delta", "card_faces": [], "colorIdentity": "C", "colors": "C", "decklists": [{"commanders": "Atogatog", "decks": [{"name": "Toontown {CEDH}", "url": "https://www.moxfield.com/decks/vnV82CWvaUer1JhrL9GIgw", "commanders": [{"name": "Atogatog", "color_identity": ["B", "G", "R", "U", "W"]}]}], "colorIdentity": ["W", "U", "B", "R", "G"]}], "cmc": 0, "prices": {"usd": 19.2, "usd_foil": 37.08, "tix": 2.0, "ck": 21.99, "ck_foil": 49.99, "lastUpdatedAtUtc": "2024-07-22T10:49:15.082Z", "ck_buy": 11.0, "ck_buy_foil": 20.0, "csi": 22.99, "csi_foil": 39.99, "csi_buy": 0.0, "csi_buy_foil": 20.0, "ct": 20.12, "ct_foil": 38.4}, "reserved": false, "multiplePrintings": true, "lastPrint": "Modern Horizons 3", "multiverse_ids": [661395], "type": "Land", "typeLine": "Land", "power": "", "toughness": "", "isCommander": false, "isIn99": true, "percentageOfUse": 100.0, "percentageOfUseByIdentity": 100.0, "avgWinRate": 0.0, "avgDrawRate": 0.143}, {"occurrences": 1, "cardName": "Windswept Heath", "card_faces": [], "colorIdentity": "C", "colors": "C", "decklists": [{"commanders": "Atogatog", "decks": [{"name": "Toontown {CEDH}", "url": "https://www.moxfield.com/decks/vnV82CWvaUer1JhrL9GIgw", "commanders": [{"name": "Atogatog", "color_identity": ["B", "G", "R", "U", "W"]}]}], "colorIdentity": ["W", "U", "B", "R", "G"]}], "cmc": 0, "prices": {"usd": 12.84, "usd_foil": 24.29, "tix": 1.6, "ck": 15.99, "ck_foil": 29.99, "lastUpdatedAtUtc": "2024-07-22T10:49:15.082Z", "ck_buy": 9.0, "ck_buy_foil": 12.0, "csi": 14.99, "csi_foil": 23.99, "csi_buy": 8.0, "csi_buy_foil": 12.0, "ct": 13.76, "ct_foil": 24.9}, "reserved": false, "multiplePrintings": true, "lastPrint": "Modern Horizons 3", "multiverse_ids": [661399], "type": "Land", "typeLine": "Land", "power": "", "toughness": "", "isCommander": false, "isIn99": true, "percentageOfUse": 100.0, "percentageOfUseByIdentity": 100.0, "avgWinRate": 0.0, "avgDrawRate": 0.143}, {"occurrences": 1, "cardName": "Wooded Foothills", "card_faces": [], "colorIdentity": "C", "colors": "C", "decklists": [{"commanders": "Atogatog", "decks": [{"name": "Toontown {CEDH}", "url": "https://www.moxfield.com/decks/vnV82CWvaUer1JhrL9GIgw", "commanders": [{"name": "Atogatog", "color_identity": ["B", "G", "R", "U", "W"]}]}], "colorIdentity": ["W", "U", "B", "R", "G"]}], "cmc": 0, "prices": {"usd": 14.89, "usd_foil": 26.92, "tix": 1.47, "ck": 15.99, "ck_foil": 34.99, "lastUpdatedAtUtc": "2024-07-22T10:49:15.082Z", "ck_buy": 9.0, "ck_buy_foil": 14.0, "csi": 16.99, "csi_foil": 27.99, "csi_buy": 8.5, "csi_buy_foil": 14.0, "ct": 14.6, "ct_foil": 26.57}, "reserved": false, "multiplePrintings": true, "lastPrint": "Modern Horizons 3", "multiverse_ids": [661400], "type": "Land", "typeLine": "Land", "power": "", "toughness": "", "isCommander": false, "isIn99": true, "percentageOfUse": 100.0, "percentageOfUseByIdentity": 100.0, "avgWinRate": 0.0, "avgDrawRate": 0.143}, {"occurrences": 1, "cardName": "Mox Diamond", "card_faces": [], "colorIdentity": "C", "colors": "C", "decklists": [{"commanders": "Atogatog", "decks": [{"name": "Toontown {CEDH}", "url": "https://www.moxfield.com/decks/vnV82CWvaUer1JhrL9GIgw", "commanders": [{"name": "Atogatog", "color_identity": ["B", "G", "R", "U", "W"]}]}], "colorIdentity": ["W", "U", "B", "R", "G"]}], "cmc": 0, "prices": {"usd": 549.02, "eur": 429.28, "tix": 17.75, "ck": 699.99, "lastUpdatedAtUtc": "2024-07-22T10:49:15.082Z", "ck_buy": 420.0, "csi": 699.99, "csi_buy": 400.0, "ct": 493.54}, "reserved": true, "multiplePrintings": true, "lastPrint": "From the Vault: Relics", "multiverse_ids": [5193], "type": "Artifact", "typeLine": "Artifact", "power": "", "toughness": "", "isCommander": false, "isIn99": true, "percentageOfUse": 100.0, "percentageOfUseByIdentity": 100.0, "avgWinRate": 0.0, "avgDrawRate": 0.143}, {"occurrences": 1, "cardName": "Flusterstorm", "card_faces": [], "colorIdentity": "U", "colors": "U", "decklists": [{"commanders": "Atogatog", "decks": [{"name": "Toontown {CEDH}", "url": "https://www.moxfield.com/decks/vnV82CWvaUer1JhrL9GIgw", "commanders": [{"name": "Atogatog", "color_identity": ["B", "G", "R", "U", "W"]}]}], "colorIdentity": ["W", "U", "B", "R", "G"]}], "cmc": 1.0, "prices": {"usd": 19.73, "usd_foil": 103.78, "eur": 10.86, "eur_foil": 47.71, "tix": 1.88, "ck": 22.99, "ck_foil": 119.99, "lastUpdatedAtUtc": "2024-07-22T10:49:15.082Z", "ck_buy": 10.5, "ck_buy_foil": 48.0, "csi": 27.99, "csi_foil": 99.99, "csi_buy": 0.0, "csi_buy_foil": 0.0, "ct": 11.14, "ct_foil": 53.83}, "reserved": false, "multiplePrintings": true, "lastPrint": "Mystery Booster 2", "multiverse_ids": [438621], "type": "Instant", "typeLine": "Instant", "power": "", "toughness": "", "isCommander": false, "isIn99": true, "percentageOfUse": 100.0, "percentageOfUseByIdentity": 0.0, "avgWinRate": 0.0, "avgDrawRate": 0.143}, {"occurrences": 1, "cardName": "Mox Opal", "card_faces": [], "colorIdentity": "C", "colors": "C", "decklists": [{"commanders": "Atogatog", "decks": [{"name": "Toontown {CEDH}", "url": "https://www.moxfield.com/decks/vnV82CWvaUer1JhrL9GIgw", "commanders": [{"name": "Atogatog", "color_identity": ["B", "G", "R", "U", "W"]}]}], "colorIdentity": ["W", "U", "B", "R", "G"]}], "cmc": 0, "prices": {"usd": 147.57, "usd_foil": 178.09, "eur": 91.91, "eur_foil": 134.63, "ck": 199.99, "ck_foil": 179.99, "lastUpdatedAtUtc": "2024-07-22T10:49:15.082Z", "ck_buy": 115.0, "ck_buy_foil": 108.0, "csi": 149.99, "csi_foil": 159.99, "csi_buy": 90.0, "csi_buy_foil": 85.0, "ct": 110.47, "ct_foil": 143.42}, "reserved": false, "multiplePrintings": true, "lastPrint": "Double Masters", "multiverse_ids": [491371], "type": "Artifact", "typeLine": "Legendary Artifact", "power": "", "toughness": "", "isCommander": false, "isIn99": true, "percentageOfUse": 100.0, "percentageOfUseByIdentity": 100.0, "avgWinRate": 0.0, "avgDrawRate": 0.143}, {"occurrences": 1, "cardName": "Silence", "card_faces": [], "colorIdentity": "W", "colors": "W", "decklists": [{"commanders": "Atogatog", "decks": [{"name": "Toontown {CEDH}", "url": "https://www.moxfield.com/decks/vnV82CWvaUer1JhrL9GIgw", "commanders": [{"name": "Atogatog", "color_identity": ["B", "G", "R", "U", "W"]}]}], "colorIdentity": ["W", "U", "B", "R", "G"]}], "cmc": 1.0, "prices": {"usd": 25.47, "usd_foil": 36.69, "ck": 24.99, "ck_foil": 34.99, "lastUpdatedAtUtc": "2024-07-22T10:49:15.082Z", "ck_buy": 15.5, "ck_buy_foil": 20.0, "csi": 19.99, "csi_foil": 25.99, "csi_buy": 0.0, "csi_buy_foil": 10.0, "ct": 26.01, "ct_foil": 38.01}, "reserved": false, "multiplePrintings": true, "lastPrint": "Time Spiral Remastered", "multiverse_ids": [0], "type": "Instant", "typeLine": "Instant", "power": "", "toughness": "", "isCommander": false, "isIn99": true, "percentageOfUse": 100.0, "percentageOfUseByIdentity": 0.01, "avgWinRate": 0.0, "avgDrawRate": 0.143}, {"occurrences": 1, "cardName": "Stifle", "card_faces": [], "colorIdentity": "U", "colors": "U", "decklists": [{"commanders": "Atogatog", "decks": [{"name": "Toontown {CEDH}", "url": "https://www.moxfield.com/decks/vnV82CWvaUer1JhrL9GIgw", "commanders": [{"name": "Atogatog", "color_identity": ["B", "G", "R", "U", "W"]}]}], "colorIdentity": ["W", "U", "B", "R", "G"]}], "cmc": 1.0, "prices": {"usd_foil": 58.49, "eur_foil": 40.07, "tix": 11.37, "ck_foil": 59.99, "lastUpdatedAtUtc": "2024-07-22T10:49:15.082Z", "ck_buy_foil": 39.0, "ck_buy_foil_qty": 5, "csi_foil": 49.99, "csi_buy_foil": 25.0, "csi_buy_foil_qty": 20, "ct_foil": 44.11}, "reserved": false, "multiplePrintings": true, "lastPrint": "Mystery Booster 2", "multiverse_ids": [429877], "type": "Instant", "typeLine": "Instant", "power": "", "toughness": "", "isCommander": false, "isIn99": true, "percentageOfUse": 100.0, "percentageOfUseByIdentity": 0.0, "avgWinRate": 0.0, "avgDrawRate": 0.143}, {"occurrences": 1, "cardName": "Talisman of Dominance", "card_faces": [], "colorIdentity": "UB", "colors": "C", "decklists": [{"commanders": "Atogatog", "decks": [{"name": "Toontown {CEDH}", "url": "https://www.moxfield.com/decks/vnV82CWvaUer1JhrL9GIgw", "commanders": [{"name": "Atogatog", "color_identity": ["B", "G", "R", "U", "W"]}]}], "colorIdentity": ["W", "U", "B", "R", "G"]}], "cmc": 2.0, "prices": {"usd": 0.46, "tix": 0.08, "ck": 0.99, "lastUpdatedAtUtc": "2024-07-22T10:49:15.082Z", "ck_buy": 0.15, "csi": 0.99, "csi_buy": 0.25, "ct": 0.46, "ct_foil": 3.04}, "reserved": false, "multiplePrintings": true, "lastPrint": "Modern Horizons 3 Commander", "multiverse_ids": [582503], "type": "Artifact", "typeLine": "Artifact", "power": "", "toughness": "", "isCommander": false, "isIn99": true, "percentageOfUse": 100.0, "percentageOfUseByIdentity": 0.01, "avgWinRate": 0.0, "avgDrawRate": 0.143}, {"occurrences": 1, "cardName": "Volcanic Island", "card_faces": [], "colorIdentity": "UR", "colors": "C", "decklists": [{"commanders": "Atogatog", "decks": [{"name": "Toontown {CEDH}", "url": "https://www.moxfield.com/decks/vnV82CWvaUer1JhrL9GIgw", "commanders": [{"name": "Atogatog", "color_identity": ["B", "G", "R", "U", "W"]}]}], "colorIdentity": ["W", "U", "B", "R", "G"]}], "cmc": 0, "prices": {"usd": 693.35, "eur": 486.03, "ck": 799.99, "lastUpdatedAtUtc": "2024-07-22T10:49:15.082Z", "ck_buy": 480.0, "csi": 849.99, "csi_buy": 520.0, "ct": 587.61}, "reserved": true, "multiplePrintings": true, "lastPrint": "Foreign Black Border", "multiverse_ids": [1385], "type": "Land", "typeLine": "Land — Island Mountain", "power": "", "toughness": "", "isCommander": false, "isIn99": true, "percentageOfUse": 100.0, "percentageOfUseByIdentity": 0.01, "avgWinRate": 0.0, "avgDrawRate": 0.143}, {"occurrences": 1, "cardName": "Karn, the Great Creator", "card_faces": [], "colorIdentity": "C", "colors": "C", "decklists": [{"commanders": "Atogatog", "decks": [{"name": "Toontown {CEDH}", "url": "https://www.moxfield.com/decks/vnV82CWvaUer1JhrL9GIgw", "commanders": [{"name": "Atogatog", "color_identity": ["B", "G", "R", "U", "W"]}]}], "colorIdentity": ["W", "U", "B", "R", "G"]}], "cmc": 4.0, "prices": {"lastUpdatedAtUtc": "2024-07-22T10:49:15.082Z", "csi": 0.0, "csi_foil": 0.0, "csi_buy": 0.0, "csi_buy_foil": 0.0}, "reserved": false, "multiplePrintings": true, "lastPrint": "Bloomburrow Commander", "multiverse_ids": [0], "type": "Planeswalker", "typeLine": "Legendary Planeswalker — Karn", "power": "", "toughness": "", "isCommander": false, "isIn99": true, "percentageOfUse": 100.0, "percentageOfUseByIdentity": 100.0, "avgWinRate": 0.0, "avgDrawRate": 0.143}, {"occurrences": 1, "cardName": "Mayhem Devil", "card_faces": [], "colorIdentity": "BR", "colors": "BR", "decklists": [{"commanders": "Atogatog", "decks": [{"name": "Toontown {CEDH}", "url": "https://www.moxfield.com/decks/vnV82CWvaUer1JhrL9GIgw", "commanders": [{"name": "Atogatog", "color_identity": ["B", "G", "R", "U", "W"]}]}], "colorIdentity": ["W", "U", "B", "R", "G"]}], "cmc": 3.0, "prices": {"usd": 1.17, "usd_foil": 3.74, "tix": 0.57, "ck": 1.79, "ck_foil": 3.99, "lastUpdatedAtUtc": "2024-07-22T10:49:15.082Z", "ck_buy": 0.36, "ck_buy_foil": 1.4, "csi": 1.49, "csi_foil": 3.99, "csi_buy": 0.15, "csi_buy_foil": 1.5, "ct": 1.09, "ct_foil": 3.26}, "reserved": false, "multiplePrintings": true, "lastPrint": "Ravnica Remastered", "multiverse_ids": [645471], "type": "Creature", "typeLine": "Creature — Devil", "power": "3", "toughness": "3", "isCommander": false, "isIn99": true, "percentageOfUse": 100.0, "percentageOfUseByIdentity": 0.01, "avgWinRate": 0.0, "avgDrawRate": 0.143}, {"occurrences": 1, "cardName": "Force of Negation", "card_faces": [], "colorIdentity": "U", "colors": "U", "decklists": [{"commanders": "Atogatog", "decks": [{"name": "Toontown {CEDH}", "url": "https://www.moxfield.com/decks/vnV82CWvaUer1JhrL9GIgw", "commanders": [{"name": "Atogatog", "color_identity": ["B", "G", "R", "U", "W"]}]}], "colorIdentity": ["W", "U", "B", "R", "G"]}], "cmc": 3.0, "prices": {"usd": 48.84, "usd_foil": 55.81, "eur": 51.63, "eur_foil": 64.03, "ck": 59.99, "ck_foil": 64.99, "lastUpdatedAtUtc": "2024-07-22T10:49:15.082Z", "ck_buy": 33.0, "ck_buy_foil": 32.5, "csi": 49.99, "csi_foil": 59.99, "csi_buy": 32.0, "csi_buy_foil": 32.0, "ct": 62.79, "ct_foil": 66.56}, "reserved": false, "multiplePrintings": true, "lastPrint": "Double Masters 2022", "multiverse_ids": [573008], "type": "Instant", "typeLine": "Instant", "power": "", "toughness": "", "isCommander": false, "isIn99": true, "percentageOfUse": 100.0, "percentageOfUseByIdentity": 0.0, "avgWinRate": 0.0, "avgDrawRate": 0.143}, {"occurrences": 1, "cardName": "Talisman of Creativity", "card_faces": [], "colorIdentity": "UR", "colors": "C", "decklists": [{"commanders": "Atogatog", "decks": [{"name": "Toontown {CEDH}", "url": "https://www.moxfield.com/decks/vnV82CWvaUer1JhrL9GIgw", "commanders": [{"name": "Atogatog", "color_identity": ["B", "G", "R", "U", "W"]}]}], "colorIdentity": ["W", "U", "B", "R", "G"]}], "cmc": 2.0, "prices": {"usd": 1.24, "eur": 0.9, "tix": 0.08, "ck": 1.49, "lastUpdatedAtUtc": "2024-07-22T10:49:15.082Z", "ck_buy": 0.38, "ck_buy_qty": 19, "csi": 1.49, "csi_buy": 0.3, "csi_buy_qty": 20, "ct": 0.85, "ct_foil": 4.32}, "reserved": false, "multiplePrintings": true, "lastPrint": "Modern Horizons 3 Commander", "multiverse_ids": [582502], "type": "Artifact", "typeLine": "Artifact", "power": "", "toughness": "", "isCommander": false, "isIn99": true, "percentageOfUse": 100.0, "percentageOfUseByIdentity": 0.01, "avgWinRate": 0.0, "avgDrawRate": 0.143}, {"occurrences": 1, "cardName": "Talisman of Curiosity", "card_faces": [], "colorIdentity": "UG", "colors": "C", "decklists": [{"commanders": "Atogatog", "decks": [{"name": "Toontown {CEDH}", "url": "https://www.moxfield.com/decks/vnV82CWvaUer1JhrL9GIgw", "commanders": [{"name": "Atogatog", "color_identity": ["B", "G", "R", "U", "W"]}]}], "colorIdentity": ["W", "U", "B", "R", "G"]}], "cmc": 2.0, "prices": {"usd": 0.23, "usd_foil": 1.5, "eur": 0.23, "eur_foil": 0.61, "ck": 0.49, "ck_foil": 2.99, "lastUpdatedAtUtc": "2024-07-22T10:49:15.082Z", "ck_buy": 0.1, "ck_buy_foil": 0.9, "csi": 0.49, "csi_foil": 1.99, "csi_buy": 0.0, "csi_buy_foil": 0.0, "ct": 0.21, "ct_foil": 0.88}, "reserved": false, "multiplePrintings": true, "lastPrint": "Modern Horizons 3 Commander", "multiverse_ids": [653208], "type": "Artifact", "typeLine": "Artifact", "power": "", "toughness": "", "isCommander": false, "isIn99": true, "percentageOfUse": 100.0, "percentageOfUseByIdentity": 0.01, "avgWinRate": 0.0, "avgDrawRate": 0.143}, {"occurrences": 1, "cardName": "Grand Abolisher", "card_faces": [], "colorIdentity": "W", "colors": "W", "decklists": [{"commanders": "Atogatog", "decks": [{"name": "Toontown {CEDH}", "url": "https://www.moxfield.com/decks/vnV82CWvaUer1JhrL9GIgw", "commanders": [{"name": "Atogatog", "color_identity": ["B", "G", "R", "U", "W"]}]}], "colorIdentity": ["W", "U", "B", "R", "G"]}], "cmc": 2.0, "prices": {"usd": 7.66, "usd_foil": 12.57, "tix": 0.26, "ck": 9.49, "ck_foil": 13.99, "lastUpdatedAtUtc": "2024-07-22T10:49:15.082Z", "ck_buy": 5.7, "ck_buy_foil": 7.0, "ck_buy_qty": 11, "ck_buy_foil_qty": 6, "csi": 8.99, "csi_foil": 13.99, "csi_buy": 4.5, "csi_buy_foil": 7.0, "csi_buy_qty": 20, "csi_buy_foil_qty": 20, "ct": 7.77, "ct_foil": 14.27}, "reserved": false, "multiplePrintings": true, "lastPrint": "The Big Score", "multiverse_ids": [660538], "type": "Creature", "typeLine": "Creature — Human Cleric", "power": "2", "toughness": "2", "isCommander": false, "isIn99": true, "percentageOfUse": 100.0, "percentageOfUseByIdentity": 0.01, "avgWinRate": 0.0, "avgDrawRate": 0.143}, {"occurrences": 1, "cardName": "Temur Sabertooth", "card_faces": [], "colorIdentity": "G", "colors": "G", "decklists": [{"commanders": "Atogatog", "decks": [{"name": "Toontown {CEDH}", "url": "https://www.moxfield.com/decks/vnV82CWvaUer1JhrL9GIgw", "commanders": [{"name": "Atogatog", "color_identity": ["B", "G", "R", "U", "W"]}]}], "colorIdentity": ["W", "U", "B", "R", "G"]}], "cmc": 4.0, "prices": {"usd": 12.0, "usd_etched": 21.13, "ck": 14.99, "ck_etched": 16.99, "lastUpdatedAtUtc": "2024-07-22T10:49:15.082Z", "ck_buy": 9.0, "ck_buy_etched": 7.75, "ck_buy_qty": 5, "ck_buy_etched_qty": 4, "csi": 11.99, "csi_buy": 6.0, "csi_buy_qty": 20, "ct": 7.41, "ct_etched": 8.1}, "reserved": false, "multiplePrintings": true, "lastPrint": "New Capenna Commander", "multiverse_ids": [0], "type": "Creature", "typeLine": "Creature — Cat", "power": "4", "toughness": "3", "isCommander": false, "isIn99": true, "percentageOfUse": 100.0, "percentageOfUseByIdentity": 0.01, "avgWinRate": 0.0, "avgDrawRate": 0.143}, {"occurrences": 1, "cardName": "Vandalblast", "card_faces": [], "colorIdentity": "R", "colors": "R", "decklists": [{"commanders": "Atogatog", "decks": [{"name": "Toontown {CEDH}", "url": "https://www.moxfield.com/decks/vnV82CWvaUer1JhrL9GIgw", "commanders": [{"name": "Atogatog", "color_identity": ["B", "G", "R", "U", "W"]}]}], "colorIdentity": ["W", "U", "B", "R", "G"]}], "cmc": 1.0, "prices": {"usd_foil": 15.47, "ck_foil": 16.99, "lastUpdatedAtUtc": "2024-07-22T10:49:15.082Z", "ck_buy_foil": 8.5, "ck_buy_foil_qty": 5, "csi_foil": 17.99, "csi_buy_foil": 9.0, "csi_buy_foil_qty": 20, "ct_foil": 16.08}, "reserved": false, "multiplePrintings": true, "lastPrint": "Outlaws of Thunder Junction Commander", "multiverse_ids": [0], "type": "Sorcery", "typeLine": "Sorcery", "power": "", "toughness": "", "isCommander": false, "isIn99": true, "percentageOfUse": 100.0, "percentageOfUseByIdentity": 0.01, "avgWinRate": 0.0, "avgDrawRate": 0.143}, {"occurrences": 1, "cardName": "Mental Misstep", "card_faces": [], "colorIdentity": "U", "colors": "U", "decklists": [{"commanders": "Atogatog", "decks": [{"name": "Toontown {CEDH}", "url": "https://www.moxfield.com/decks/vnV82CWvaUer1JhrL9GIgw", "commanders": [{"name": "Atogatog", "color_identity": ["B", "G", "R", "U", "W"]}]}], "colorIdentity": ["W", "U", "B", "R", "G"]}], "cmc": 1.0, "prices": {"usd": 64.3, "usd_foil": 105.55, "ck": 84.99, "ck_foil": 89.99, "lastUpdatedAtUtc": "2024-07-22T10:49:15.082Z", "ck_buy": 47.0, "ck_buy_foil": 54.0, "ck_buy_qty": 2, "ck_buy_foil_qty": 5, "csi": 59.99, "csi_foil": 89.99, "csi_buy": 28.0, "csi_buy_foil": 35.0, "csi_buy_qty": 20, "csi_buy_foil_qty": 20, "ct": 71.52, "ct_foil": 119.52}, "reserved": false, "multiplePrintings": true, "lastPrint": "Mystery Booster 2", "multiverse_ids": [0], "type": "Instant", "typeLine": "Instant", "power": "", "toughness": "", "isCommander": false, "isIn99": true, "percentageOfUse": 100.0, "percentageOfUseByIdentity": 0.0, "avgWinRate": 0.0, "avgDrawRate": 0.143}, {"occurrences": 1, "cardName": "Torpor Orb", "card_faces": [], "colorIdentity": "C", "colors": "C", "decklists": [{"commanders": "Atogatog", "decks": [{"name": "Toontown {CEDH}", "url": "https://www.moxfield.com/decks/vnV82CWvaUer1JhrL9GIgw", "commanders": [{"name": "Atogatog", "color_identity": ["B", "G", "R", "U", "W"]}]}], "colorIdentity": ["W", "U", "B", "R", "G"]}], "cmc": 2.0, "prices": {"usd": 2.22, "usd_foil": 34.23, "eur": 2.74, "eur_foil": 18.57, "tix": 0.06, "ck": 4.99, "ck_foil": 49.99, "lastUpdatedAtUtc": "2024-07-22T10:49:15.082Z", "ck_buy": 1.5, "ck_buy_foil": 20.0, "csi": 5.99, "csi_foil": 49.99, "csi_buy": 0.0, "csi_buy_foil": 25.0, "ct": 2.41, "ct_foil": 25.26}, "reserved": false, "multiplePrintings": true, "lastPrint": "Mystery Booster 2", "multiverse_ids": [233069], "type": "Artifact", "typeLine": "Artifact", "power": "", "toughness": "", "isCommander": false, "isIn99": true, "percentageOfUse": 100.0, "percentageOfUseByIdentity": 100.0, "avgWinRate": 0.0, "avgDrawRate": 0.143}, {"occurrences": 1, "cardName": "Drannith Magistrate", "card_faces": [], "colorIdentity": "W", "colors": "W", "decklists": [{"commanders": "Atogatog", "decks": [{"name": "Toontown {CEDH}", "url": "https://www.moxfield.com/decks/vnV82CWvaUer1JhrL9GIgw", "commanders": [{"name": "Atogatog", "color_identity": ["B", "G", "R", "U", "W"]}]}], "colorIdentity": ["W", "U", "B", "R", "G"]}], "cmc": 2.0, "prices": {"usd": 21.9, "usd_foil": 25.26, "eur": 17.87, "eur_foil": 20.07, "ck": 21.99, "ck_foil": 29.99, "lastUpdatedAtUtc": "2024-07-22T10:49:15.082Z", "ck_buy": 14.0, "ck_buy_foil": 18.0, "csi": 21.99, "csi_foil": 24.99, "csi_buy": 0.0, "csi_buy_foil": 0.0, "ct": 27.18, "ct_foil": 27.18}, "reserved": false, "multiplePrintings": false, "lastPrint": "Ikoria: Lair of Behemoths", "multiverse_ids": [0], "type": "Creature", "typeLine": "Creature — Human Wizard", "power": "1", "toughness": "3", "isCommander": false, "isIn99": true, "percentageOfUse": 100.0, "percentageOfUseByIdentity": 0.01, "avgWinRate": 0.0, "avgDrawRate": 0.143}, {"occurrences": 1, "cardName": "Imperial Recruiter", "card_faces": [], "colorIdentity": "R", "colors": "R", "decklists": [{"commanders": "Atogatog", "decks": [{"name": "Toontown {CEDH}", "url": "https://www.moxfield.com/decks/vnV82CWvaUer1JhrL9GIgw", "commanders": [{"name": "Atogatog", "color_identity": ["B", "G", "R", "U", "W"]}]}], "colorIdentity": ["W", "U", "B", "R", "G"]}], "cmc": 3.0, "prices": {"usd": 9.66, "usd_foil": 18.8, "eur": 7.91, "eur_foil": 13.25, "ck": 10.99, "ck_foil": 17.99, "lastUpdatedAtUtc": "2024-07-22T10:49:15.082Z", "ck_buy": 6.9, "ck_buy_foil": 9.0, "ck_buy_qty": 25, "ck_buy_foil_qty": 2, "csi": 8.99, "csi_foil": 14.99, "csi_buy": 5.0, "csi_buy_foil": 7.5, "csi_buy_qty": 20, "csi_buy_foil_qty": 20, "ct": 9.48, "ct_foil": 12.47}, "reserved": false, "multiplePrintings": true, "lastPrint": "Modern Horizons 2 Timeshifts", "multiverse_ids": [525349], "type": "Creature", "typeLine": "Creature — Human Advisor", "power": "1", "toughness": "1", "isCommander": false, "isIn99": true, "percentageOfUse": 100.0, "percentageOfUseByIdentity": 0.01, "avgWinRate": 0.0, "avgDrawRate": 0.143}, {"occurrences": 1, "cardName": "Elvish Spirit Guide", "card_faces": [], "colorIdentity": "G", "colors": "G", "decklists": [{"commanders": "Atogatog", "decks": [{"name": "Toontown {CEDH}", "url": "https://www.moxfield.com/decks/vnV82CWvaUer1JhrL9GIgw", "commanders": [{"name": "Atogatog", "color_identity": ["B", "G", "R", "U", "W"]}]}], "colorIdentity": ["W", "U", "B", "R", "G"]}], "cmc": 3.0, "prices": {"usd": 9.57, "usd_foil": 15.8, "ck": 11.99, "ck_foil": 14.99, "lastUpdatedAtUtc": "2024-07-22T10:49:15.082Z", "ck_buy": 7.5, "ck_buy_foil": 8.5, "ck_buy_qty": 10, "ck_buy_foil_qty": 7, "csi": 9.99, "csi_foil": 13.99, "csi_buy": 5.0, "csi_buy_foil": 6.0, "csi_buy_qty": 20, "csi_buy_foil_qty": 20, "ct": 9.89, "ct_foil": 13.22}, "reserved": false, "multiplePrintings": true, "lastPrint": "Mystery Booster 2", "multiverse_ids": [0], "type": "Creature", "typeLine": "Creature — Elf Spirit", "power": "2", "toughness": "2", "isCommander": false, "isIn99": true, "percentageOfUse": 100.0, "percentageOfUseByIdentity": 0.01, "avgWinRate": 0.0, "avgDrawRate": 0.143}, {"occurrences": 1, "cardName": "Chain of Vapor", "card_faces": [], "colorIdentity": "U", "colors": "U", "decklists": [{"commanders": "Atogatog", "decks": [{"name": "Toontown {CEDH}", "url": "https://www.moxfield.com/decks/vnV82CWvaUer1JhrL9GIgw", "commanders": [{"name": "Atogatog", "color_identity": ["B", "G", "R", "U", "W"]}]}], "colorIdentity": ["W", "U", "B", "R", "G"]}], "cmc": 1.0, "prices": {"usd": 15.55, "usd_foil": 230.31, "eur": 6.95, "eur_foil": 86.69, "tix": 0.04, "ck": 15.99, "ck_foil": 259.99, "lastUpdatedAtUtc": "2024-07-22T10:49:15.082Z", "ck_buy": 7.25, "ck_buy_foil": 130.0, "csi": 12.99, "csi_foil": 149.99, "csi_buy": 7.0, "csi_buy_foil": 0.0, "ct": 8.1, "ct_foil": 196.76}, "reserved": false, "multiplePrintings": true, "lastPrint": "Mystery Booster 2", "multiverse_ids": [12447], "type": "Instant", "typeLine": "Instant", "power": "", "toughness": "", "isCommander": false, "isIn99": true, "percentageOfUse": 100.0, "percentageOfUseByIdentity": 0.0, "avgWinRate": 0.0, "avgDrawRate": 0.143}, {"occurrences": 1, "cardName": "Simian Spirit Guide", "card_faces": [], "colorIdentity": "R", "colors": "R", "decklists": [{"commanders": "Atogatog", "decks": [{"name": "Toontown {CEDH}", "url": "https://www.moxfield.com/decks/vnV82CWvaUer1JhrL9GIgw", "commanders": [{"name": "Atogatog", "color_identity": ["B", "G", "R", "U", "W"]}]}], "colorIdentity": ["W", "U", "B", "R", "G"]}], "cmc": 3.0, "prices": {"usd_foil": 33.47, "ck_foil": 19.99, "lastUpdatedAtUtc": "2024-07-22T10:49:15.082Z", "ck_buy_foil": 12.0, "ck_buy_foil_qty": 5}, "reserved": false, "multiplePrintings": true, "lastPrint": "Mystery Booster 2", "multiverse_ids": [0], "type": "Creature", "typeLine": "Creature — Ape Spirit", "power": "2", "toughness": "2", "isCommander": false, "isIn99": true, "percentageOfUse": 100.0, "percentageOfUseByIdentity": 0.01, "avgWinRate": 0.0, "avgDrawRate": 0.143}, {"occurrences": 1, "cardName": "Lithatog", "card_faces": [], "colorIdentity": "RG", "colors": "RG", "decklists": [{"commanders": "Atogatog", "decks": [{"name": "Toontown {CEDH}", "url": "https://www.moxfield.com/decks/vnV82CWvaUer1JhrL9GIgw", "commanders": [{"name": "Atogatog", "color_identity": ["B", "G", "R", "U", "W"]}]}], "colorIdentity": ["W", "U", "B", "R", "G"]}], "cmc": 3.0, "prices": {"usd": 0.23, "usd_foil": 9.08, "eur": 0.22, "eur_foil": 3.03, "tix": 0.04, "ck": 0.35, "ck_foil": 2.49, "lastUpdatedAtUtc": "2024-07-22T10:49:15.082Z", "ck_buy": 0.04, "ck_buy_foil": 0.88, "ck_buy_qty": 0, "ck_buy_foil_qty": 5, "csi": 0.25, "csi_foil": 0.75, "csi_buy": 0.0, "csi_buy_foil": 0.0, "csi_buy_qty": 0, "csi_buy_foil_qty": 0, "ct": 0.11, "ct_foil": 4.58}, "reserved": false, "multiplePrintings": false, "lastPrint": "Odyssey", "multiverse_ids": [31770], "type": "Creature", "typeLine": "Creature — Atog", "power": "1", "toughness": "2", "isCommander": false, "isIn99": true, "percentageOfUse": 100.0, "percentageOfUseByIdentity": 0.01, "avgWinRate": 0.0, "avgDrawRate": 0.143}, {"occurrences": 1, "cardName": "Sarcatog", "card_faces": [], "colorIdentity": "BR", "colors": "BR", "decklists": [{"commanders": "Atogatog", "decks": [{"name": "Toontown {CEDH}", "url": "https://www.moxfield.com/decks/vnV82CWvaUer1JhrL9GIgw", "commanders": [{"name": "Atogatog", "color_identity": ["B", "G", "R", "U", "W"]}]}], "colorIdentity": ["W", "U", "B", "R", "G"]}], "cmc": 3.0, "prices": {"usd": 0.25, "usd_foil": 2.63, "eur": 0.24, "eur_foil": 3.24, "tix": 0.09, "ck": 0.49, "ck_foil": 2.99, "lastUpdatedAtUtc": "2024-07-22T10:49:15.082Z", "ck_buy": 0.04, "ck_buy_foil": 0.9, "ck_buy_qty": 0, "ck_buy_foil_qty": 5, "csi": 0.25, "csi_foil": 0.49, "csi_buy": 0.05, "csi_buy_foil": 0.0, "csi_buy_qty": 20, "csi_buy_foil_qty": 0, "ct": 0.17, "ct_foil": 2.81}, "reserved": false, "multiplePrintings": false, "lastPrint": "Odyssey", "multiverse_ids": [31793], "type": "Creature", "typeLine": "Creature — Atog", "power": "1", "toughness": "2", "isCommander": false, "isIn99": true, "percentageOfUse": 100.0, "percentageOfUseByIdentity": 0.01, "avgWinRate": 0.0, "avgDrawRate": 0.143}, {"occurrences": 1, "cardName": "Kediss, Emberclaw Familiar", "card_faces": [], "colorIdentity": "R", "colors": "R", "decklists": [{"commanders": "Atogatog", "decks": [{"name": "Toontown {CEDH}", "url": "https://www.moxfield.com/decks/vnV82CWvaUer1JhrL9GIgw", "commanders": [{"name": "Atogatog", "color_identity": ["B", "G", "R", "U", "W"]}]}], "colorIdentity": ["W", "U", "B", "R", "G"]}], "cmc": 2.0, "prices": {"usd": 4.58, "usd_foil": 4.73, "eur": 1.59, "eur_foil": 1.25, "tix": 0.41, "ck": 3.99, "ck_foil": 4.99, "lastUpdatedAtUtc": "2024-07-22T10:49:15.082Z", "ck_buy": 1.5, "ck_buy_foil": 1.75, "csi": 1.49, "csi_foil": 2.99, "csi_buy": 0.5, "csi_buy_foil": 0.0, "ct": 2.29, "ct_foil": 4.03}, "reserved": false, "multiplePrintings": false, "lastPrint": "Commander Legends", "multiverse_ids": [497708], "type": "Creature", "typeLine": "Legendary Creature — Elemental Lizard", "power": "1", "toughness": "1", "isCommander": false, "isIn99": true, "percentageOfUse": 100.0, "percentageOfUseByIdentity": 0.01, "avgWinRate": 0.0, "avgDrawRate": 0.143}, {"occurrences": 1, "cardName": "Ignoble Hierarch", "card_faces": [], "colorIdentity": "BRG", "colors": "G", "decklists": [{"commanders": "Atogatog", "decks": [{"name": "Toontown {CEDH}", "url": "https://www.moxfield.com/decks/vnV82CWvaUer1JhrL9GIgw", "commanders": [{"name": "Atogatog", "color_identity": ["B", "G", "R", "U", "W"]}]}], "colorIdentity": ["W", "U", "B", "R", "G"]}], "cmc": 1.0, "prices": {"usd": 1.9, "usd_foil": 2.61, "eur": 2.73, "eur_foil": 3.88, "ck": 2.49, "ck_foil": 2.99, "lastUpdatedAtUtc": "2024-07-22T10:49:15.082Z", "ck_buy": 0.4, "ck_buy_foil": 0.9, "csi": 2.49, "csi_foil": 3.49, "csi_buy": 1.0, "csi_buy_foil": 1.25, "ct": 2.0, "ct_foil": 3.55}, "reserved": false, "multiplePrintings": true, "lastPrint": "Modern Horizons 3 Commander", "multiverse_ids": [526723], "type": "Creature", "typeLine": "Creature — Goblin Shaman", "power": "0", "toughness": "1", "isCommander": false, "isIn99": true, "percentageOfUse": 100.0, "percentageOfUseByIdentity": 0.02, "avgWinRate": 0.0, "avgDrawRate": 0.143}, {"occurrences": 1, "cardName": "Ragavan, Nimble Pilferer", "card_faces": [], "colorIdentity": "R", "colors": "R", "decklists": [{"commanders": "Atogatog", "decks": [{"name": "Toontown {CEDH}", "url": "https://www.moxfield.com/decks/vnV82CWvaUer1JhrL9GIgw", "commanders": [{"name": "Atogatog", "color_identity": ["B", "G", "R", "U", "W"]}]}], "colorIdentity": ["W", "U", "B", "R", "G"]}], "cmc": 1.0, "prices": {"ck_foil": 2799.99, "lastUpdatedAtUtc": "2024-07-22T10:49:15.082Z", "ck_buy_foil": 1400.0, "ck_buy_foil_qty": 1, "csi_foil": 2999.99, "csi_buy_foil": 0.0, "csi_buy_foil_qty": 0}, "reserved": false, "multiplePrintings": true, "lastPrint": "Modern Horizons 2 Timeshifts", "multiverse_ids": [0], "type": "Creature", "typeLine": "Legendary Creature — Monkey Pirate", "power": "2", "toughness": "1", "isCommander": false, "isIn99": true, "percentageOfUse": 100.0, "percentageOfUseByIdentity": 0.01, "avgWinRate": 0.0, "avgDrawRate": 0.143}, {"occurrences": 1, "cardName": "Esper Sentinel", "card_faces": [], "colorIdentity": "W", "colors": "W", "decklists": [{"commanders": "Atogatog", "decks": [{"name": "Toontown {CEDH}", "url": "https://www.moxfield.com/decks/vnV82CWvaUer1JhrL9GIgw", "commanders": [{"name": "Atogatog", "color_identity": ["B", "G", "R", "U", "W"]}]}], "colorIdentity": ["W", "U", "B", "R", "G"]}], "cmc": 1.0, "prices": {"usd": 17.19, "usd_foil": 19.86, "ck": 23.99, "ck_foil": 32.99, "lastUpdatedAtUtc": "2024-07-22T10:49:15.082Z", "ck_buy": 13.5, "ck_buy_foil": 13.2, "csi": 23.99, "csi_foil": 29.99, "csi_buy": 0.0, "csi_buy_foil": 0.0, "ct": 16.41, "ct_foil": 24.3}, "reserved": false, "multiplePrintings": true, "lastPrint": "Modern Horizons 2 Timeshifts", "multiverse_ids": [0], "type": "Creature", "typeLine": "Artifact Creature — Human Soldier", "power": "1", "toughness": "1", "isCommander": false, "isIn99": true, "percentageOfUse": 100.0, "percentageOfUseByIdentity": 0.01, "avgWinRate": 0.0, "avgDrawRate": 0.143}, {"occurrences": 1, "cardName": "Boseiju, Who Endures", "card_faces": [], "colorIdentity": "G", "colors": "C", "decklists": [{"commanders": "Atogatog", "decks": [{"name": "Toontown {CEDH}", "url": "https://www.moxfield.com/decks/vnV82CWvaUer1JhrL9GIgw", "commanders": [{"name": "Atogatog", "color_identity": ["B", "G", "R", "U", "W"]}]}], "colorIdentity": ["W", "U", "B", "R", "G"]}], "cmc": 0, "prices": {"usd": 42.34, "usd_foil": 83.97, "eur": 40.88, "eur_foil": 80.83, "ck": 57.99, "ck_foil": 99.99, "lastUpdatedAtUtc": "2024-07-22T10:49:15.082Z", "ck_buy": 32.0, "ck_buy_foil": 50.0, "csi": 54.99, "csi_foil": 79.99, "csi_buy": 27.0, "csi_buy_foil": 45.0, "ct": 48.86, "ct_foil": 87.68}, "reserved": false, "multiplePrintings": false, "lastPrint": "Kamigawa: Neon Dynasty", "multiverse_ids": [552122], "type": "Land", "typeLine": "Legendary Land", "power": "", "toughness": "", "isCommander": false, "isIn99": true, "percentageOfUse": 100.0, "percentageOfUseByIdentity": 0.01, "avgWinRate": 0.0, "avgDrawRate": 0.143}, {"occurrences": 1, "cardName": "An Offer You Can't Refuse", "card_faces": [], "colorIdentity": "U", "colors": "U", "decklists": [{"commanders": "Atogatog", "decks": [{"name": "Toontown {CEDH}", "url": "https://www.moxfield.com/decks/vnV82CWvaUer1JhrL9GIgw", "commanders": [{"name": "Atogatog", "color_identity": ["B", "G", "R", "U", "W"]}]}], "colorIdentity": ["W", "U", "B", "R", "G"]}], "cmc": 1.0, "prices": {"usd": 6.54, "usd_foil": 21.38, "ck": 7.49, "ck_foil": 21.99, "lastUpdatedAtUtc": "2024-07-22T10:49:15.082Z", "ck_buy": 3.8, "ck_buy_foil": 13.0, "csi": 6.99, "csi_foil": 39.99, "csi_buy": 3.0, "csi_buy_foil": 0.0, "ct": 3.58, "ct_foil": 8.07}, "reserved": false, "multiplePrintings": true, "lastPrint": "Bloomburrow Commander", "multiverse_ids": [0], "type": "Instant", "typeLine": "Instant", "power": "", "toughness": "", "isCommander": false, "isIn99": true, "percentageOfUse": 100.0, "percentageOfUseByIdentity": 0.0, "avgWinRate": 0.0, "avgDrawRate": 0.143}, {"occurrences": 1, "cardName": "Karn's Sylex", "card_faces": [], "colorIdentity": "C", "colors": "C", "decklists": [{"commanders": "Atogatog", "decks": [{"name": "Toontown {CEDH}", "url": "https://www.moxfield.com/decks/vnV82CWvaUer1JhrL9GIgw", "commanders": [{"name": "Atogatog", "color_identity": ["B", "G", "R", "U", "W"]}]}], "colorIdentity": ["W", "U", "B", "R", "G"]}], "cmc": 3.0, "prices": {"usd": 0.66, "usd_foil": 0.81, "eur": 1.11, "eur_foil": 1.78, "tix": 0.45, "ck": 1.29, "ck_foil": 0.99, "lastUpdatedAtUtc": "2024-07-22T10:49:15.082Z", "ck_buy": 0.33, "ck_buy_foil": 0.2, "csi": 0.99, "csi_foil": 1.99, "csi_buy": 0.0, "csi_buy_foil": 0.0, "ct": 0.87, "ct_foil": 2.28}, "reserved": false, "multiplePrintings": false, "lastPrint": "Dominaria United", "multiverse_ids": [574714], "type": "Artifact", "typeLine": "Legendary Artifact", "power": "", "toughness": "", "isCommander": false, "isIn99": true, "percentageOfUse": 100.0, "percentageOfUseByIdentity": 100.0, "avgWinRate": 0.0, "avgDrawRate": 0.143}, {"occurrences": 1, "cardName": "Delighted Halfling", "card_faces": [], "colorIdentity": "G", "colors": "G", "decklists": [{"commanders": "Atogatog", "decks": [{"name": "Toontown {CEDH}", "url": "https://www.moxfield.com/decks/vnV82CWvaUer1JhrL9GIgw", "commanders": [{"name": "Atogatog", "color_identity": ["B", "G", "R", "U", "W"]}]}], "colorIdentity": ["W", "U", "B", "R", "G"]}], "cmc": 1.0, "prices": {"usd": 16.38, "usd_foil": 16.52, "tix": 1.96, "ck": 22.99, "ck_foil": 18.99, "lastUpdatedAtUtc": "2024-07-22T10:49:15.082Z", "ck_buy": 14.5, "ck_buy_foil": 9.5, "csi": 14.99, "csi_foil": 16.99, "csi_buy": 8.0, "csi_buy_foil": 8.5, "ct": 16.28, "ct_foil": 21.36}, "reserved": false, "multiplePrintings": false, "lastPrint": "The Lord of the Rings: Tales of Middle-earth", "multiverse_ids": [636206], "type": "Creature", "typeLine": "Creature — Halfling Citizen", "power": "1", "toughness": "2", "isCommander": false, "isIn99": true, "percentageOfUse": 100.0, "percentageOfUseByIdentity": 0.01, "avgWinRate": 0.0, "avgDrawRate": 0.143}, {"occurrences": 1, "cardName": "Orcish Bowmasters", "card_faces": [], "colorIdentity": "B", "colors": "B", "decklists": [{"commanders": "Atogatog", "decks": [{"name": "Toontown {CEDH}", "url": "https://www.moxfield.com/decks/vnV82CWvaUer1JhrL9GIgw", "commanders": [{"name": "Atogatog", "color_identity": ["B", "G", "R", "U", "W"]}]}], "colorIdentity": ["W", "U", "B", "R", "G"]}], "cmc": 2.0, "prices": {"usd": 44.19, "usd_foil": 44.3, "eur": 43.77, "eur_foil": 53.56, "tix": 23.51, "ck": 59.99, "ck_foil": 59.99, "lastUpdatedAtUtc": "2024-07-22T10:49:15.082Z", "ck_buy": 36.0, "ck_buy_foil": 30.0, "csi": 54.99, "csi_foil": 59.99, "csi_buy": 8.5, "csi_buy_foil": 35.0, "ct": 49.89, "ct_foil": 55.91}, "reserved": false, "multiplePrintings": false, "lastPrint": "The Lord of the Rings: Tales of Middle-earth", "multiverse_ids": [619720], "type": "Creature", "typeLine": "Creature — Orc Archer", "power": "1", "toughness": "1", "isCommander": false, "isIn99": true, "percentageOfUse": 100.0, "percentageOfUseByIdentity": 0.01, "avgWinRate": 0.0, "avgDrawRate": 0.143}, {"occurrences": 1, "cardName": "Borne Upon a Wind", "card_faces": [], "colorIdentity": "U", "colors": "U", "decklists": [{"commanders": "Atogatog", "decks": [{"name": "Toontown {CEDH}", "url": "https://www.moxfield.com/decks/vnV82CWvaUer1JhrL9GIgw", "commanders": [{"name": "Atogatog", "color_identity": ["B", "G", "R", "U", "W"]}]}], "colorIdentity": ["W", "U", "B", "R", "G"]}], "cmc": 2.0, "prices": {"usd": 9.3, "usd_foil": 9.85, "tix": 0.04, "ck": 6.49, "ck_foil": 9.99, "lastUpdatedAtUtc": "2024-07-22T10:49:15.082Z", "ck_buy": 3.25, "ck_buy_foil": 5.0, "csi": 7.99, "csi_foil": 11.99, "csi_buy": 0.0, "csi_buy_foil": 0.0, "ct": 10.59, "ct_foil": 10.59}, "reserved": false, "multiplePrintings": false, "lastPrint": "The Lord of the Rings: Tales of Middle-earth", "multiverse_ids": [636092], "type": "Instant", "typeLine": "Instant", "power": "", "toughness": "", "isCommander": false, "isIn99": true, "percentageOfUse": 100.0, "percentageOfUseByIdentity": 0.0, "avgWinRate": 0.0, "avgDrawRate": 0.143}, {"occurrences": 1, "cardName": "Lotho, Corrupt Shirriff", "card_faces": [], "colorIdentity": "WB", "colors": "WB", "decklists": [{"commanders": "Atogatog", "decks": [{"name": "Toontown {CEDH}", "url": "https://www.moxfield.com/decks/vnV82CWvaUer1JhrL9GIgw", "commanders": [{"name": "Atogatog", "color_identity": ["B", "G", "R", "U", "W"]}]}], "colorIdentity": ["W", "U", "B", "R", "G"]}], "cmc": 2.0, "prices": {"usd": 8.85, "usd_foil": 8.85, "tix": 0.03, "ck": 8.99, "ck_foil": 9.99, "lastUpdatedAtUtc": "2024-07-22T10:49:15.082Z", "ck_buy": 5.0, "ck_buy_foil": 4.0, "ck_buy_qty": 7, "ck_buy_foil_qty": 0, "csi": 7.49, "csi_foil": 9.99, "csi_buy": 2.5, "csi_buy_foil": 4.0, "csi_buy_qty": 20, "csi_buy_foil_qty": 20, "ct": 9.17, "ct_foil": 12.42}, "reserved": false, "multiplePrintings": false, "lastPrint": "The Lord of the Rings: Tales of Middle-earth", "multiverse_ids": [636261], "type": "Creature", "typeLine": "Legendary Creature — Halfling Rogue", "power": "2", "toughness": "1", "isCommander": false, "isIn99": true, "percentageOfUse": 100.0, "percentageOfUseByIdentity": 0.01, "avgWinRate": 0.0, "avgDrawRate": 0.143}, {"occurrences": 1, "cardName": "Tishana's Tidebinder", "card_faces": [], "colorIdentity": "U", "colors": "U", "decklists": [{"commanders": "Atogatog", "decks": [{"name": "Toontown {CEDH}", "url": "https://www.moxfield.com/decks/vnV82CWvaUer1JhrL9GIgw", "commanders": [{"name": "Atogatog", "color_identity": ["B", "G", "R", "U", "W"]}]}], "colorIdentity": ["W", "U", "B", "R", "G"]}], "cmc": 3.0, "prices": {"usd": 2.99, "usd_foil": 4.51, "eur": 7.61, "eur_foil": 10.84, "tix": 2.33, "ck": 7.99, "ck_foil": 11.99, "lastUpdatedAtUtc": "2024-07-22T10:49:15.082Z", "ck_buy": 2.0, "ck_buy_foil": 4.8, "csi": 8.99, "csi_foil": 11.99, "csi_buy": 0.0, "csi_buy_foil": 0.0, "ct": 8.07, "ct_foil": 11.91}, "reserved": false, "multiplePrintings": false, "lastPrint": "The Lost Caverns of Ixalan", "multiverse_ids": [639261], "type": "Creature", "typeLine": "Creature — Merfolk Wizard", "power": "3", "toughness": "2", "isCommander": false, "isIn99": true, "percentageOfUse": 100.0, "percentageOfUseByIdentity": 0.0, "avgWinRate": 0.0, "avgDrawRate": 0.143}, {"occurrences": 1, "cardName": "Sink into Stupor // Soporific Springs", "card_faces": ["Sink into Stupor", "Soporific Springs"], "colorIdentity": "U", "colors": "U", "decklists": [{"commanders": "Atogatog", "decks": [{"name": "Toontown {CEDH}", "url": "https://www.moxfield.com/decks/vnV82CWvaUer1JhrL9GIgw", "commanders": [{"name": "Atogatog", "color_identity": ["B", "G", "R", "U", "W"]}]}], "colorIdentity": ["W", "U", "B", "R", "G"]}], "cmc": 3.0, "prices": {"usd": 3.69, "usd_foil": 7.65, "eur": 3.44, "eur_foil": 4.96, "ck": 4.49, "ck_foil": 8.99, "lastUpdatedAtUtc": "2024-07-22T10:49:15.082Z", "ck_buy": 0.9, "ck_buy_foil": 3.6, "csi": 3.99, "csi_foil": 5.99, "csi_buy": 1.25, "csi_buy_foil": 0.0, "ct": 3.62, "ct_foil": 5.82}, "reserved": false, "multiplePrintings": false, "lastPrint": "Modern Horizons 3", "multiverse_ids": [661761], "type": "Instant", "typeLine": "Instant // Land", "power": "", "toughness": "", "isCommander": false, "isIn99": true, "percentageOfUse": 100.0, "percentageOfUseByIdentity": 0.0, "avgWinRate": 0.0, "avgDrawRate": 0.143}, {"occurrences": 1, "cardName": "Atogatog", "card_faces": [], "colorIdentity": "WUBRG", "colors": "WUBRG", "decklists": [{"commanders": "Atogatog", "decks": [{"name": "Toontown {CEDH}", "url": "https://www.moxfield.com/decks/vnV82CWvaUer1JhrL9GIgw", "commanders": [{"name": "Atogatog", "color_identity": ["B", "G", "R", "U", "W"]}]}], "colorIdentity": ["W", "U", "B", "R", "G"]}], "cmc": 5.0, "prices": {"usd": 1.15, "usd_foil": 35.92, "eur": 0.47, "eur_foil": 43.09, "tix": 0.02, "ck": 2.29, "ck_foil": 49.99, "lastUpdatedAtUtc": "2024-07-22T10:49:15.082Z", "ck_buy": 0.6, "ck_buy_foil": 25.0, "csi": 0.99, "csi_foil": 79.99, "csi_buy": 0.1, "csi_buy_foil": 0.0, "ct": 0.49, "ct_foil": 27.08}, "reserved": false, "multiplePrintings": false, "lastPrint": "Odyssey", "multiverse_ids": [31834], "type": "Creature", "typeLine": "Legendary Creature — Atog", "power": "5", "toughness": "5", "isCommander": true, "isIn99": false, "percentageOfUse": 100.0, "percentageOfUseByIdentity": 0.03, "avgWinRate": 0.0, "avgDrawRate": 0.143}]