[{"occurrences": 1, "cardName": "Island", "card_faces": [], "colorIdentity": "U", "colors": "C", "decklists": [{"commanders": "The Reality Chip", "decks": [{"name": "Bend Reality", "url": "https://www.moxfield.com/decks/fvuyt4A-FESSlVbF1-l3DQ", "commanders": [{"name": "The Reality Chip", "color_identity": ["U"]}]}], "colorIdentity": ["U"]}], "cmc": 0, "prices": {"usd": 0.41, "eur": 0.08, "ck": 0.35, "lastUpdatedAtUtc": "2024-06-11T10:48:49.438Z", "ck_buy": 0.04, "ck_buy_qty": 0, "csi": 0.25, "csi_buy": 0.0, "csi_buy_qty": 0, "ct": 0.17}, "reserved": false, "multiplePrintings": true, "lastPrint": "Jurassic World Collection", "multiverse_ids": [479476], "type": "Land", "typeLine": "Basic Land — Island", "power": "", "toughness": "", "isCommander": false, "isIn99": true, "percentageOfUse": 100.0, "percentageOfUseByIdentity": 0.0, "avgWinRate": 0.0, "avgDrawRate": 0.0}, {"occurrences": 1, "cardName": "Thassa's Oracle", "card_faces": [], "colorIdentity": "U", "colors": "U", "decklists": [{"commanders": "The Reality Chip", "decks": [{"name": "Bend Reality", "url": "https://www.moxfield.com/decks/fvuyt4A-FESSlVbF1-l3DQ", "commanders": [{"name": "The Reality Chip", "color_identity": ["U"]}]}], "colorIdentity": ["U"]}], "cmc": 2.0, "prices": {"usd": 19.41, "usd_foil": 20.23, "eur": 12.17, "eur_foil": 15.6, "tix": 1.16, "ck": 22.99, "ck_foil": 29.99, "lastUpdatedAtUtc": "2024-06-11T10:48:49.438Z", "ck_buy": 11.5, "ck_buy_foil": 15.0, "csi": 19.99, "csi_foil": 19.99, "csi_buy": 12.0, "csi_buy_foil": 12.0, "ct": 19.31, "ct_foil": 22.62}, "reserved": false, "multiplePrintings": false, "lastPrint": "Theros Beyond Death", "multiverse_ids": [476324], "type": "Creature", "typeLine": "Creature — Merfolk Wizard", "power": "1", "toughness": "3", "isCommander": false, "isIn99": true, "percentageOfUse": 100.0, "percentageOfUseByIdentity": 0.0, "avgWinRate": 0.0, "avgDrawRate": 0.0}, {"occurrences": 1, "cardName": "Emry, Lurker of the Loch", "card_faces": [], "colorIdentity": "U", "colors": "U", "decklists": [{"commanders": "The Reality Chip", "decks": [{"name": "Bend Reality", "url": "https://www.moxfield.com/decks/fvuyt4A-FESSlVbF1-l3DQ", "commanders": [{"name": "The Reality Chip", "color_identity": ["U"]}]}], "colorIdentity": ["U"]}], "cmc": 3.0, "prices": {"usd": 0.8, "usd_foil": 0.9, "eur": 0.71, "eur_foil": 2.89, "tix": 0.35, "ck": 1.29, "ck_foil": 2.49, "lastUpdatedAtUtc": "2024-06-11T10:48:49.438Z", "ck_buy": 0.33, "ck_buy_foil": 0.75, "ck_buy_qty": 32, "ck_buy_foil_qty": 15, "csi": 1.99, "csi_foil": 3.99, "csi_buy": 0.0, "csi_buy_foil": 0.0, "csi_buy_qty": 0, "csi_buy_foil_qty": 0, "ct": 0.9, "ct_foil": 1.09}, "reserved": false, "multiplePrintings": true, "lastPrint": "The Brothers' War Commander", "multiverse_ids": [473005], "type": "Creature", "typeLine": "Legendary Creature — Merfolk Wizard", "power": "1", "toughness": "2", "isCommander": false, "isIn99": true, "percentageOfUse": 100.0, "percentageOfUseByIdentity": 0.0, "avgWinRate": 0.0, "avgDrawRate": 0.0}, {"occurrences": 1, "cardName": "Swan Song", "card_faces": [], "colorIdentity": "U", "colors": "U", "decklists": [{"commanders": "The Reality Chip", "decks": [{"name": "Bend Reality", "url": "https://www.moxfield.com/decks/fvuyt4A-FESSlVbF1-l3DQ", "commanders": [{"name": "The Reality Chip", "color_identity": ["U"]}]}], "colorIdentity": ["U"]}], "cmc": 1.0, "prices": {"usd": 11.65, "usd_foil": 49.76, "eur": 8.35, "eur_foil": 23.11, "tix": 0.02, "ck": 14.99, "ck_foil": 64.99, "lastUpdatedAtUtc": "2024-06-11T10:48:49.438Z", "ck_buy": 6.0, "ck_buy_foil": 32.5, "ck_buy_qty": 0, "ck_buy_foil_qty": 4, "csi": 11.99, "csi_foil": 39.99, "csi_buy": 6.5, "csi_buy_foil": 20.0, "csi_buy_qty": 20, "csi_buy_foil_qty": 20, "ct": 10.56, "ct_foil": 26.21}, "reserved": false, "multiplePrintings": true, "lastPrint": "Tales of Middle-earth Commander", "multiverse_ids": [373701], "type": "Instant", "typeLine": "Instant", "power": "", "toughness": "", "isCommander": false, "isIn99": true, "percentageOfUse": 100.0, "percentageOfUseByIdentity": 0.0, "avgWinRate": 0.0, "avgDrawRate": 0.0}, {"occurrences": 1, "cardName": "Aether Spellbomb", "card_faces": [], "colorIdentity": "U", "colors": "C", "decklists": [{"commanders": "The Reality Chip", "decks": [{"name": "Bend Reality", "url": "https://www.moxfield.com/decks/fvuyt4A-FESSlVbF1-l3DQ", "commanders": [{"name": "The Reality Chip", "color_identity": ["U"]}]}], "colorIdentity": ["U"]}], "cmc": 1.0, "prices": {"usd": 0.29, "usd_foil": 5.28, "eur": 0.23, "eur_foil": 5.77, "tix": 0.03, "ck": 0.35, "ck_foil": 4.99, "lastUpdatedAtUtc": "2024-06-11T10:48:49.438Z", "ck_buy": 0.05, "ck_buy_foil": 2.0, "csi": 0.25, "csi_foil": 4.99, "csi_buy": 0.0, "csi_buy_foil": 0.0, "ct": 0.22, "ct_foil": 5.43}, "reserved": false, "multiplePrintings": true, "lastPrint": "Jumpstart 2022", "multiverse_ids": [370524], "type": "Artifact", "typeLine": "Artifact", "power": "", "toughness": "", "isCommander": false, "isIn99": true, "percentageOfUse": 100.0, "percentageOfUseByIdentity": 0.0, "avgWinRate": 0.0, "avgDrawRate": 0.0}, {"occurrences": 1, "cardName": "Artificer's Assistant", "card_faces": [], "colorIdentity": "U", "colors": "U", "decklists": [{"commanders": "The Reality Chip", "decks": [{"name": "Bend Reality", "url": "https://www.moxfield.com/decks/fvuyt4A-FESSlVbF1-l3DQ", "commanders": [{"name": "The Reality Chip", "color_identity": ["U"]}]}], "colorIdentity": ["U"]}], "cmc": 1.0, "prices": {"usd": 0.15, "eur": 0.12, "ck": 0.35, "lastUpdatedAtUtc": "2024-06-11T10:48:49.438Z", "ck_buy": 0.05, "ck_buy_qty": 10, "csi": 0.25, "csi_buy": 0.02, "csi_buy_qty": 20, "ct": 0.14}, "reserved": false, "multiplePrintings": false, "lastPrint": "Dominaria", "multiverse_ids": [0], "type": "Creature", "typeLine": "Creature — Bird", "power": "1", "toughness": "1", "isCommander": false, "isIn99": true, "percentageOfUse": 100.0, "percentageOfUseByIdentity": 0.0, "avgWinRate": 0.0, "avgDrawRate": 0.0}, {"occurrences": 1, "cardName": "Foundry Inspector", "card_faces": [], "colorIdentity": "C", "colors": "C", "decklists": [{"commanders": "The Reality Chip", "decks": [{"name": "Bend Reality", "url": "https://www.moxfield.com/decks/fvuyt4A-FESSlVbF1-l3DQ", "commanders": [{"name": "The Reality Chip", "color_identity": ["U"]}]}], "colorIdentity": ["U"]}], "cmc": 3.0, "prices": {"usd": 0.13, "usd_foil": 0.22, "eur": 0.15, "eur_foil": 0.21, "tix": 0.06, "ck": 0.35, "ck_foil": 0.79, "lastUpdatedAtUtc": "2024-06-11T10:48:49.438Z", "ck_buy": 0.03, "ck_buy_foil": 0.12, "ck_buy_qty": 0, "ck_buy_foil_qty": 0, "csi": 0.35, "csi_foil": 0.49, "csi_buy": 0.0, "csi_buy_foil": 0.0, "csi_buy_qty": 0, "csi_buy_foil_qty": 0, "ct": 0.1, "ct_foil": 0.19}, "reserved": false, "multiplePrintings": true, "lastPrint": "Commander Masters", "multiverse_ids": [497830], "type": "Creature", "typeLine": "Artifact Creature — Construct", "power": "3", "toughness": "2", "isCommander": false, "isIn99": true, "percentageOfUse": 100.0, "percentageOfUseByIdentity": 100.0, "avgWinRate": 0.0, "avgDrawRate": 0.0}, {"occurrences": 1, "cardName": "Helm of Awakening", "card_faces": [], "colorIdentity": "C", "colors": "C", "decklists": [{"commanders": "The Reality Chip", "decks": [{"name": "Bend Reality", "url": "https://www.moxfield.com/decks/fvuyt4A-FESSlVbF1-l3DQ", "commanders": [{"name": "The Reality Chip", "color_identity": ["U"]}]}], "colorIdentity": ["U"]}], "cmc": 2.0, "prices": {"usd": 1.08, "eur": 0.37, "ck": 1.29, "lastUpdatedAtUtc": "2024-06-11T10:48:49.438Z", "ck_buy": 0.33, "ck_buy_qty": 20, "csi": 3.99, "csi_buy": 0.0, "csi_buy_qty": 0, "ct": 0.55}, "reserved": false, "multiplePrintings": true, "lastPrint": "Dominaria Remastered", "multiverse_ids": [0], "type": "Artifact", "typeLine": "Artifact", "power": "", "toughness": "", "isCommander": false, "isIn99": true, "percentageOfUse": 100.0, "percentageOfUseByIdentity": 100.0, "avgWinRate": 0.0, "avgDrawRate": 0.0}, {"occurrences": 1, "cardName": "Lotus Petal", "card_faces": [], "colorIdentity": "C", "colors": "C", "decklists": [{"commanders": "The Reality Chip", "decks": [{"name": "Bend Reality", "url": "https://www.moxfield.com/decks/fvuyt4A-FESSlVbF1-l3DQ", "commanders": [{"name": "The Reality Chip", "color_identity": ["U"]}]}], "colorIdentity": ["U"]}], "cmc": 0, "prices": {"usd": 17.16, "eur": 11.97, "ck": 19.99, "lastUpdatedAtUtc": "2024-06-11T10:48:49.438Z", "ck_buy": 11.0, "ck_buy_qty": 24, "csi": 17.99, "csi_buy": 10.0, "csi_buy_qty": 20, "ct": 11.12}, "reserved": false, "multiplePrintings": true, "lastPrint": "From the Vault: Exiled", "multiverse_ids": [0], "type": "Artifact", "typeLine": "Artifact", "power": "", "toughness": "", "isCommander": false, "isIn99": true, "percentageOfUse": 100.0, "percentageOfUseByIdentity": 100.0, "avgWinRate": 0.0, "avgDrawRate": 0.0}, {"occurrences": 1, "cardName": "Mana Crypt", "card_faces": [], "colorIdentity": "C", "colors": "C", "decklists": [{"commanders": "The Reality Chip", "decks": [{"name": "Bend Reality", "url": "https://www.moxfield.com/decks/fvuyt4A-FESSlVbF1-l3DQ", "commanders": [{"name": "The Reality Chip", "color_identity": ["U"]}]}], "colorIdentity": ["U"]}], "cmc": 0, "prices": {"usd": 179.58, "usd_foil": 219.6, "eur": 149.58, "eur_foil": 186.72, "tix": 12.98, "ck": 229.99, "ck_foil": 329.99, "lastUpdatedAtUtc": "2024-06-11T10:48:49.438Z", "ck_buy": 150.0, "ck_buy_foil": 165.0, "csi": 199.99, "csi_foil": 249.99, "csi_buy": 125.0, "csi_buy_foil": 130.0, "ct": 191.43, "ct_foil": 219.64}, "reserved": false, "multiplePrintings": true, "lastPrint": "Double Masters", "multiverse_ids": [413767], "type": "Artifact", "typeLine": "Artifact", "power": "", "toughness": "", "isCommander": false, "isIn99": true, "percentageOfUse": 100.0, "percentageOfUseByIdentity": 100.0, "avgWinRate": 0.0, "avgDrawRate": 0.0}, {"occurrences": 1, "cardName": "Millikin", "card_faces": [], "colorIdentity": "C", "colors": "C", "decklists": [{"commanders": "The Reality Chip", "decks": [{"name": "Bend Reality", "url": "https://www.moxfield.com/decks/fvuyt4A-FESSlVbF1-l3DQ", "commanders": [{"name": "The Reality Chip", "color_identity": ["U"]}]}], "colorIdentity": ["U"]}], "cmc": 2.0, "prices": {"usd": 0.18, "eur": 0.19, "ck": 0.35, "lastUpdatedAtUtc": "2024-06-11T10:48:49.438Z", "ck_buy": 0.06, "ck_buy_qty": 10, "csi": 0.35, "csi_buy": 0.05, "csi_buy_qty": 20, "ct": 0.19}, "reserved": false, "multiplePrintings": true, "lastPrint": "Modern Horizons 2 Timeshifts", "multiverse_ids": [0], "type": "Creature", "typeLine": "Artifact Creature — Construct", "power": "0", "toughness": "1", "isCommander": false, "isIn99": true, "percentageOfUse": 100.0, "percentageOfUseByIdentity": 100.0, "avgWinRate": 0.0, "avgDrawRate": 0.0}, {"occurrences": 1, "cardName": "Myr Retriever", "card_faces": [], "colorIdentity": "C", "colors": "C", "decklists": [{"commanders": "The Reality Chip", "decks": [{"name": "Bend Reality", "url": "https://www.moxfield.com/decks/fvuyt4A-FESSlVbF1-l3DQ", "commanders": [{"name": "The Reality Chip", "color_identity": ["U"]}]}], "colorIdentity": ["U"]}], "cmc": 2.0, "prices": {"usd": 1.0, "usd_foil": 3.63, "eur": 0.69, "eur_foil": 2.19, "tix": 0.04, "ck": 1.49, "ck_foil": 5.99, "lastUpdatedAtUtc": "2024-06-11T10:48:49.438Z", "ck_buy": 0.6, "ck_buy_foil": 3.3, "ck_buy_qty": 21, "ck_buy_foil_qty": 13, "csi": 1.49, "csi_foil": 3.99, "csi_buy": 0.5, "csi_buy_foil": 1.5, "csi_buy_qty": 20, "csi_buy_foil_qty": 20, "ct": 1.1, "ct_foil": 3.77}, "reserved": false, "multiplePrintings": true, "lastPrint": "Double Masters", "multiverse_ids": [370520], "type": "Creature", "typeLine": "Artifact Creature — Myr", "power": "1", "toughness": "1", "isCommander": false, "isIn99": true, "percentageOfUse": 100.0, "percentageOfUseByIdentity": 100.0, "avgWinRate": 0.0, "avgDrawRate": 0.0}, {"occurrences": 1, "cardName": "Phyrexian Metamorph", "card_faces": [], "colorIdentity": "U", "colors": "U", "decklists": [{"commanders": "The Reality Chip", "decks": [{"name": "Bend Reality", "url": "https://www.moxfield.com/decks/fvuyt4A-FESSlVbF1-l3DQ", "commanders": [{"name": "The Reality Chip", "color_identity": ["U"]}]}], "colorIdentity": ["U"]}], "cmc": 4.0, "prices": {"usd": 4.63, "eur": 3.46, "tix": 0.28, "ck": 4.99, "lastUpdatedAtUtc": "2024-06-11T10:48:49.438Z", "ck_buy": 2.0, "ck_buy_qty": 101, "csi": 5.99, "csi_buy": 1.0, "csi_buy_qty": 20, "ct": 3.44}, "reserved": false, "multiplePrintings": true, "lastPrint": "Murders at Karlov Manor Commander", "multiverse_ids": [650210], "type": "Creature", "typeLine": "Artifact Creature — Phyrexian Shapeshifter", "power": "0", "toughness": "0", "isCommander": false, "isIn99": true, "percentageOfUse": 100.0, "percentageOfUseByIdentity": 0.0, "avgWinRate": 0.0, "avgDrawRate": 0.0}, {"occurrences": 1, "cardName": "Rhystic Study", "card_faces": [], "colorIdentity": "U", "colors": "U", "decklists": [{"commanders": "The Reality Chip", "decks": [{"name": "Bend Reality", "url": "https://www.moxfield.com/decks/fvuyt4A-FESSlVbF1-l3DQ", "commanders": [{"name": "The Reality Chip", "color_identity": ["U"]}]}], "colorIdentity": ["U"]}], "cmc": 3.0, "prices": {"usd": 41.2, "eur": 29.4, "ck": 49.99, "lastUpdatedAtUtc": "2024-06-11T10:48:49.438Z", "ck_buy": 25.0, "ck_buy_qty": 16, "csi": 47.99, "csi_buy": 25.0, "csi_buy_qty": 20, "ct": 30.31}, "reserved": false, "multiplePrintings": true, "lastPrint": "Jumpstart 2022", "multiverse_ids": [0], "type": "Enchantment", "typeLine": "Enchantment", "power": "", "toughness": "", "isCommander": false, "isIn99": true, "percentageOfUse": 100.0, "percentageOfUseByIdentity": 0.0, "avgWinRate": 0.0, "avgDrawRate": 0.0}, {"occurrences": 1, "cardName": "Sol Ring", "card_faces": [], "colorIdentity": "C", "colors": "C", "decklists": [{"commanders": "The Reality Chip", "decks": [{"name": "Bend Reality", "url": "https://www.moxfield.com/decks/fvuyt4A-FESSlVbF1-l3DQ", "commanders": [{"name": "The Reality Chip", "color_identity": ["U"]}]}], "colorIdentity": ["U"]}], "cmc": 1.0, "prices": {"eur": 0.59, "ck": 1.79, "ck_foil": 7.99, "lastUpdatedAtUtc": "2024-06-11T10:48:49.438Z", "ck_buy": 0.5, "ck_buy_foil": 3.2, "ck_buy_qty": 100, "ck_buy_foil_qty": 0, "csi": 1.99, "csi_buy": 0.0, "csi_buy_qty": 0, "ct": 0.66, "ct_foil": 15.16}, "reserved": false, "multiplePrintings": true, "lastPrint": "Bloomburrow Commander", "multiverse_ids": [0], "type": "Artifact", "typeLine": "Artifact", "power": "", "toughness": "", "isCommander": false, "isIn99": true, "percentageOfUse": 100.0, "percentageOfUseByIdentity": 100.0, "avgWinRate": 0.0, "avgDrawRate": 0.0}, {"occurrences": 1, "cardName": "Snap", "card_faces": [], "colorIdentity": "U", "colors": "U", "decklists": [{"commanders": "The Reality Chip", "decks": [{"name": "Bend Reality", "url": "https://www.moxfield.com/decks/fvuyt4A-FESSlVbF1-l3DQ", "commanders": [{"name": "The Reality Chip", "color_identity": ["U"]}]}], "colorIdentity": ["U"]}], "cmc": 2.0, "prices": {"usd": 1.04, "usd_foil": 70.86, "eur": 1.53, "eur_foil": 47.17, "tix": 0.18, "ck": 1.49, "ck_foil": 84.99, "lastUpdatedAtUtc": "2024-06-11T10:48:49.438Z", "ck_buy": 0.3, "ck_buy_foil": 42.5, "ck_buy_qty": 25, "ck_buy_foil_qty": 4, "csi": 1.49, "csi_foil": 69.99, "csi_buy": 0.35, "csi_buy_foil": 0.0, "csi_buy_qty": 20, "csi_buy_foil_qty": 0, "ct": 1.5, "ct_foil": 80.51}, "reserved": false, "multiplePrintings": true, "lastPrint": "Wilds of Eldraine Commander", "multiverse_ids": [12374], "type": "Instant", "typeLine": "Instant", "power": "", "toughness": "", "isCommander": false, "isIn99": true, "percentageOfUse": 100.0, "percentageOfUseByIdentity": 0.0, "avgWinRate": 0.0, "avgDrawRate": 0.0}, {"occurrences": 1, "cardName": "Trinket Mage", "card_faces": [], "colorIdentity": "U", "colors": "U", "decklists": [{"commanders": "The Reality Chip", "decks": [{"name": "Bend Reality", "url": "https://www.moxfield.com/decks/fvuyt4A-FESSlVbF1-l3DQ", "commanders": [{"name": "The Reality Chip", "color_identity": ["U"]}]}], "colorIdentity": ["U"]}], "cmc": 3.0, "prices": {"usd": 0.29, "usd_foil": 6.71, "eur": 0.25, "eur_foil": 4.47, "tix": 0.03, "ck": 0.39, "ck_foil": 5.99, "lastUpdatedAtUtc": "2024-06-11T10:48:49.438Z", "ck_buy": 0.05, "ck_buy_foil": 3.0, "ck_buy_qty": 34, "ck_buy_foil_qty": 5, "csi": 0.35, "csi_foil": 6.99, "csi_buy": 0.0, "csi_buy_foil": 2.5, "csi_buy_qty": 0, "csi_buy_foil_qty": 20, "ct": 0.17, "ct_foil": 3.3}, "reserved": false, "multiplePrintings": true, "lastPrint": "Time Spiral Remastered", "multiverse_ids": [209040], "type": "Creature", "typeLine": "Creature — Human Wizard", "power": "2", "toughness": "2", "isCommander": false, "isIn99": true, "percentageOfUse": 100.0, "percentageOfUseByIdentity": 0.0, "avgWinRate": 0.0, "avgDrawRate": 0.0}, {"occurrences": 1, "cardName": "Whir of Invention", "card_faces": [], "colorIdentity": "U", "colors": "U", "decklists": [{"commanders": "The Reality Chip", "decks": [{"name": "Bend Reality", "url": "https://www.moxfield.com/decks/fvuyt4A-FESSlVbF1-l3DQ", "commanders": [{"name": "The Reality Chip", "color_identity": ["U"]}]}], "colorIdentity": ["U"]}], "cmc": 3.0, "prices": {"usd": 3.13, "usd_foil": 5.62, "eur": 2.02, "eur_foil": 5.22, "tix": 0.03, "ck": 3.99, "ck_foil": 6.99, "lastUpdatedAtUtc": "2024-06-11T10:48:49.438Z", "ck_buy": 1.8, "ck_buy_foil": 2.8, "ck_buy_qty": 65, "ck_buy_foil_qty": 0, "csi": 2.49, "csi_foil": 5.99, "csi_buy": 1.0, "csi_buy_foil": 3.0, "csi_buy_qty": 20, "csi_buy_foil_qty": 20, "ct": 1.98, "ct_foil": 4.98}, "reserved": false, "multiplePrintings": false, "lastPrint": "Aether Revolt", "multiverse_ids": [423716], "type": "Instant", "typeLine": "Instant", "power": "", "toughness": "", "isCommander": false, "isIn99": true, "percentageOfUse": 100.0, "percentageOfUseByIdentity": 0.0, "avgWinRate": 0.0, "avgDrawRate": 0.0}, {"occurrences": 1, "cardName": "Spell Pierce", "card_faces": [], "colorIdentity": "U", "colors": "U", "decklists": [{"commanders": "The Reality Chip", "decks": [{"name": "Bend Reality", "url": "https://www.moxfield.com/decks/fvuyt4A-FESSlVbF1-l3DQ", "commanders": [{"name": "The Reality Chip", "color_identity": ["U"]}]}], "colorIdentity": ["U"]}], "cmc": 1.0, "prices": {"usd": 0.18, "usd_foil": 1.59, "eur": 0.15, "eur_foil": 2.24, "tix": 0.03, "ck": 0.39, "ck_foil": 2.49, "lastUpdatedAtUtc": "2024-06-11T10:48:49.438Z", "ck_buy": 0.04, "ck_buy_foil": 0.63, "csi": 0.25, "csi_foil": 3.99, "csi_buy": 0.0, "csi_buy_foil": 1.5, "ct": 0.27, "ct_foil": 1.59}, "reserved": false, "multiplePrintings": true, "lastPrint": "Double Masters 2022", "multiverse_ids": [435234], "type": "Instant", "typeLine": "Instant", "power": "", "toughness": "", "isCommander": false, "isIn99": true, "percentageOfUse": 100.0, "percentageOfUseByIdentity": 0.0, "avgWinRate": 0.0, "avgDrawRate": 0.0}, {"occurrences": 1, "cardName": "Walking Ballista", "card_faces": [], "colorIdentity": "C", "colors": "C", "decklists": [{"commanders": "The Reality Chip", "decks": [{"name": "Bend Reality", "url": "https://www.moxfield.com/decks/fvuyt4A-FESSlVbF1-l3DQ", "commanders": [{"name": "The Reality Chip", "color_identity": ["U"]}]}], "colorIdentity": ["U"]}], "cmc": 0, "prices": {"usd": 14.95, "usd_foil": 16.82, "ck": 17.99, "ck_foil": 19.99, "lastUpdatedAtUtc": "2024-06-11T10:48:49.438Z", "ck_buy": 9.0, "ck_buy_foil": 8.0, "ck_buy_qty": 23, "ck_buy_foil_qty": 2, "csi": 14.99, "csi_foil": 17.99, "csi_buy": 8.0, "csi_buy_foil": 0.0, "csi_buy_qty": 20, "csi_buy_foil_qty": 0, "ct": 17.39, "ct_foil": 17.39}, "reserved": false, "multiplePrintings": true, "lastPrint": "Fallout", "multiverse_ids": [654388], "type": "Creature", "typeLine": "Artifact Creature — Construct", "power": "0", "toughness": "0", "isCommander": false, "isIn99": true, "percentageOfUse": 100.0, "percentageOfUseByIdentity": 100.0, "avgWinRate": 0.0, "avgDrawRate": 0.0}, {"occurrences": 1, "cardName": "Mana Vault", "card_faces": [], "colorIdentity": "C", "colors": "C", "decklists": [{"commanders": "The Reality Chip", "decks": [{"name": "Bend Reality", "url": "https://www.moxfield.com/decks/fvuyt4A-FESSlVbF1-l3DQ", "commanders": [{"name": "The Reality Chip", "color_identity": ["U"]}]}], "colorIdentity": ["U"]}], "cmc": 1.0, "prices": {"usd": 50.01, "eur": 30.52, "ck": 59.99, "lastUpdatedAtUtc": "2024-06-11T10:48:49.438Z", "ck_buy": 33.0, "ck_buy_qty": 17, "csi": 54.99, "csi_buy": 30.0, "csi_buy_qty": 20, "ct": 44.69}, "reserved": false, "multiplePrintings": true, "lastPrint": "Double Masters 2022", "multiverse_ids": [2057], "type": "Artifact", "typeLine": "Artifact", "power": "", "toughness": "", "isCommander": false, "isIn99": true, "percentageOfUse": 100.0, "percentageOfUseByIdentity": 100.0, "avgWinRate": 0.0, "avgDrawRate": 0.0}, {"occurrences": 1, "cardName": "Manifold Key", "card_faces": [], "colorIdentity": "C", "colors": "C", "decklists": [{"commanders": "The Reality Chip", "decks": [{"name": "Bend Reality", "url": "https://www.moxfield.com/decks/fvuyt4A-FESSlVbF1-l3DQ", "commanders": [{"name": "The Reality Chip", "color_identity": ["U"]}]}], "colorIdentity": ["U"]}], "cmc": 1.0, "prices": {"usd": 0.6, "usd_foil": 5.96, "eur": 0.28, "eur_foil": 4.02, "tix": 0.03, "ck": 0.69, "ck_foil": 7.99, "lastUpdatedAtUtc": "2024-06-11T10:48:49.438Z", "ck_buy": 0.09, "ck_buy_foil": 4.0, "ck_buy_qty": 51, "ck_buy_foil_qty": 3, "csi": 0.35, "csi_foil": 3.99, "csi_buy": 0.1, "csi_buy_foil": 1.5, "csi_buy_qty": 20, "csi_buy_foil_qty": 20, "ct": 0.32, "ct_foil": 4.3}, "reserved": false, "multiplePrintings": true, "lastPrint": "Commander Legends: Battle for Baldur's Gate", "multiverse_ids": [466984], "type": "Artifact", "typeLine": "Artifact", "power": "", "toughness": "", "isCommander": false, "isIn99": true, "percentageOfUse": 100.0, "percentageOfUseByIdentity": 100.0, "avgWinRate": 0.0, "avgDrawRate": 0.0}, {"occurrences": 1, "cardName": "Basalt Monolith", "card_faces": [], "colorIdentity": "C", "colors": "C", "decklists": [{"commanders": "The Reality Chip", "decks": [{"name": "Bend Reality", "url": "https://www.moxfield.com/decks/fvuyt4A-FESSlVbF1-l3DQ", "commanders": [{"name": "The Reality Chip", "color_identity": ["U"]}]}], "colorIdentity": ["U"]}], "cmc": 3.0, "prices": {"usd": 4.13, "usd_foil": 3.84, "eur": 1.58, "eur_foil": 2.83, "tix": 0.15, "ck": 5.49, "ck_foil": 4.99, "lastUpdatedAtUtc": "2024-06-11T10:48:49.438Z", "ck_buy": 2.3, "ck_buy_foil": 2.0, "ck_buy_qty": 36, "ck_buy_foil_qty": 10, "csi": 2.99, "csi_foil": 3.49, "csi_buy": 1.0, "csi_buy_foil": 1.25, "csi_buy_qty": 20, "csi_buy_foil_qty": 20, "ct": 1.77, "ct_foil": 3.07}, "reserved": false, "multiplePrintings": true, "lastPrint": "Tales of Middle-earth Commander", "multiverse_ids": [489905], "type": "Artifact", "typeLine": "Artifact", "power": "", "toughness": "", "isCommander": false, "isIn99": true, "percentageOfUse": 100.0, "percentageOfUseByIdentity": 100.0, "avgWinRate": 0.0, "avgDrawRate": 0.0}, {"occurrences": 1, "cardName": "Buried Ruin", "card_faces": [], "colorIdentity": "C", "colors": "C", "decklists": [{"commanders": "The Reality Chip", "decks": [{"name": "Bend Reality", "url": "https://www.moxfield.com/decks/fvuyt4A-FESSlVbF1-l3DQ", "commanders": [{"name": "The Reality Chip", "color_identity": ["U"]}]}], "colorIdentity": ["U"]}], "cmc": 0, "prices": {"usd": 0.25, "eur": 0.48, "ck": 0.39, "lastUpdatedAtUtc": "2024-06-11T10:48:49.438Z", "ck_buy": 0.04, "ck_buy_qty": 0, "csi": 0.99, "csi_buy": 0.0, "csi_buy_qty": 0, "ct": 0.4}, "reserved": false, "multiplePrintings": true, "lastPrint": "Fallout", "multiverse_ids": [489474], "type": "Land", "typeLine": "Land", "power": "", "toughness": "", "isCommander": false, "isIn99": true, "percentageOfUse": 100.0, "percentageOfUseByIdentity": 100.0, "avgWinRate": 0.0, "avgDrawRate": 0.0}, {"occurrences": 1, "cardName": "Armory Automaton", "card_faces": [], "colorIdentity": "C", "colors": "C", "decklists": [{"commanders": "The Reality Chip", "decks": [{"name": "Bend Reality", "url": "https://www.moxfield.com/decks/fvuyt4A-FESSlVbF1-l3DQ", "commanders": [{"name": "The Reality Chip", "color_identity": ["U"]}]}], "colorIdentity": ["U"]}], "cmc": 3.0, "prices": {"usd": 2.53, "eur": 2.78, "ck": 5.99, "lastUpdatedAtUtc": "2024-06-11T10:48:49.438Z", "ck_buy": 3.0, "csi": 3.49, "csi_buy": 1.0, "ct": 2.6}, "reserved": false, "multiplePrintings": false, "lastPrint": "Commander 2016", "multiverse_ids": [420668], "type": "Creature", "typeLine": "Artifact Creature — Construct", "power": "2", "toughness": "2", "isCommander": false, "isIn99": true, "percentageOfUse": 100.0, "percentageOfUseByIdentity": 100.0, "avgWinRate": 0.0, "avgDrawRate": 0.0}, {"occurrences": 1, "cardName": "Reality Shift", "card_faces": [], "colorIdentity": "U", "colors": "U", "decklists": [{"commanders": "The Reality Chip", "decks": [{"name": "Bend Reality", "url": "https://www.moxfield.com/decks/fvuyt4A-FESSlVbF1-l3DQ", "commanders": [{"name": "The Reality Chip", "color_identity": ["U"]}]}], "colorIdentity": ["U"]}], "cmc": 2.0, "prices": {"usd": 0.36, "eur": 0.64, "ck": 0.79, "lastUpdatedAtUtc": "2024-06-11T10:48:49.438Z", "ck_buy": 0.12, "ck_buy_qty": 16, "csi": 1.99, "csi_buy": 0.0, "csi_buy_qty": 0, "ct": 0.46}, "reserved": false, "multiplePrintings": true, "lastPrint": "Wilds of Eldraine Commander", "multiverse_ids": [470638], "type": "Instant", "typeLine": "Instant", "power": "", "toughness": "", "isCommander": false, "isIn99": true, "percentageOfUse": 100.0, "percentageOfUseByIdentity": 0.0, "avgWinRate": 0.0, "avgDrawRate": 0.0}, {"occurrences": 1, "cardName": "Mishra's Workshop", "card_faces": [], "colorIdentity": "C", "colors": "C", "decklists": [{"commanders": "The Reality Chip", "decks": [{"name": "Bend Reality", "url": "https://www.moxfield.com/decks/fvuyt4A-FESSlVbF1-l3DQ", "commanders": [{"name": "The Reality Chip", "color_identity": ["U"]}]}], "colorIdentity": ["U"]}], "cmc": 0, "prices": {"usd": 2149.98, "eur": 1704.95, "ck": 2999.99, "lastUpdatedAtUtc": "2024-06-11T10:48:49.438Z", "ck_buy": 1950.0, "ck_buy_qty": 5, "csi": 2799.99, "csi_buy": 1600.0, "csi_buy_qty": 20, "ct": 2369.67}, "reserved": true, "multiplePrintings": false, "lastPrint": "Antiquities", "multiverse_ids": [1075], "type": "Land", "typeLine": "Land", "power": "", "toughness": "", "isCommander": false, "isIn99": true, "percentageOfUse": 100.0, "percentageOfUseByIdentity": 100.0, "avgWinRate": 0.0, "avgDrawRate": 0.0}, {"occurrences": 1, "cardName": "Power Artifact", "card_faces": [], "colorIdentity": "U", "colors": "U", "decklists": [{"commanders": "The Reality Chip", "decks": [{"name": "Bend Reality", "url": "https://www.moxfield.com/decks/fvuyt4A-FESSlVbF1-l3DQ", "commanders": [{"name": "The Reality Chip", "color_identity": ["U"]}]}], "colorIdentity": ["U"]}], "cmc": 2.0, "prices": {"usd": 202.85, "eur": 147.98, "ck": 179.99, "lastUpdatedAtUtc": "2024-06-11T10:48:49.438Z", "ck_buy": 85.0, "ck_buy_qty": 0, "csi": 249.99, "csi_buy": 0.05, "csi_buy_qty": 20, "ct": 164.19}, "reserved": true, "multiplePrintings": false, "lastPrint": "Antiquities", "multiverse_ids": [1043], "type": "Enchantment", "typeLine": "Enchantment — Aura", "power": "", "toughness": "", "isCommander": false, "isIn99": true, "percentageOfUse": 100.0, "percentageOfUseByIdentity": 0.0, "avgWinRate": 0.0, "avgDrawRate": 0.0}, {"occurrences": 1, "cardName": "Transmute Artifact", "card_faces": [], "colorIdentity": "U", "colors": "U", "decklists": [{"commanders": "The Reality Chip", "decks": [{"name": "Bend Reality", "url": "https://www.moxfield.com/decks/fvuyt4A-FESSlVbF1-l3DQ", "commanders": [{"name": "The Reality Chip", "color_identity": ["U"]}]}], "colorIdentity": ["U"]}], "cmc": 2.0, "prices": {"usd": 410.87, "eur": 261.79, "ck": 549.99, "lastUpdatedAtUtc": "2024-06-11T10:48:49.438Z", "ck_buy": 330.0, "ck_buy_qty": 13, "csi": 329.99, "csi_buy": 0.05, "csi_buy_qty": 20, "ct": 350.52}, "reserved": true, "multiplePrintings": false, "lastPrint": "Antiquities", "multiverse_ids": [1047], "type": "Sorcery", "typeLine": "Sorcery", "power": "", "toughness": "", "isCommander": false, "isIn99": true, "percentageOfUse": 100.0, "percentageOfUseByIdentity": 0.0, "avgWinRate": 0.0, "avgDrawRate": 0.0}, {"occurrences": 1, "cardName": "Svyelunite Temple", "card_faces": [], "colorIdentity": "U", "colors": "C", "decklists": [{"commanders": "The Reality Chip", "decks": [{"name": "Bend Reality", "url": "https://www.moxfield.com/decks/fvuyt4A-FESSlVbF1-l3DQ", "commanders": [{"name": "The Reality Chip", "color_identity": ["U"]}]}], "colorIdentity": ["U"]}], "cmc": 0, "prices": {"usd": 0.91, "eur": 0.67, "ck": 0.39, "lastUpdatedAtUtc": "2024-06-11T10:48:49.438Z", "ck_buy": 0.04, "ck_buy_qty": 24, "csi": 0.25, "csi_buy": 0.05, "csi_buy_qty": 20, "ct": 0.66}, "reserved": false, "multiplePrintings": true, "lastPrint": "Classic Sixth Edition", "multiverse_ids": [2013], "type": "Land", "typeLine": "Land", "power": "", "toughness": "", "isCommander": false, "isIn99": true, "percentageOfUse": 100.0, "percentageOfUseByIdentity": 0.0, "avgWinRate": 0.0, "avgDrawRate": 0.0}, {"occurrences": 1, "cardName": "Intuition", "card_faces": [], "colorIdentity": "U", "colors": "U", "decklists": [{"commanders": "The Reality Chip", "decks": [{"name": "Bend Reality", "url": "https://www.moxfield.com/decks/fvuyt4A-FESSlVbF1-l3DQ", "commanders": [{"name": "The Reality Chip", "color_identity": ["U"]}]}], "colorIdentity": ["U"]}], "cmc": 3.0, "prices": {"usd": 169.37, "eur": 95.57, "tix": 5.17, "ck": 199.99, "lastUpdatedAtUtc": "2024-06-11T10:48:49.438Z", "ck_buy": 115.0, "csi": 149.99, "csi_buy": 90.0, "ct": 99.94}, "reserved": true, "multiplePrintings": false, "lastPrint": "Tempest", "multiverse_ids": [4707], "type": "Instant", "typeLine": "Instant", "power": "", "toughness": "", "isCommander": false, "isIn99": true, "percentageOfUse": 100.0, "percentageOfUseByIdentity": 0.0, "avgWinRate": 0.0, "avgDrawRate": 0.0}, {"occurrences": 1, "cardName": "Artificer's Intuition", "card_faces": [], "colorIdentity": "U", "colors": "U", "decklists": [{"commanders": "The Reality Chip", "decks": [{"name": "Bend Reality", "url": "https://www.moxfield.com/decks/fvuyt4A-FESSlVbF1-l3DQ", "commanders": [{"name": "The Reality Chip", "color_identity": ["U"]}]}], "colorIdentity": ["U"]}], "cmc": 2.0, "prices": {"usd": 1.64, "usd_foil": 16.19, "eur": 1.62, "eur_foil": 10.74, "tix": 0.02, "ck": 2.29, "ck_foil": 21.99, "lastUpdatedAtUtc": "2024-06-11T10:48:49.438Z", "ck_buy": 0.8, "ck_buy_foil": 13.2, "ck_buy_qty": 6, "ck_buy_foil_qty": 5, "csi": 0.99, "csi_foil": 22.99, "csi_buy": 0.35, "csi_buy_foil": 0.0, "csi_buy_qty": 20, "csi_buy_foil_qty": 0, "ct_foil": 12.17}, "reserved": false, "multiplePrintings": false, "lastPrint": "Fifth Dawn", "multiverse_ids": [50172], "type": "Enchantment", "typeLine": "Enchantment", "power": "", "toughness": "", "isCommander": false, "isIn99": true, "percentageOfUse": 100.0, "percentageOfUseByIdentity": 0.0, "avgWinRate": 0.0, "avgDrawRate": 0.0}, {"occurrences": 1, "cardName": "Staff of Domination", "card_faces": [], "colorIdentity": "C", "colors": "C", "decklists": [{"commanders": "The Reality Chip", "decks": [{"name": "Bend Reality", "url": "https://www.moxfield.com/decks/fvuyt4A-FESSlVbF1-l3DQ", "commanders": [{"name": "The Reality Chip", "color_identity": ["U"]}]}], "colorIdentity": ["U"]}], "cmc": 3.0, "prices": {"usd": 3.96, "usd_foil": 4.65, "eur": 2.53, "eur_foil": 3.95, "tix": 0.03, "ck": 4.49, "ck_foil": 4.99, "lastUpdatedAtUtc": "2024-06-11T10:48:49.438Z", "ck_buy": 2.5, "ck_buy_foil": 1.75, "ck_buy_qty": 36, "ck_buy_foil_qty": 1, "csi": 2.49, "csi_foil": 3.49, "csi_buy": 1.0, "csi_buy_foil": 1.25, "csi_buy_qty": 20, "csi_buy_foil_qty": 20, "ct": 3.63, "ct_foil": 3.28}, "reserved": false, "multiplePrintings": true, "lastPrint": "Commander Legends", "multiverse_ids": [586606], "type": "Artifact", "typeLine": "Artifact", "power": "", "toughness": "", "isCommander": false, "isIn99": true, "percentageOfUse": 100.0, "percentageOfUseByIdentity": 100.0, "avgWinRate": 0.0, "avgDrawRate": 0.0}, {"occurrences": 1, "cardName": "Minamo, School at Water's Edge", "card_faces": [], "colorIdentity": "U", "colors": "C", "decklists": [{"commanders": "The Reality Chip", "decks": [{"name": "Bend Reality", "url": "https://www.moxfield.com/decks/fvuyt4A-FESSlVbF1-l3DQ", "commanders": [{"name": "The Reality Chip", "color_identity": ["U"]}]}], "colorIdentity": ["U"]}], "cmc": 0, "prices": {"usd": 49.72, "usd_foil": 49.2, "eur": 32.87, "eur_foil": 36.33, "tix": 1.84, "ck": 64.99, "ck_foil": 49.99, "lastUpdatedAtUtc": "2024-06-11T10:48:49.438Z", "ck_buy": 39.0, "ck_buy_foil": 20.0, "ck_buy_qty": 12, "ck_buy_foil_qty": 1, "csi": 54.99, "csi_foil": 59.99, "csi_buy": 28.0, "csi_buy_foil": 0.0, "csi_buy_qty": 20, "csi_buy_foil_qty": 0, "ct": 35.41, "ct_foil": 36.35}, "reserved": false, "multiplePrintings": true, "lastPrint": "Tales of Middle-earth Commander", "multiverse_ids": [622601], "type": "Land", "typeLine": "Legendary Land", "power": "", "toughness": "", "isCommander": false, "isIn99": true, "percentageOfUse": 100.0, "percentageOfUseByIdentity": 0.0, "avgWinRate": 0.0, "avgDrawRate": 0.0}, {"occurrences": 1, "cardName": "Sensei's Divining Top", "card_faces": [], "colorIdentity": "C", "colors": "C", "decklists": [{"commanders": "The Reality Chip", "decks": [{"name": "Bend Reality", "url": "https://www.moxfield.com/decks/fvuyt4A-FESSlVbF1-l3DQ", "commanders": [{"name": "The Reality Chip", "color_identity": ["U"]}]}], "colorIdentity": ["U"]}], "cmc": 1.0, "prices": {"usd": 27.14, "usd_foil": 87.87, "eur": 11.26, "eur_foil": 57.05, "tix": 0.07, "ck": 27.99, "ck_foil": 79.99, "lastUpdatedAtUtc": "2024-06-11T10:48:49.438Z", "ck_buy": 16.0, "ck_buy_foil": 40.0, "ck_buy_qty": 30, "ck_buy_foil_qty": 5, "csi": 24.99, "csi_foil": 89.99, "csi_buy": 15.0, "csi_buy_foil": 0.0, "csi_buy_qty": 20, "csi_buy_foil_qty": 0, "ct": 12.14, "ct_foil": 66.17}, "reserved": false, "multiplePrintings": true, "lastPrint": "Double Masters 2022", "multiverse_ids": [50400], "type": "Artifact", "typeLine": "Artifact", "power": "", "toughness": "", "isCommander": false, "isIn99": true, "percentageOfUse": 100.0, "percentageOfUseByIdentity": 100.0, "avgWinRate": 0.0, "avgDrawRate": 0.0}, {"occurrences": 1, "cardName": "Cloud Key", "card_faces": [], "colorIdentity": "C", "colors": "C", "decklists": [{"commanders": "The Reality Chip", "decks": [{"name": "Bend Reality", "url": "https://www.moxfield.com/decks/fvuyt4A-FESSlVbF1-l3DQ", "commanders": [{"name": "The Reality Chip", "color_identity": ["U"]}]}], "colorIdentity": ["U"]}], "cmc": 3.0, "prices": {"usd": 2.29, "usd_foil": 2.75, "eur": 1.53, "eur_foil": 2.81, "tix": 0.02, "ck": 2.49, "ck_foil": 3.49, "lastUpdatedAtUtc": "2024-06-11T10:48:49.438Z", "ck_buy": 1.15, "ck_buy_foil": 1.4, "ck_buy_qty": 52, "ck_buy_foil_qty": 6, "csi": 0.99, "csi_foil": 1.99, "csi_buy": 0.0, "csi_buy_foil": 0.25, "csi_buy_qty": 0, "csi_buy_foil_qty": 20, "ct": 1.52, "ct_foil": 1.97}, "reserved": false, "multiplePrintings": true, "lastPrint": "Time Spiral Remastered", "multiverse_ids": [586562], "type": "Artifact", "typeLine": "Artifact", "power": "", "toughness": "", "isCommander": false, "isIn99": true, "percentageOfUse": 100.0, "percentageOfUseByIdentity": 100.0, "avgWinRate": 0.0, "avgDrawRate": 0.0}, {"occurrences": 1, "cardName": "Force of Will", "card_faces": [], "colorIdentity": "U", "colors": "U", "decklists": [{"commanders": "The Reality Chip", "decks": [{"name": "Bend Reality", "url": "https://www.moxfield.com/decks/fvuyt4A-FESSlVbF1-l3DQ", "commanders": [{"name": "The Reality Chip", "color_identity": ["U"]}]}], "colorIdentity": ["U"]}], "cmc": 5.0, "prices": {"usd": 58.19, "usd_foil": 61.21, "eur": 53.7, "eur_foil": 58.26, "tix": 15.68, "ck": 64.99, "ck_foil": 84.99, "lastUpdatedAtUtc": "2024-06-11T10:48:49.438Z", "ck_buy": 33.0, "ck_buy_foil": 34.0, "ck_buy_qty": 8, "ck_buy_foil_qty": 0, "csi": 64.99, "csi_foil": 69.99, "csi_buy": 35.0, "csi_buy_foil": 35.0, "csi_buy_qty": 20, "csi_buy_foil_qty": 20, "ct": 62.34, "ct_foil": 69.67}, "reserved": false, "multiplePrintings": true, "lastPrint": "Dominaria Remastered", "multiverse_ids": [598924], "type": "Instant", "typeLine": "Instant", "power": "", "toughness": "", "isCommander": false, "isIn99": true, "percentageOfUse": 100.0, "percentageOfUseByIdentity": 0.0, "avgWinRate": 0.0, "avgDrawRate": 0.0}, {"occurrences": 1, "cardName": "Mystic Remora", "card_faces": [], "colorIdentity": "U", "colors": "U", "decklists": [{"commanders": "The Reality Chip", "decks": [{"name": "Bend Reality", "url": "https://www.moxfield.com/decks/fvuyt4A-FESSlVbF1-l3DQ", "commanders": [{"name": "The Reality Chip", "color_identity": ["U"]}]}], "colorIdentity": ["U"]}], "cmc": 1.0, "prices": {"usd": 7.73, "usd_foil": 6.83, "eur": 5.49, "eur_foil": 6.76, "tix": 4.15, "ck": 8.99, "ck_foil": 6.99, "lastUpdatedAtUtc": "2024-06-11T10:48:49.438Z", "ck_buy": 5.0, "ck_buy_foil": 3.5, "ck_buy_qty": 23, "ck_buy_foil_qty": 16, "csi": 6.99, "csi_foil": 6.99, "csi_buy": 0.0, "csi_buy_foil": 3.5, "csi_buy_qty": 0, "csi_buy_foil_qty": 20, "ct": 7.17, "ct_foil": 8.01}, "reserved": false, "multiplePrintings": true, "lastPrint": "Dominaria Remastered", "multiverse_ids": [598933], "type": "Enchantment", "typeLine": "Enchantment", "power": "", "toughness": "", "isCommander": false, "isIn99": true, "percentageOfUse": 100.0, "percentageOfUseByIdentity": 0.0, "avgWinRate": 0.0, "avgDrawRate": 0.0}, {"occurrences": 1, "cardName": "Mystical Tutor", "card_faces": [], "colorIdentity": "U", "colors": "U", "decklists": [{"commanders": "The Reality Chip", "decks": [{"name": "Bend Reality", "url": "https://www.moxfield.com/decks/fvuyt4A-FESSlVbF1-l3DQ", "commanders": [{"name": "The Reality Chip", "color_identity": ["U"]}]}], "colorIdentity": ["U"]}], "cmc": 1.0, "prices": {"usd": 9.93, "usd_foil": 10.89, "eur": 7.68, "eur_foil": 7.65, "tix": 0.34, "ck": 13.99, "ck_foil": 12.99, "lastUpdatedAtUtc": "2024-06-11T10:48:49.438Z", "ck_buy": 7.0, "ck_buy_foil": 5.2, "ck_buy_qty": 25, "ck_buy_foil_qty": 0, "csi": 9.99, "csi_foil": 9.99, "csi_buy": 5.0, "csi_buy_foil": 5.0, "csi_buy_qty": 20, "csi_buy_foil_qty": 20, "ct": 9.23, "ct_foil": 9.95}, "reserved": false, "multiplePrintings": true, "lastPrint": "Dominaria Remastered", "multiverse_ids": [598934], "type": "Instant", "typeLine": "Instant", "power": "", "toughness": "", "isCommander": false, "isIn99": true, "percentageOfUse": 100.0, "percentageOfUseByIdentity": 0.0, "avgWinRate": 0.0, "avgDrawRate": 0.0}, {"occurrences": 1, "cardName": "Etherium Sculptor", "card_faces": [], "colorIdentity": "U", "colors": "U", "decklists": [{"commanders": "The Reality Chip", "decks": [{"name": "Bend Reality", "url": "https://www.moxfield.com/decks/fvuyt4A-FESSlVbF1-l3DQ", "commanders": [{"name": "The Reality Chip", "color_identity": ["U"]}]}], "colorIdentity": ["U"]}], "cmc": 2.0, "prices": {"usd": 0.82, "usd_foil": 4.76, "eur": 0.32, "eur_foil": 2.05, "tix": 0.03, "ck": 0.99, "ck_foil": 3.49, "lastUpdatedAtUtc": "2024-06-11T10:48:49.438Z", "ck_buy": 0.25, "ck_buy_foil": 1.4, "ck_buy_qty": 49, "ck_buy_foil_qty": 3, "csi": 0.59, "csi_foil": 2.99, "csi_buy": 0.15, "csi_buy_foil": 0.0, "csi_buy_qty": 20, "csi_buy_foil_qty": 0, "ct": 0.39, "ct_foil": 3.03}, "reserved": false, "multiplePrintings": true, "lastPrint": "The Brothers' War Commander", "multiverse_ids": [176435], "type": "Creature", "typeLine": "Artifact Creature — Vedalken Artificer", "power": "1", "toughness": "2", "isCommander": false, "isIn99": true, "percentageOfUse": 100.0, "percentageOfUseByIdentity": 0.0, "avgWinRate": 0.0, "avgDrawRate": 0.0}, {"occurrences": 1, "cardName": "Spellseeker", "card_faces": [], "colorIdentity": "U", "colors": "U", "decklists": [{"commanders": "The Reality Chip", "decks": [{"name": "Bend Reality", "url": "https://www.moxfield.com/decks/fvuyt4A-FESSlVbF1-l3DQ", "commanders": [{"name": "The Reality Chip", "color_identity": ["U"]}]}], "colorIdentity": ["U"]}], "cmc": 3.0, "prices": {"usd": 11.26, "usd_foil": 14.13, "eur": 12.69, "eur_foil": 13.22, "tix": 5.97, "ck": 12.99, "ck_foil": 22.99, "lastUpdatedAtUtc": "2024-06-11T10:48:49.438Z", "ck_buy": 6.5, "ck_buy_foil": 11.5, "ck_buy_qty": 21, "ck_buy_foil_qty": 5, "csi": 10.99, "csi_foil": 24.99, "csi_buy": 4.5, "csi_buy_foil": 12.0, "csi_buy_qty": 20, "csi_buy_foil_qty": 20, "ct": 12.17, "ct_foil": 19.28}, "reserved": false, "multiplePrintings": true, "lastPrint": "Commander Masters", "multiverse_ids": [446009], "type": "Creature", "typeLine": "Creature — Human Wizard", "power": "1", "toughness": "1", "isCommander": false, "isIn99": true, "percentageOfUse": 100.0, "percentageOfUseByIdentity": 0.0, "avgWinRate": 0.0, "avgDrawRate": 0.0}, {"occurrences": 1, "cardName": "Chrome Mox", "card_faces": [], "colorIdentity": "C", "colors": "C", "decklists": [{"commanders": "The Reality Chip", "decks": [{"name": "Bend Reality", "url": "https://www.moxfield.com/decks/fvuyt4A-FESSlVbF1-l3DQ", "commanders": [{"name": "The Reality Chip", "color_identity": ["U"]}]}], "colorIdentity": ["U"]}], "cmc": 0, "prices": {"usd": 110.28, "usd_foil": 113.82, "eur": 65.68, "eur_foil": 82.55, "tix": 5.37, "ck": 119.99, "ck_foil": 159.99, "lastUpdatedAtUtc": "2024-06-11T10:48:49.438Z", "ck_buy": 75.0, "ck_buy_foil": 96.0, "csi": 119.99, "csi_foil": 129.99, "csi_buy": 70.0, "csi_buy_foil": 70.0, "ct": 113.98, "ct_foil": 128.18}, "reserved": false, "multiplePrintings": true, "lastPrint": "Double Masters", "multiverse_ids": [413761], "type": "Artifact", "typeLine": "Artifact", "power": "", "toughness": "", "isCommander": false, "isIn99": true, "percentageOfUse": 100.0, "percentageOfUseByIdentity": 100.0, "avgWinRate": 0.0, "avgDrawRate": 0.0}, {"occurrences": 1, "cardName": "Ancient Tomb", "card_faces": [], "colorIdentity": "C", "colors": "C", "decklists": [{"commanders": "The Reality Chip", "decks": [{"name": "Bend Reality", "url": "https://www.moxfield.com/decks/fvuyt4A-FESSlVbF1-l3DQ", "commanders": [{"name": "The Reality Chip", "color_identity": ["U"]}]}], "colorIdentity": ["U"]}], "cmc": 0, "prices": {"usd": 88.74, "eur": 61.84, "tix": 22.62, "ck": 109.99, "lastUpdatedAtUtc": "2024-06-11T10:48:49.438Z", "ck_buy": 55.0, "ck_buy_qty": 27, "csi": 94.99, "csi_buy": 50.0, "csi_buy_qty": 20, "ct": 81.47}, "reserved": false, "multiplePrintings": true, "lastPrint": "Tales of Middle-earth Commander", "multiverse_ids": [4636], "type": "Land", "typeLine": "Land", "power": "", "toughness": "", "isCommander": false, "isIn99": true, "percentageOfUse": 100.0, "percentageOfUseByIdentity": 100.0, "avgWinRate": 0.0, "avgDrawRate": 0.0}, {"occurrences": 1, "cardName": "Deranged Assistant", "card_faces": [], "colorIdentity": "U", "colors": "U", "decklists": [{"commanders": "The Reality Chip", "decks": [{"name": "Bend Reality", "url": "https://www.moxfield.com/decks/fvuyt4A-FESSlVbF1-l3DQ", "commanders": [{"name": "The Reality Chip", "color_identity": ["U"]}]}], "colorIdentity": ["U"]}], "cmc": 2.0, "prices": {"usd": 0.07, "usd_foil": 0.15, "eur": 0.08, "eur_foil": 0.21, "tix": 0.05, "ck": 0.35, "ck_foil": 0.49, "lastUpdatedAtUtc": "2024-06-11T10:48:49.438Z", "ck_buy": 0.03, "ck_buy_foil": 0.08, "ck_buy_qty": 0, "ck_buy_foil_qty": 0, "csi": 0.49, "csi_foil": 0.25, "csi_buy": 0.0, "csi_buy_foil": 0.0, "csi_buy_qty": 0, "csi_buy_foil_qty": 0, "ct": 0.05, "ct_foil": 0.12}, "reserved": false, "multiplePrintings": true, "lastPrint": "Commander Masters", "multiverse_ids": [456645], "type": "Creature", "typeLine": "Creature — Human Wizard", "power": "1", "toughness": "1", "isCommander": false, "isIn99": true, "percentageOfUse": 100.0, "percentageOfUseByIdentity": 0.0, "avgWinRate": 0.0, "avgDrawRate": 0.0}, {"occurrences": 1, "cardName": "Inventors' Fair", "card_faces": [], "colorIdentity": "C", "colors": "C", "decklists": [{"commanders": "The Reality Chip", "decks": [{"name": "Bend Reality", "url": "https://www.moxfield.com/decks/fvuyt4A-FESSlVbF1-l3DQ", "commanders": [{"name": "The Reality Chip", "color_identity": ["U"]}]}], "colorIdentity": ["U"]}], "cmc": 0, "prices": {"usd": 14.59, "usd_foil": 27.48, "eur": 10.61, "eur_foil": 20.42, "tix": 0.02, "ck": 18.99, "ck_foil": 37.99, "lastUpdatedAtUtc": "2024-06-11T10:48:49.438Z", "ck_buy": 9.5, "ck_buy_foil": 15.2, "csi": 15.99, "csi_foil": 24.99, "csi_buy": 8.0, "csi_buy_foil": 13.0, "ct": 11.51, "ct_foil": 22.32}, "reserved": false, "multiplePrintings": false, "lastPrint": "Kaladesh", "multiverse_ids": [417820], "type": "Land", "typeLine": "Legendary Land", "power": "", "toughness": "", "isCommander": false, "isIn99": true, "percentageOfUse": 100.0, "percentageOfUseByIdentity": 100.0, "avgWinRate": 0.0, "avgDrawRate": 0.0}, {"occurrences": 1, "cardName": "Scrap Trawler", "card_faces": [], "colorIdentity": "C", "colors": "C", "decklists": [{"commanders": "The Reality Chip", "decks": [{"name": "Bend Reality", "url": "https://www.moxfield.com/decks/fvuyt4A-FESSlVbF1-l3DQ", "commanders": [{"name": "The Reality Chip", "color_identity": ["U"]}]}], "colorIdentity": ["U"]}], "cmc": 3.0, "prices": {"usd": 0.4, "usd_foil": 1.97, "eur": 0.39, "eur_foil": 1.42, "tix": 0.02, "ck": 1.29, "ck_foil": 2.99, "lastUpdatedAtUtc": "2024-06-11T10:48:49.438Z", "ck_buy": 0.26, "ck_buy_foil": 0.9, "ck_buy_qty": 21, "ck_buy_foil_qty": 4, "csi": 0.99, "csi_foil": 2.49, "csi_buy": 0.0, "csi_buy_foil": 0.0, "csi_buy_qty": 0, "csi_buy_foil_qty": 0, "ct": 0.33, "ct_foil": 1.31}, "reserved": false, "multiplePrintings": true, "lastPrint": "March of the Machine Commander", "multiverse_ids": [423842], "type": "Creature", "typeLine": "Artifact Creature — Construct", "power": "3", "toughness": "2", "isCommander": false, "isIn99": true, "percentageOfUse": 100.0, "percentageOfUseByIdentity": 100.0, "avgWinRate": 0.0, "avgDrawRate": 0.0}, {"occurrences": 1, "cardName": "Cyclonic Rift", "card_faces": [], "colorIdentity": "U", "colors": "U", "decklists": [{"commanders": "The Reality Chip", "decks": [{"name": "Bend Reality", "url": "https://www.moxfield.com/decks/fvuyt4A-FESSlVbF1-l3DQ", "commanders": [{"name": "The Reality Chip", "color_identity": ["U"]}]}], "colorIdentity": ["U"]}], "cmc": 2.0, "prices": {"usd": 28.47, "usd_foil": 35.55, "eur": 24.67, "eur_foil": 25.82, "tix": 0.13, "ck": 39.99, "ck_foil": 44.99, "lastUpdatedAtUtc": "2024-06-11T10:48:49.438Z", "ck_buy": 22.0, "ck_buy_foil": 18.0, "ck_buy_qty": 20, "ck_buy_foil_qty": 1, "csi": 34.99, "csi_foil": 34.99, "csi_buy": 18.0, "csi_buy_foil": 18.0, "csi_buy_qty": 20, "csi_buy_foil_qty": 20, "ct": 27.86, "ct_foil": 30.27}, "reserved": false, "multiplePrintings": true, "lastPrint": "Ravnica Remastered", "multiverse_ids": [425860], "type": "Instant", "typeLine": "Instant", "power": "", "toughness": "", "isCommander": false, "isIn99": true, "percentageOfUse": 100.0, "percentageOfUseByIdentity": 0.0, "avgWinRate": 0.0, "avgDrawRate": 0.0}, {"occurrences": 1, "cardName": "Mox Diamond", "card_faces": [], "colorIdentity": "C", "colors": "C", "decklists": [{"commanders": "The Reality Chip", "decks": [{"name": "Bend Reality", "url": "https://www.moxfield.com/decks/fvuyt4A-FESSlVbF1-l3DQ", "commanders": [{"name": "The Reality Chip", "color_identity": ["U"]}]}], "colorIdentity": ["U"]}], "cmc": 0, "prices": {"usd": 583.05, "eur": 393.26, "tix": 16.33, "ck": 799.99, "lastUpdatedAtUtc": "2024-06-11T10:48:49.438Z", "ck_buy": 480.0, "ck_buy_qty": 23, "csi": 649.99, "csi_buy": 390.0, "csi_buy_qty": 20, "ct": 496.66}, "reserved": true, "multiplePrintings": true, "lastPrint": "From the Vault: Relics", "multiverse_ids": [5193], "type": "Artifact", "typeLine": "Artifact", "power": "", "toughness": "", "isCommander": false, "isIn99": true, "percentageOfUse": 100.0, "percentageOfUseByIdentity": 100.0, "avgWinRate": 0.0, "avgDrawRate": 0.0}, {"occurrences": 1, "cardName": "Academy Ruins", "card_faces": [], "colorIdentity": "U", "colors": "C", "decklists": [{"commanders": "The Reality Chip", "decks": [{"name": "Bend Reality", "url": "https://www.moxfield.com/decks/fvuyt4A-FESSlVbF1-l3DQ", "commanders": [{"name": "The Reality Chip", "color_identity": ["U"]}]}], "colorIdentity": ["U"]}], "cmc": 0, "prices": {"usd": 15.25, "usd_foil": 16.01, "ck": 17.99, "ck_foil": 16.99, "lastUpdatedAtUtc": "2024-06-11T10:48:49.438Z", "ck_buy": 11.0, "ck_buy_foil": 10.25, "csi": 15.99, "csi_foil": 19.99, "csi_buy": 5.0, "csi_buy_foil": 6.0, "ct": 13.0, "ct_foil": 13.17}, "reserved": false, "multiplePrintings": true, "lastPrint": "Double Masters", "multiverse_ids": [0], "type": "Land", "typeLine": "Legendary Land", "power": "", "toughness": "", "isCommander": false, "isIn99": true, "percentageOfUse": 100.0, "percentageOfUseByIdentity": 0.0, "avgWinRate": 0.0, "avgDrawRate": 0.0}, {"occurrences": 1, "cardName": "Flusterstorm", "card_faces": [], "colorIdentity": "U", "colors": "U", "decklists": [{"commanders": "The Reality Chip", "decks": [{"name": "Bend Reality", "url": "https://www.moxfield.com/decks/fvuyt4A-FESSlVbF1-l3DQ", "commanders": [{"name": "The Reality Chip", "color_identity": ["U"]}]}], "colorIdentity": ["U"]}], "cmc": 1.0, "prices": {"usd": 25.56, "eur": 8.62, "tix": 2.14, "ck": 27.99, "lastUpdatedAtUtc": "2024-06-11T10:48:49.438Z", "ck_buy": 13.0, "ck_buy_qty": 0}, "reserved": false, "multiplePrintings": true, "lastPrint": "Modern Horizons 3", "multiverse_ids": [466744], "type": "Instant", "typeLine": "Instant", "power": "", "toughness": "", "isCommander": false, "isIn99": true, "percentageOfUse": 100.0, "percentageOfUseByIdentity": 0.0, "avgWinRate": 0.0, "avgDrawRate": 0.0}, {"occurrences": 1, "cardName": "Seat of the Synod", "card_faces": [], "colorIdentity": "U", "colors": "C", "decklists": [{"commanders": "The Reality Chip", "decks": [{"name": "Bend Reality", "url": "https://www.moxfield.com/decks/fvuyt4A-FESSlVbF1-l3DQ", "commanders": [{"name": "The Reality Chip", "color_identity": ["U"]}]}], "colorIdentity": ["U"]}], "cmc": 0, "prices": {"usd": 1.15, "eur": 1.23, "ck": 1.99, "lastUpdatedAtUtc": "2024-06-11T10:48:49.438Z", "ck_buy": 1.0, "ck_buy_qty": 70, "csi": 1.49, "csi_buy": 0.25, "csi_buy_qty": 20, "ct": 1.5}, "reserved": false, "multiplePrintings": true, "lastPrint": "Jumpstart 2022", "multiverse_ids": [596237], "type": "Land", "typeLine": "Artifact Land", "power": "", "toughness": "", "isCommander": false, "isIn99": true, "percentageOfUse": 100.0, "percentageOfUseByIdentity": 0.0, "avgWinRate": 0.0, "avgDrawRate": 0.0}, {"occurrences": 1, "cardName": "Silver Myr", "card_faces": [], "colorIdentity": "U", "colors": "C", "decklists": [{"commanders": "The Reality Chip", "decks": [{"name": "Bend Reality", "url": "https://www.moxfield.com/decks/fvuyt4A-FESSlVbF1-l3DQ", "commanders": [{"name": "The Reality Chip", "color_identity": ["U"]}]}], "colorIdentity": ["U"]}], "cmc": 2.0, "prices": {"usd": 0.27, "usd_foil": 10.74, "eur": 0.19, "eur_foil": 5.31, "tix": 0.03, "ck": 0.69, "ck_foil": 9.99, "lastUpdatedAtUtc": "2024-06-11T10:48:49.438Z", "ck_buy": 0.07, "ck_buy_foil": 5.0, "ck_buy_qty": 0, "ck_buy_foil_qty": 8, "csi": 0.49, "csi_foil": 1.49, "csi_buy": 0.02, "csi_buy_foil": 0.0, "csi_buy_qty": 20, "csi_buy_foil_qty": 0, "ct": 0.21, "ct_foil": 5.72}, "reserved": false, "multiplePrintings": true, "lastPrint": "Neon Dynasty Commander", "multiverse_ids": [194378], "type": "Creature", "typeLine": "Artifact Creature — Myr", "power": "1", "toughness": "1", "isCommander": false, "isIn99": true, "percentageOfUse": 100.0, "percentageOfUseByIdentity": 0.0, "avgWinRate": 0.0, "avgDrawRate": 0.0}, {"occurrences": 1, "cardName": "Mox Opal", "card_faces": [], "colorIdentity": "C", "colors": "C", "decklists": [{"commanders": "The Reality Chip", "decks": [{"name": "Bend Reality", "url": "https://www.moxfield.com/decks/fvuyt4A-FESSlVbF1-l3DQ", "commanders": [{"name": "The Reality Chip", "color_identity": ["U"]}]}], "colorIdentity": ["U"]}], "cmc": 0, "prices": {"usd": 87.88, "usd_foil": 92.62, "eur": 65.87, "eur_foil": 73.7, "tix": 7.18, "ck": 99.99, "ck_foil": 129.99, "lastUpdatedAtUtc": "2024-06-11T10:48:49.438Z", "ck_buy": 55.0, "ck_buy_foil": 78.0, "ck_buy_qty": 16, "ck_buy_foil_qty": 5, "csi": 94.99, "csi_foil": 99.99, "csi_buy": 58.0, "csi_buy_foil": 55.0, "csi_buy_qty": 20, "csi_buy_foil_qty": 20, "ct": 65.52, "ct_foil": 75.47}, "reserved": false, "multiplePrintings": true, "lastPrint": "Double Masters", "multiverse_ids": [489948], "type": "Artifact", "typeLine": "Legendary Artifact", "power": "", "toughness": "", "isCommander": false, "isIn99": true, "percentageOfUse": 100.0, "percentageOfUseByIdentity": 100.0, "avgWinRate": 0.0, "avgDrawRate": 0.0}, {"occurrences": 1, "cardName": "Semblance Anvil", "card_faces": [], "colorIdentity": "C", "colors": "C", "decklists": [{"commanders": "The Reality Chip", "decks": [{"name": "Bend Reality", "url": "https://www.moxfield.com/decks/fvuyt4A-FESSlVbF1-l3DQ", "commanders": [{"name": "The Reality Chip", "color_identity": ["U"]}]}], "colorIdentity": ["U"]}], "cmc": 3.0, "prices": {"usd": 0.96, "usd_foil": 0.99, "eur": 0.74, "eur_foil": 1.16, "tix": 0.02, "ck": 1.49, "ck_foil": 0.99, "lastUpdatedAtUtc": "2024-06-11T10:48:49.438Z", "ck_buy": 0.6, "ck_buy_foil": 0.15, "ck_buy_qty": 33, "ck_buy_foil_qty": 1, "csi": 0.99, "csi_foil": 1.99, "csi_buy": 0.0, "csi_buy_foil": 0.0, "csi_buy_qty": 0, "csi_buy_foil_qty": 0, "ct": 0.57, "ct_foil": 1.1}, "reserved": false, "multiplePrintings": false, "lastPrint": "Scars of Mirrodin", "multiverse_ids": [586602], "type": "Artifact", "typeLine": "Artifact", "power": "", "toughness": "", "isCommander": false, "isIn99": true, "percentageOfUse": 100.0, "percentageOfUseByIdentity": 100.0, "avgWinRate": 0.0, "avgDrawRate": 0.0}, {"occurrences": 1, "cardName": "Tezzeret the Seeker", "card_faces": [], "colorIdentity": "U", "colors": "U", "decklists": [{"commanders": "The Reality Chip", "decks": [{"name": "Bend Reality", "url": "https://www.moxfield.com/decks/fvuyt4A-FESSlVbF1-l3DQ", "commanders": [{"name": "The Reality Chip", "color_identity": ["U"]}]}], "colorIdentity": ["U"]}], "cmc": 5.0, "prices": {"usd": 21.36, "usd_foil": 24.43, "eur": 11.07, "eur_foil": 12.46, "tix": 0.03, "ck": 24.99, "ck_foil": 34.99, "lastUpdatedAtUtc": "2024-06-11T10:48:49.438Z", "ck_buy": 14.5, "ck_buy_foil": 14.0, "ck_buy_qty": 13, "ck_buy_foil_qty": 0, "csi": 19.99, "csi_foil": 24.99, "csi_buy": 10.0, "csi_buy_foil": 13.0, "csi_buy_qty": 20, "csi_buy_foil_qty": 20, "ct": 11.16, "ct_foil": 20.12}, "reserved": false, "multiplePrintings": true, "lastPrint": "Modern Masters 2015", "multiverse_ids": [397700], "type": "Planeswalker", "typeLine": "Legendary Planeswalker — Tezzeret", "power": "", "toughness": "", "isCommander": false, "isIn99": true, "percentageOfUse": 100.0, "percentageOfUseByIdentity": 0.0, "avgWinRate": 0.0, "avgDrawRate": 0.0}, {"occurrences": 1, "cardName": "Fabricate", "card_faces": [], "colorIdentity": "U", "colors": "U", "decklists": [{"commanders": "The Reality Chip", "decks": [{"name": "Bend Reality", "url": "https://www.moxfield.com/decks/fvuyt4A-FESSlVbF1-l3DQ", "commanders": [{"name": "The Reality Chip", "color_identity": ["U"]}]}], "colorIdentity": ["U"]}], "cmc": 3.0, "prices": {"usd": 5.79, "eur": 4.34, "ck": 6.49, "lastUpdatedAtUtc": "2024-01-20T01:49:14.997Z", "ck_buy": 3.7, "ck_buy_qty": 10, "ct": 4.77}, "reserved": false, "multiplePrintings": true, "lastPrint": "Warhammer 40,000 Commander", "multiverse_ids": [0], "type": "Sorcery", "typeLine": "Sorcery", "power": "", "toughness": "", "isCommander": false, "isIn99": true, "percentageOfUse": 100.0, "percentageOfUseByIdentity": 0.0, "avgWinRate": 0.0, "avgDrawRate": 0.0}, {"occurrences": 1, "cardName": "Reshape", "card_faces": [], "colorIdentity": "U", "colors": "U", "decklists": [{"commanders": "The Reality Chip", "decks": [{"name": "Bend Reality", "url": "https://www.moxfield.com/decks/fvuyt4A-FESSlVbF1-l3DQ", "commanders": [{"name": "The Reality Chip", "color_identity": ["U"]}]}], "colorIdentity": ["U"]}], "cmc": 2.0, "prices": {"usd": 2.94, "usd_foil": 22.9, "eur": 1.03, "eur_foil": 9.41, "tix": 0.02, "ck": 4.99, "ck_foil": 27.99, "lastUpdatedAtUtc": "2024-06-11T10:48:49.438Z", "ck_buy": 2.0, "ck_buy_foil": 14.0, "ck_buy_qty": 17, "ck_buy_foil_qty": 4, "csi": 2.99, "csi_foil": 21.99, "csi_buy": 1.0, "csi_buy_foil": 0.0, "csi_buy_qty": 20, "csi_buy_foil_qty": 0, "ct_foil": 9.1}, "reserved": false, "multiplePrintings": true, "lastPrint": "Double Masters", "multiverse_ids": [48147], "type": "Sorcery", "typeLine": "Sorcery", "power": "", "toughness": "", "isCommander": false, "isIn99": true, "percentageOfUse": 100.0, "percentageOfUseByIdentity": 0.0, "avgWinRate": 0.0, "avgDrawRate": 0.0}, {"occurrences": 1, "cardName": "Saprazzan Skerry", "card_faces": [], "colorIdentity": "U", "colors": "C", "decklists": [{"commanders": "The Reality Chip", "decks": [{"name": "Bend Reality", "url": "https://www.moxfield.com/decks/fvuyt4A-FESSlVbF1-l3DQ", "commanders": [{"name": "The Reality Chip", "color_identity": ["U"]}]}], "colorIdentity": ["U"]}], "cmc": 0, "prices": {"usd": 1.9, "usd_foil": 42.49, "eur": 2.42, "eur_foil": 23.11, "tix": 5.68, "ck": 2.29, "ck_foil": 44.99, "lastUpdatedAtUtc": "2024-06-11T10:48:49.438Z", "ck_buy": 0.8, "ck_buy_foil": 22.5, "ck_buy_qty": 55, "ck_buy_foil_qty": 4, "csi": 1.49, "csi_foil": 39.99, "csi_buy": 0.25, "csi_buy_foil": 0.0, "csi_buy_qty": 20, "csi_buy_foil_qty": 0, "ct": 2.57, "ct_foil": 40.95}, "reserved": false, "multiplePrintings": false, "lastPrint": "Mercadian Masques", "multiverse_ids": [19643], "type": "Land", "typeLine": "Land", "power": "", "toughness": "", "isCommander": false, "isIn99": true, "percentageOfUse": 100.0, "percentageOfUseByIdentity": 0.0, "avgWinRate": 0.0, "avgDrawRate": 0.0}, {"occurrences": 1, "cardName": "Grim Monolith", "card_faces": [], "colorIdentity": "C", "colors": "C", "decklists": [{"commanders": "The Reality Chip", "decks": [{"name": "Bend Reality", "url": "https://www.moxfield.com/decks/fvuyt4A-FESSlVbF1-l3DQ", "commanders": [{"name": "The Reality Chip", "color_identity": ["U"]}]}], "colorIdentity": ["U"]}], "cmc": 2.0, "prices": {"usd": 274.04, "usd_foil": 2662.99, "eur": 186.41, "eur_foil": 1369.36, "tix": 13.35, "ck": 299.99, "ck_foil": 2999.99, "lastUpdatedAtUtc": "2024-06-11T10:48:49.438Z", "ck_buy": 160.0, "ck_buy_foil": 1500.0, "ck_buy_qty": 11, "ck_buy_foil_qty": 5, "csi": 299.99, "csi_foil": 2799.99, "csi_buy": 180.0, "csi_buy_foil": 0.0, "csi_buy_qty": 20, "csi_buy_foil_qty": 0, "ct": 191.37, "ct_foil": 2914.21}, "reserved": true, "multiplePrintings": false, "lastPrint": "Urza's Legacy", "multiverse_ids": [12626], "type": "Artifact", "typeLine": "Artifact", "power": "", "toughness": "", "isCommander": false, "isIn99": true, "percentageOfUse": 100.0, "percentageOfUseByIdentity": 100.0, "avgWinRate": 0.0, "avgDrawRate": 0.0}, {"occurrences": 1, "cardName": "Emergence Zone", "card_faces": [], "colorIdentity": "C", "colors": "C", "decklists": [{"commanders": "The Reality Chip", "decks": [{"name": "Bend Reality", "url": "https://www.moxfield.com/decks/fvuyt4A-FESSlVbF1-l3DQ", "commanders": [{"name": "The Reality Chip", "color_identity": ["U"]}]}], "colorIdentity": ["U"]}], "cmc": 0, "prices": {"usd": 1.55, "usd_foil": 33.4, "eur": 0.5, "eur_foil": 10.34, "tix": 0.03, "ck": 1.99, "ck_foil": 32.99, "lastUpdatedAtUtc": "2024-06-11T10:48:49.438Z", "ck_buy": 0.5, "ck_buy_foil": 16.5, "ck_buy_qty": 88, "ck_buy_foil_qty": 7, "csi": 1.25, "csi_foil": 27.99, "csi_buy": 0.25, "csi_buy_foil": 12.0, "csi_buy_qty": 20, "csi_buy_foil_qty": 20, "ct_foil": 26.23}, "reserved": false, "multiplePrintings": false, "lastPrint": "War of the Spark", "multiverse_ids": [461172], "type": "Land", "typeLine": "Land", "power": "", "toughness": "", "isCommander": false, "isIn99": true, "percentageOfUse": 100.0, "percentageOfUseByIdentity": 100.0, "avgWinRate": 0.0, "avgDrawRate": 0.0}, {"occurrences": 1, "cardName": "Jace, Wielder of Mysteries", "card_faces": [], "colorIdentity": "U", "colors": "U", "decklists": [{"commanders": "The Reality Chip", "decks": [{"name": "Bend Reality", "url": "https://www.moxfield.com/decks/fvuyt4A-FESSlVbF1-l3DQ", "commanders": [{"name": "The Reality Chip", "color_identity": ["U"]}]}], "colorIdentity": ["U"]}], "cmc": 4.0, "prices": {"usd": 4.65, "usd_foil": 44.15, "eur": 5.24, "eur_foil": 58.4, "ck": 5.49, "ck_foil": 79.99, "lastUpdatedAtUtc": "2024-06-11T10:48:49.438Z", "ck_buy": 1.1, "ck_buy_foil": 32.0, "ck_buy_qty": 0, "ck_buy_foil_qty": 0, "csi": 5.99, "csi_foil": 74.99, "csi_buy": 2.5, "csi_buy_foil": 38.0, "csi_buy_qty": 20, "csi_buy_foil_qty": 20}, "reserved": false, "multiplePrintings": false, "lastPrint": "War of the Spark", "multiverse_ids": [0], "type": "Planeswalker", "typeLine": "Legendary Planeswalker — Jace", "power": "", "toughness": "", "isCommander": false, "isIn99": true, "percentageOfUse": 100.0, "percentageOfUseByIdentity": 0.0, "avgWinRate": 0.0, "avgDrawRate": 0.0}, {"occurrences": 1, "cardName": "Karn, the Great Creator", "card_faces": [], "colorIdentity": "C", "colors": "C", "decklists": [{"commanders": "The Reality Chip", "decks": [{"name": "Bend Reality", "url": "https://www.moxfield.com/decks/fvuyt4A-FESSlVbF1-l3DQ", "commanders": [{"name": "The Reality Chip", "color_identity": ["U"]}]}], "colorIdentity": ["U"]}], "cmc": 4.0, "prices": {"usd": 6.92, "usd_foil": 18.76, "eur": 7.02, "eur_foil": 15.62, "tix": 3.25, "ck": 7.49, "ck_foil": 17.99, "lastUpdatedAtUtc": "2024-06-11T10:48:49.438Z", "ck_buy": 3.8, "ck_buy_foil": 10.8, "ck_buy_qty": 39, "ck_buy_foil_qty": 17, "csi": 7.99, "csi_foil": 17.99, "csi_buy": 0.0, "csi_buy_foil": 0.0, "csi_buy_qty": 0, "csi_buy_foil_qty": 0, "ct": 7.08, "ct_foil": 15.76}, "reserved": false, "multiplePrintings": true, "lastPrint": "Bloomburrow Commander", "multiverse_ids": [460928], "type": "Planeswalker", "typeLine": "Legendary Planeswalker — Karn", "power": "", "toughness": "", "isCommander": false, "isIn99": true, "percentageOfUse": 100.0, "percentageOfUseByIdentity": 100.0, "avgWinRate": 0.0, "avgDrawRate": 0.0}, {"occurrences": 1, "cardName": "Force of Negation", "card_faces": [], "colorIdentity": "U", "colors": "U", "decklists": [{"commanders": "The Reality Chip", "decks": [{"name": "Bend Reality", "url": "https://www.moxfield.com/decks/fvuyt4A-FESSlVbF1-l3DQ", "commanders": [{"name": "The Reality Chip", "color_identity": ["U"]}]}], "colorIdentity": ["U"]}], "cmc": 3.0, "prices": {"usd": 37.44, "usd_foil": 52.31, "eur": 40.19, "eur_foil": 61.57, "tix": 9.67, "ck": 42.99, "ck_foil": 59.99, "lastUpdatedAtUtc": "2024-06-11T10:48:49.438Z", "ck_buy": 20.0, "ck_buy_foil": 24.0, "ck_buy_qty": 13, "ck_buy_foil_qty": 0, "csi": 47.99, "csi_foil": 54.99, "csi_buy": 0.0, "csi_buy_foil": 32.0, "csi_buy_qty": 0, "csi_buy_foil_qty": 20, "ct": 40.48, "ct_foil": 67.51}, "reserved": false, "multiplePrintings": true, "lastPrint": "Double Masters 2022", "multiverse_ids": [464001], "type": "Instant", "typeLine": "Instant", "power": "", "toughness": "", "isCommander": false, "isIn99": true, "percentageOfUse": 100.0, "percentageOfUseByIdentity": 0.0, "avgWinRate": 0.0, "avgDrawRate": 0.0}, {"occurrences": 1, "cardName": "Tribute Mage", "card_faces": [], "colorIdentity": "U", "colors": "U", "decklists": [{"commanders": "The Reality Chip", "decks": [{"name": "Bend Reality", "url": "https://www.moxfield.com/decks/fvuyt4A-FESSlVbF1-l3DQ", "commanders": [{"name": "The Reality Chip", "color_identity": ["U"]}]}], "colorIdentity": ["U"]}], "cmc": 3.0, "prices": {"usd": 1.0, "usd_foil": 3.08, "eur": 0.65, "eur_foil": 3.05, "tix": 0.03, "ck": 1.29, "ck_foil": 3.49, "lastUpdatedAtUtc": "2024-06-11T10:48:49.438Z", "ck_buy": 0.52, "ck_buy_foil": 1.4, "ck_buy_qty": 101, "ck_buy_foil_qty": 9, "csi": 0.99, "csi_foil": 3.99, "csi_buy": 0.25, "csi_buy_foil": 1.5, "csi_buy_qty": 20, "csi_buy_foil_qty": 20, "ct": 0.52, "ct_foil": 3.23}, "reserved": false, "multiplePrintings": true, "lastPrint": "Modern Horizons 1 Timeshifts", "multiverse_ids": [464022], "type": "Creature", "typeLine": "Creature — Human Wizard", "power": "2", "toughness": "2", "isCommander": false, "isIn99": true, "percentageOfUse": 100.0, "percentageOfUseByIdentity": 0.0, "avgWinRate": 0.0, "avgDrawRate": 0.0}, {"occurrences": 1, "cardName": "Fierce Guardianship", "card_faces": [], "colorIdentity": "U", "colors": "U", "decklists": [{"commanders": "The Reality Chip", "decks": [{"name": "Bend Reality", "url": "https://www.moxfield.com/decks/fvuyt4A-FESSlVbF1-l3DQ", "commanders": [{"name": "The Reality Chip", "color_identity": ["U"]}]}], "colorIdentity": ["U"]}], "cmc": 3.0, "prices": {"usd": 41.11, "eur": 35.23, "tix": 9.9, "ck": 54.99, "lastUpdatedAtUtc": "2024-06-11T10:48:49.438Z", "ck_buy": 31.0, "ck_buy_qty": 37, "csi": 44.99, "csi_buy": 28.0, "csi_buy_qty": 20, "ct": 42.89}, "reserved": false, "multiplePrintings": true, "lastPrint": "Commander Masters", "multiverse_ids": [484882], "type": "Instant", "typeLine": "Instant", "power": "", "toughness": "", "isCommander": false, "isIn99": true, "percentageOfUse": 100.0, "percentageOfUseByIdentity": 0.0, "avgWinRate": 0.0, "avgDrawRate": 0.0}, {"occurrences": 1, "cardName": "Spellskite", "card_faces": [], "colorIdentity": "U", "colors": "C", "decklists": [{"commanders": "The Reality Chip", "decks": [{"name": "Bend Reality", "url": "https://www.moxfield.com/decks/fvuyt4A-FESSlVbF1-l3DQ", "commanders": [{"name": "The Reality Chip", "color_identity": ["U"]}]}], "colorIdentity": ["U"]}], "cmc": 2.0, "prices": {"usd": 5.29, "usd_foil": 5.61, "eur": 3.32, "eur_foil": 5.42, "tix": 0.22, "ck": 5.49, "ck_foil": 6.99, "lastUpdatedAtUtc": "2024-06-11T10:48:49.438Z", "ck_buy": 2.75, "ck_buy_foil": 3.85, "ck_buy_qty": 26, "ck_buy_foil_qty": 8, "csi": 3.49, "csi_foil": 4.99, "csi_buy": 1.5, "csi_buy_foil": 2.5, "csi_buy_qty": 20, "csi_buy_foil_qty": 20, "ct": 4.39, "ct_foil": 7.49}, "reserved": false, "multiplePrintings": true, "lastPrint": "Commander Legends: Battle for Baldur's Gate", "multiverse_ids": [489962], "type": "Creature", "typeLine": "Artifact Creature — Phyrexian Horror", "power": "0", "toughness": "4", "isCommander": false, "isIn99": true, "percentageOfUse": 100.0, "percentageOfUseByIdentity": 0.0, "avgWinRate": 0.0, "avgDrawRate": 0.0}, {"occurrences": 1, "cardName": "Codex Shredder", "card_faces": [], "colorIdentity": "C", "colors": "C", "decklists": [{"commanders": "The Reality Chip", "decks": [{"name": "Bend Reality", "url": "https://www.moxfield.com/decks/fvuyt4A-FESSlVbF1-l3DQ", "commanders": [{"name": "The Reality Chip", "color_identity": ["U"]}]}], "colorIdentity": ["U"]}], "cmc": 1.0, "prices": {"usd": 0.18, "usd_foil": 3.38, "eur": 0.13, "eur_foil": 2.29, "tix": 0.03, "ck": 0.49, "ck_foil": 3.99, "lastUpdatedAtUtc": "2024-06-11T10:48:49.438Z", "ck_buy": 0.1, "ck_buy_foil": 1.6, "ck_buy_qty": 45, "ck_buy_foil_qty": 10, "csi": 0.25, "csi_foil": 3.99, "csi_buy": 0.0, "csi_buy_foil": 0.0, "csi_buy_qty": 0, "csi_buy_foil_qty": 0, "ct": 0.14, "ct_foil": 1.57}, "reserved": false, "multiplePrintings": true, "lastPrint": "Commander Legends", "multiverse_ids": [253635], "type": "Artifact", "typeLine": "Artifact", "power": "", "toughness": "", "isCommander": false, "isIn99": true, "percentageOfUse": 100.0, "percentageOfUseByIdentity": 100.0, "avgWinRate": 0.0, "avgDrawRate": 0.0}, {"occurrences": 1, "cardName": "Mental Misstep", "card_faces": [], "colorIdentity": "U", "colors": "U", "decklists": [{"commanders": "The Reality Chip", "decks": [{"name": "Bend Reality", "url": "https://www.moxfield.com/decks/fvuyt4A-FESSlVbF1-l3DQ", "commanders": [{"name": "The Reality Chip", "color_identity": ["U"]}]}], "colorIdentity": ["U"]}], "cmc": 1.0, "prices": {"usd": 10.1, "usd_foil": 85.9, "eur": 5.01, "eur_foil": 38.75, "tix": 0.03, "ck": 10.99, "ck_foil": 99.99, "lastUpdatedAtUtc": "2024-06-11T10:48:49.438Z", "ck_buy": 4.6, "ck_buy_foil": 50.0, "ck_buy_qty": 43, "ck_buy_foil_qty": 9, "csi": 5.99, "csi_foil": 99.99, "csi_buy": 3.0, "csi_buy_foil": 50.0, "csi_buy_qty": 20, "csi_buy_foil_qty": 20, "ct": 5.5, "ct_foil": 84.72}, "reserved": false, "multiplePrintings": true, "lastPrint": "2022 Heroes of the Realm", "multiverse_ids": [230066], "type": "Instant", "typeLine": "Instant", "power": "", "toughness": "", "isCommander": false, "isIn99": true, "percentageOfUse": 100.0, "percentageOfUseByIdentity": 0.0, "avgWinRate": 0.0, "avgDrawRate": 0.0}, {"occurrences": 1, "cardName": "Rings of Brighthearth", "card_faces": [], "colorIdentity": "C", "colors": "C", "decklists": [{"commanders": "The Reality Chip", "decks": [{"name": "Bend Reality", "url": "https://www.moxfield.com/decks/fvuyt4A-FESSlVbF1-l3DQ", "commanders": [{"name": "The Reality Chip", "color_identity": ["U"]}]}], "colorIdentity": ["U"]}], "cmc": 3.0, "prices": {"usd": 3.17, "usd_foil": 5.49, "eur": 3.4, "eur_foil": 4.08, "tix": 0.02, "ck": 5.49, "ck_foil": 5.99, "lastUpdatedAtUtc": "2024-06-11T10:48:49.438Z", "ck_buy": 1.85, "ck_buy_foil": 3.0, "ck_buy_qty": 55, "ck_buy_foil_qty": 19, "csi": 3.99, "csi_foil": 4.99, "csi_buy": 2.0, "csi_buy_foil": 2.0, "csi_buy_qty": 20, "csi_buy_foil_qty": 20, "ct": 4.2, "ct_foil": 4.48}, "reserved": false, "multiplePrintings": true, "lastPrint": "Tales of Middle-earth Commander", "multiverse_ids": [497855], "type": "Artifact", "typeLine": "Artifact", "power": "", "toughness": "", "isCommander": false, "isIn99": true, "percentageOfUse": 100.0, "percentageOfUseByIdentity": 100.0, "avgWinRate": 0.0, "avgDrawRate": 0.0}, {"occurrences": 1, "cardName": "Springleaf Drum", "card_faces": [], "colorIdentity": "C", "colors": "C", "decklists": [{"commanders": "The Reality Chip", "decks": [{"name": "Bend Reality", "url": "https://www.moxfield.com/decks/fvuyt4A-FESSlVbF1-l3DQ", "commanders": [{"name": "The Reality Chip", "color_identity": ["U"]}]}], "colorIdentity": ["U"]}], "cmc": 1.0, "prices": {"usd": 0.24, "usd_foil": 0.77, "eur": 0.49, "eur_foil": 0.63, "tix": 0.04, "ck": 0.59, "ck_foil": 0.99, "lastUpdatedAtUtc": "2024-06-11T10:48:49.438Z", "ck_buy": 0.15, "ck_buy_foil": 0.15, "ck_buy_qty": 81, "ck_buy_foil_qty": 0, "csi": 0.35, "csi_foil": 0.99, "csi_buy": 0.0, "csi_buy_foil": 0.0, "csi_buy_qty": 0, "csi_buy_foil_qty": 0, "ct": 0.34, "ct_foil": 0.9}, "reserved": false, "multiplePrintings": true, "lastPrint": "Double Masters", "multiverse_ids": [586605], "type": "Artifact", "typeLine": "Artifact", "power": "", "toughness": "", "isCommander": false, "isIn99": true, "percentageOfUse": 100.0, "percentageOfUseByIdentity": 100.0, "avgWinRate": 0.0, "avgDrawRate": 0.0}, {"occurrences": 1, "cardName": "Pongify", "card_faces": [], "colorIdentity": "U", "colors": "U", "decklists": [{"commanders": "The Reality Chip", "decks": [{"name": "Bend Reality", "url": "https://www.moxfield.com/decks/fvuyt4A-FESSlVbF1-l3DQ", "commanders": [{"name": "The Reality Chip", "color_identity": ["U"]}]}], "colorIdentity": ["U"]}], "cmc": 1.0, "prices": {"eur": 2.44, "ck": 2.79, "ck_foil": 5.99, "lastUpdatedAtUtc": "2024-06-11T10:48:49.438Z", "ck_buy": 0.45, "ck_buy_foil": 2.4, "ck_buy_qty": 0, "ck_buy_foil_qty": 0, "csi": 3.99, "csi_buy": 0.0, "csi_buy_qty": 0, "ct": 2.47, "ct_foil": 7.61}, "reserved": false, "multiplePrintings": true, "lastPrint": "Modern Horizons 3 Commander", "multiverse_ids": [0], "type": "Instant", "typeLine": "Instant", "power": "", "toughness": "", "isCommander": false, "isIn99": true, "percentageOfUse": 100.0, "percentageOfUseByIdentity": 0.0, "avgWinRate": 0.0, "avgDrawRate": 0.0}, {"occurrences": 1, "cardName": "Thought Lash", "card_faces": [], "colorIdentity": "U", "colors": "U", "decklists": [{"commanders": "The Reality Chip", "decks": [{"name": "Bend Reality", "url": "https://www.moxfield.com/decks/fvuyt4A-FESSlVbF1-l3DQ", "commanders": [{"name": "The Reality Chip", "color_identity": ["U"]}]}], "colorIdentity": ["U"]}], "cmc": 4.0, "prices": {"usd": 10.51, "eur": 10.13, "ck": 15.99, "lastUpdatedAtUtc": "2024-06-11T10:48:49.438Z", "ck_buy": 7.25, "ck_buy_qty": 11, "csi": 10.99, "csi_buy": 5.0, "csi_buy_qty": 20, "ct": 12.09}, "reserved": true, "multiplePrintings": false, "lastPrint": "Alliances", "multiverse_ids": [3123], "type": "Enchantment", "typeLine": "Enchantment", "power": "", "toughness": "", "isCommander": false, "isIn99": true, "percentageOfUse": 100.0, "percentageOfUseByIdentity": 0.0, "avgWinRate": 0.0, "avgDrawRate": 0.0}, {"occurrences": 1, "cardName": "Chain of Vapor", "card_faces": [], "colorIdentity": "U", "colors": "U", "decklists": [{"commanders": "The Reality Chip", "decks": [{"name": "Bend Reality", "url": "https://www.moxfield.com/decks/fvuyt4A-FESSlVbF1-l3DQ", "commanders": [{"name": "The Reality Chip", "color_identity": ["U"]}]}], "colorIdentity": ["U"]}], "cmc": 1.0, "prices": {"usd": 12.25, "usd_foil": 218.98, "eur": 4.92, "eur_foil": 93.43, "tix": 0.05, "ck": 15.99, "ck_foil": 249.99, "lastUpdatedAtUtc": "2024-06-11T10:48:49.438Z", "ck_buy": 9.0, "ck_buy_foil": 125.0, "ck_buy_qty": 40, "ck_buy_foil_qty": 3, "csi": 12.99, "csi_foil": 149.99, "csi_buy": 6.0, "csi_buy_foil": 0.0, "csi_buy_qty": 20, "csi_buy_foil_qty": 0, "ct": 8.23, "ct_foil": 194.77}, "reserved": false, "multiplePrintings": true, "lastPrint": "Commander 2016", "multiverse_ids": [12447], "type": "Instant", "typeLine": "Instant", "power": "", "toughness": "", "isCommander": false, "isIn99": true, "percentageOfUse": 100.0, "percentageOfUseByIdentity": 0.0, "avgWinRate": 0.0, "avgDrawRate": 0.0}, {"occurrences": 1, "cardName": "Gemstone Caverns", "card_faces": [], "colorIdentity": "C", "colors": "C", "decklists": [{"commanders": "The Reality Chip", "decks": [{"name": "Bend Reality", "url": "https://www.moxfield.com/decks/fvuyt4A-FESSlVbF1-l3DQ", "commanders": [{"name": "The Reality Chip", "color_identity": ["U"]}]}], "colorIdentity": ["U"]}], "cmc": 0, "prices": {"usd": 47.07, "eur": 34.3, "ck": 57.99, "lastUpdatedAtUtc": "2024-06-11T10:48:49.438Z", "ck_buy": 35.0, "csi": 57.99, "csi_buy": 35.0, "ct": 50.02}, "reserved": false, "multiplePrintings": true, "lastPrint": "Tales of Middle-earth Commander", "multiverse_ids": [0], "type": "Land", "typeLine": "Legendary Land", "power": "", "toughness": "", "isCommander": false, "isIn99": true, "percentageOfUse": 100.0, "percentageOfUseByIdentity": 100.0, "avgWinRate": 0.0, "avgDrawRate": 0.0}, {"occurrences": 1, "cardName": "Mindbreak Trap", "card_faces": [], "colorIdentity": "U", "colors": "U", "decklists": [{"commanders": "The Reality Chip", "decks": [{"name": "Bend Reality", "url": "https://www.moxfield.com/decks/fvuyt4A-FESSlVbF1-l3DQ", "commanders": [{"name": "The Reality Chip", "color_identity": ["U"]}]}], "colorIdentity": ["U"]}], "cmc": 4.0, "prices": {"usd": 12.92, "usd_foil": 25.85, "tix": 0.62, "ck": 11.99, "ck_foil": 44.99, "lastUpdatedAtUtc": "2024-06-11T10:48:49.438Z", "ck_buy": 5.0, "ck_buy_foil": 18.0, "ck_buy_qty": 82, "ck_buy_foil_qty": 0, "csi": 17.99, "csi_foil": 39.99, "csi_buy": 4.5, "csi_buy_foil": 0.0, "csi_buy_qty": 20, "csi_buy_foil_qty": 0, "ct": 12.14, "ct_foil": 23.01}, "reserved": false, "multiplePrintings": false, "lastPrint": "Zendikar", "multiverse_ids": [657757], "type": "Instant", "typeLine": "Instant — Trap", "power": "", "toughness": "", "isCommander": false, "isIn99": true, "percentageOfUse": 100.0, "percentageOfUseByIdentity": 0.0, "avgWinRate": 0.0, "avgDrawRate": 0.0}, {"occurrences": 1, "cardName": "Jeweled Lotus", "card_faces": [], "colorIdentity": "C", "colors": "C", "decklists": [{"commanders": "The Reality Chip", "decks": [{"name": "Bend Reality", "url": "https://www.moxfield.com/decks/fvuyt4A-FESSlVbF1-l3DQ", "commanders": [{"name": "The Reality Chip", "color_identity": ["U"]}]}], "colorIdentity": ["U"]}], "cmc": 0, "prices": {"usd": 97.5, "usd_foil": 114.65, "eur": 86.71, "eur_foil": 99.09, "tix": 19.04, "ck": 119.99, "ck_foil": 149.99, "lastUpdatedAtUtc": "2024-06-11T10:48:49.438Z", "ck_buy": 70.0, "ck_buy_foil": 60.0, "ck_buy_qty": 27, "ck_buy_foil_qty": 0, "csi": 109.99, "csi_foil": 119.99, "csi_buy": 60.0, "csi_buy_foil": 65.0, "csi_buy_qty": 20, "csi_buy_foil_qty": 20, "ct": 97.76, "ct_foil": 122.05}, "reserved": false, "multiplePrintings": true, "lastPrint": "Commander Masters", "multiverse_ids": [497839], "type": "Artifact", "typeLine": "Artifact", "power": "", "toughness": "", "isCommander": false, "isIn99": true, "percentageOfUse": 100.0, "percentageOfUseByIdentity": 100.0, "avgWinRate": 0.0, "avgDrawRate": 0.0}, {"occurrences": 1, "cardName": "Urza's Saga", "card_faces": [], "colorIdentity": "C", "colors": "C", "decklists": [{"commanders": "The Reality Chip", "decks": [{"name": "Bend Reality", "url": "https://www.moxfield.com/decks/fvuyt4A-FESSlVbF1-l3DQ", "commanders": [{"name": "The Reality Chip", "color_identity": ["U"]}]}], "colorIdentity": ["U"]}], "cmc": 0, "prices": {"usd": 36.53, "usd_foil": 68.69, "eur": 42.72, "eur_foil": 70.38, "tix": 22.86, "ck": 49.99, "ck_foil": 94.99, "lastUpdatedAtUtc": "2024-06-11T10:48:49.438Z", "ck_buy": 30.0, "ck_buy_foil": 47.5, "ck_buy_qty": 77, "ck_buy_foil_qty": 11, "csi": 44.99, "csi_foil": 74.99, "csi_buy": 28.0, "csi_buy_foil": 0.0, "csi_buy_qty": 20, "csi_buy_foil_qty": 0, "ct": 46.07, "ct_foil": 69.83}, "reserved": false, "multiplePrintings": true, "lastPrint": "Modern Horizons 2 Timeshifts", "multiverse_ids": [522335], "type": "Land", "typeLine": "Enchantment Land — Urza's Saga", "power": "", "toughness": "", "isCommander": false, "isIn99": true, "percentageOfUse": 100.0, "percentageOfUseByIdentity": 100.0, "avgWinRate": 0.0, "avgDrawRate": 0.0}, {"occurrences": 1, "cardName": "Alchemist's Retrieval", "card_faces": [], "colorIdentity": "U", "colors": "U", "decklists": [{"commanders": "The Reality Chip", "decks": [{"name": "Bend Reality", "url": "https://www.moxfield.com/decks/fvuyt4A-FESSlVbF1-l3DQ", "commanders": [{"name": "The Reality Chip", "color_identity": ["U"]}]}], "colorIdentity": ["U"]}], "cmc": 1.0, "prices": {"usd": 0.1, "usd_foil": 0.31, "eur": 0.1, "eur_foil": 0.2, "tix": 0.03, "ck": 0.35, "ck_foil": 0.59, "lastUpdatedAtUtc": "2024-06-11T10:48:49.438Z", "ck_buy": 0.03, "ck_buy_foil": 0.09, "csi": 0.49, "csi_foil": 0.25, "csi_buy": 0.0, "csi_buy_foil": 0.0, "ct": 0.1, "ct_foil": 0.14}, "reserved": false, "multiplePrintings": false, "lastPrint": "Innistrad: Crimson Vow", "multiverse_ids": [540883], "type": "Instant", "typeLine": "Instant", "power": "", "toughness": "", "isCommander": false, "isIn99": true, "percentageOfUse": 100.0, "percentageOfUseByIdentity": 0.0, "avgWinRate": 0.0, "avgDrawRate": 0.0}, {"occurrences": 1, "cardName": "Otawara, Soaring City", "card_faces": [], "colorIdentity": "U", "colors": "C", "decklists": [{"commanders": "The Reality Chip", "decks": [{"name": "Bend Reality", "url": "https://www.moxfield.com/decks/fvuyt4A-FESSlVbF1-l3DQ", "commanders": [{"name": "The Reality Chip", "color_identity": ["U"]}]}], "colorIdentity": ["U"]}], "cmc": 0, "prices": {"usd": 18.87, "usd_foil": 22.35, "eur": 20.49, "eur_foil": 21.02, "tix": 9.48, "ck": 23.99, "ck_foil": 29.99, "lastUpdatedAtUtc": "2024-06-11T10:48:49.438Z", "ck_buy": 12.0, "ck_buy_foil": 12.0, "csi": 24.99, "csi_foil": 27.99, "csi_buy": 14.0, "csi_buy_foil": 14.0, "ct": 19.94, "ct_foil": 24.72}, "reserved": false, "multiplePrintings": false, "lastPrint": "Kamigawa: Neon Dynasty", "multiverse_ids": [548584], "type": "Land", "typeLine": "Legendary Land", "power": "", "toughness": "", "isCommander": false, "isIn99": true, "percentageOfUse": 100.0, "percentageOfUseByIdentity": 0.0, "avgWinRate": 0.0, "avgDrawRate": 0.0}, {"occurrences": 1, "cardName": "March of Swirling Mist", "card_faces": [], "colorIdentity": "U", "colors": "U", "decklists": [{"commanders": "The Reality Chip", "decks": [{"name": "Bend Reality", "url": "https://www.moxfield.com/decks/fvuyt4A-FESSlVbF1-l3DQ", "commanders": [{"name": "The Reality Chip", "color_identity": ["U"]}]}], "colorIdentity": ["U"]}], "cmc": 1.0, "prices": {"usd": 3.11, "usd_foil": 2.71, "eur": 3.16, "eur_foil": 3.48, "tix": 0.35, "ck": 4.49, "ck_foil": 6.99, "lastUpdatedAtUtc": "2024-06-11T10:48:49.438Z", "ck_buy": 1.8, "ck_buy_foil": 2.8, "csi": 4.99, "csi_foil": 5.99, "csi_buy": 0.0, "csi_buy_foil": 0.0, "ct": 2.87, "ct_foil": 3.03}, "reserved": false, "multiplePrintings": false, "lastPrint": "Kamigawa: Neon Dynasty", "multiverse_ids": [548358], "type": "Instant", "typeLine": "Instant", "power": "", "toughness": "", "isCommander": false, "isIn99": true, "percentageOfUse": 100.0, "percentageOfUseByIdentity": 0.0, "avgWinRate": 0.0, "avgDrawRate": 0.0}, {"occurrences": 1, "cardName": "Ledger Shredder", "card_faces": [], "colorIdentity": "U", "colors": "U", "decklists": [{"commanders": "The Reality Chip", "decks": [{"name": "Bend Reality", "url": "https://www.moxfield.com/decks/fvuyt4A-FESSlVbF1-l3DQ", "commanders": [{"name": "The Reality Chip", "color_identity": ["U"]}]}], "colorIdentity": ["U"]}], "cmc": 2.0, "prices": {"usd": 12.11, "usd_foil": 20.0, "eur": 16.34, "eur_foil": 17.37, "ck": 18.99, "ck_foil": 17.99, "lastUpdatedAtUtc": "2024-06-11T10:48:49.438Z", "ck_buy": 8.75, "ck_buy_foil": 9.0, "ck_buy_qty": 20, "ck_buy_foil_qty": 5, "csi": 17.99, "csi_foil": 19.99, "csi_buy": 10.0, "csi_buy_foil": 10.0, "csi_buy_qty": 20, "csi_buy_foil_qty": 20, "ct": 14.31, "ct_foil": 20.39}, "reserved": false, "multiplePrintings": false, "lastPrint": "Streets of New Capenna", "multiverse_ids": [558250], "type": "Creature", "typeLine": "Creature — Bird Advisor", "power": "1", "toughness": "3", "isCommander": false, "isIn99": true, "percentageOfUse": 100.0, "percentageOfUseByIdentity": 0.0, "avgWinRate": 0.0, "avgDrawRate": 0.0}, {"occurrences": 1, "cardName": "An Offer You Can't Refuse", "card_faces": [], "colorIdentity": "U", "colors": "U", "decklists": [{"commanders": "The Reality Chip", "decks": [{"name": "Bend Reality", "url": "https://www.moxfield.com/decks/fvuyt4A-FESSlVbF1-l3DQ", "commanders": [{"name": "The Reality Chip", "color_identity": ["U"]}]}], "colorIdentity": ["U"]}], "cmc": 1.0, "prices": {"usd": 3.8, "usd_foil": 4.57, "eur": 3.19, "eur_foil": 3.97, "tix": 0.01, "ck": 6.99, "ck_foil": 7.99, "lastUpdatedAtUtc": "2024-06-11T10:48:49.438Z", "ck_buy": 3.0, "ck_buy_foil": 3.2, "csi": 3.99, "csi_foil": 3.99, "csi_buy": 1.5, "csi_buy_foil": 1.5, "ct_foil": 3.59}, "reserved": false, "multiplePrintings": true, "lastPrint": "Bloomburrow Commander", "multiverse_ids": [555252], "type": "Instant", "typeLine": "Instant", "power": "", "toughness": "", "isCommander": false, "isIn99": true, "percentageOfUse": 100.0, "percentageOfUseByIdentity": 0.0, "avgWinRate": 0.0, "avgDrawRate": 0.0}, {"occurrences": 1, "cardName": "Faerie Mastermind", "card_faces": [], "colorIdentity": "U", "colors": "U", "decklists": [{"commanders": "The Reality Chip", "decks": [{"name": "Bend Reality", "url": "https://www.moxfield.com/decks/fvuyt4A-FESSlVbF1-l3DQ", "commanders": [{"name": "The Reality Chip", "color_identity": ["U"]}]}], "colorIdentity": ["U"]}], "cmc": 2.0, "prices": {"usd": 8.34, "usd_foil": 10.26, "eur": 8.54, "eur_foil": 8.83, "tix": 0.41, "ck": 12.99, "ck_foil": 14.99, "lastUpdatedAtUtc": "2024-06-11T10:48:49.438Z", "ck_buy": 6.5, "ck_buy_foil": 6.0, "ck_buy_qty": 58, "ck_buy_foil_qty": 0, "csi": 12.99, "csi_foil": 12.99, "csi_buy": 5.0, "csi_buy_foil": 7.0, "csi_buy_qty": 20, "csi_buy_foil_qty": 20, "ct": 8.51, "ct_foil": 11.27}, "reserved": false, "multiplePrintings": false, "lastPrint": "March of the Machine", "multiverse_ids": [607079], "type": "Creature", "typeLine": "Creature — Faerie Rogue", "power": "2", "toughness": "1", "isCommander": false, "isIn99": true, "percentageOfUse": 100.0, "percentageOfUseByIdentity": 0.0, "avgWinRate": 0.0, "avgDrawRate": 0.0}, {"occurrences": 1, "cardName": "The One Ring", "card_faces": [], "colorIdentity": "C", "colors": "C", "decklists": [{"commanders": "The Reality Chip", "decks": [{"name": "Bend Reality", "url": "https://www.moxfield.com/decks/fvuyt4A-FESSlVbF1-l3DQ", "commanders": [{"name": "The Reality Chip", "color_identity": ["U"]}]}], "colorIdentity": ["U"]}], "cmc": 4.0, "prices": {"usd": 64.08, "usd_foil": 67.74, "eur": 72.11, "eur_foil": 68.63, "tix": 42.24, "ck": 94.99, "ck_foil": 79.99, "lastUpdatedAtUtc": "2024-06-11T10:48:49.438Z", "ck_buy": 62.0, "ck_buy_foil": 40.0, "ck_buy_qty": 16, "ck_buy_foil_qty": 50, "csi": 64.99, "csi_foil": 59.99, "csi_buy": 40.0, "csi_buy_foil": 0.0, "csi_buy_qty": 20, "csi_buy_foil_qty": 0, "ct": 76.24, "ct_foil": 81.2}, "reserved": false, "multiplePrintings": false, "lastPrint": "The Lord of the Rings: Tales of Middle-earth", "multiverse_ids": [619130], "type": "Artifact", "typeLine": "Legendary Artifact", "power": "", "toughness": "", "isCommander": false, "isIn99": true, "percentageOfUse": 100.0, "percentageOfUseByIdentity": 100.0, "avgWinRate": 0.0, "avgDrawRate": 0.0}, {"occurrences": 1, "cardName": "Forensic Gadgeteer", "card_faces": [], "colorIdentity": "U", "colors": "U", "decklists": [{"commanders": "The Reality Chip", "decks": [{"name": "Bend Reality", "url": "https://www.moxfield.com/decks/fvuyt4A-FESSlVbF1-l3DQ", "commanders": [{"name": "The Reality Chip", "color_identity": ["U"]}]}], "colorIdentity": ["U"]}], "cmc": 3.0, "prices": {"usd": 2.62, "usd_foil": 2.69, "eur": 1.99, "eur_foil": 2.69, "tix": 0.03, "ck": 3.49, "ck_foil": 2.99, "lastUpdatedAtUtc": "2024-06-11T10:48:49.438Z", "ck_buy": 1.3, "ck_buy_foil": 0.9, "ck_buy_qty": 85, "ck_buy_foil_qty": 23, "csi": 2.99, "csi_foil": 3.99, "csi_buy": 0.75, "csi_buy_foil": 0.0, "csi_buy_qty": 20, "csi_buy_foil_qty": 0, "ct": 2.11, "ct_foil": 2.3}, "reserved": false, "multiplePrintings": false, "lastPrint": "Murders at Karlov Manor", "multiverse_ids": [646619], "type": "Creature", "typeLine": "Creature — Vedalken Artificer Detective", "power": "2", "toughness": "3", "isCommander": false, "isIn99": true, "percentageOfUse": 100.0, "percentageOfUseByIdentity": 0.0, "avgWinRate": 0.0, "avgDrawRate": 0.0}, {"occurrences": 1, "cardName": "The Reality Chip", "card_faces": [], "colorIdentity": "U", "colors": "U", "decklists": [{"commanders": "The Reality Chip", "decks": [{"name": "Bend Reality", "url": "https://www.moxfield.com/decks/fvuyt4A-FESSlVbF1-l3DQ", "commanders": [{"name": "The Reality Chip", "color_identity": ["U"]}]}], "colorIdentity": ["U"]}], "cmc": 2.0, "prices": {"usd": 3.0, "usd_foil": 3.55, "eur": 1.87, "eur_foil": 1.87, "tix": 0.01, "ck": 4.49, "ck_foil": 3.49, "lastUpdatedAtUtc": "2024-06-11T10:48:49.438Z", "ck_buy": 0.9, "ck_buy_foil": 1.4, "ck_buy_qty": 28, "ck_buy_foil_qty": 17, "csi": 2.49, "csi_foil": 2.99, "csi_buy": 1.0, "csi_buy_foil": 0.0, "csi_buy_qty": 20, "csi_buy_foil_qty": 0, "ct": 2.27, "ct_foil": 2.43}, "reserved": false, "multiplePrintings": false, "lastPrint": "Kamigawa: Neon Dynasty", "multiverse_ids": [548372], "type": "Creature", "typeLine": "Legendary Artifact Creature — Equipment Jellyfish", "power": "0", "toughness": "4", "isCommander": true, "isIn99": false, "percentageOfUse": 100.0, "percentageOfUseByIdentity": 0.0, "avgWinRate": 0.0, "avgDrawRate": 0.0}]